[{"gpt-4-1106-preview_direct_sole-planning_results": "Travel Plan:\n\nDay 1: March 11, 2022\nCurrent City: from Indianapolis to Grand Junction\nTransportation: Self-driving, Duration: 19 hours 23 mins, Distance: 2,132 km, Cost: $106\nBreakfast: -\nAttraction: -\nLunch: -\nDinner: -\nAccommodation: NYC Apartment near Central Park!, Grand Junction, Price: $1118, Room Type: Entire home/apt, Pet-friendly: Yes (assuming based on the absence of a \"No pets\" house rule)\n\nDay 2: March 12, 2022\nCurrent City: Grand Junction\nTransportation: -\nBreakfast: -\nAttraction: Museum of the West, Museums of Western Colorado, Grand Junction\nLunch: Austin's BBQ and Oyster Bar, Grand Junction, Average Cost: $15, Cuisines: Tea, Bakery, Fast Food, Indian, Seafood\nDinner: Punjab Da Pind, Grand Junction, Average Cost: $52, Cuisines: Desserts, Pizza, Bakery, Chinese, Mediterranean, Seafood\nAccommodation: NYC Apartment near Central Park!, Grand Junction, Price: $1118, Room Type: Entire home/apt, Pet-friendly: Yes\n\nDay 3: March 13, 2022\nCurrent City: from Grand Junction to Alamosa\nTransportation: Self-driving, Duration: 4 hours 37 mins, Distance: 397 km, Cost: $19\nBreakfast: -\nAttraction: Eureka! McConnell Science Museum, Grand Junction\nLunch: 2 Dog, Grand Junction, Average Cost: $29, Cuisines: Desserts, BBQ, Fast Food, Cafe, American\nDinner: -\nAccommodation: Comfortable studio suite in midtown Manhattan, Alamosa, Price: $67, Room Type: Entire home/apt, Pet-friendly: Yes (assuming based on the absence of a \"No pets\" house rule)\n\nDay 4: March 14, 2022\nCurrent City: Alamosa\nTransportation: -\nBreakfast: -\nAttraction: San Luis Valley Museum | Alamosa\nLunch: Riverwalk Cafe, Alamosa, Average Cost: $97, Cuisines: Tea, Pizza, Fast Food\nDinner: Street Foods by Punjab Grill, Alamosa, Average Cost: $55, Cuisines: Pizza, BBQ, Fast Food, Chinese, Mediterranean\nAccommodation: Comfortable studio suite in midtown Manhattan, Alamosa, Price: $67, Room Type: Entire home/apt, Pet-friendly: Yes\n\nDay 5: March 15, 2022\nCurrent City: from Alamosa to Denver\nTransportation: Flight Number: F3837896, from Alamosa to Denver, Departure Time: 18:06, Arrival Time: 18:57, Price: $57\nBreakfast: -\nAttraction: Cole Park, Alamosa\nLunch: Cafe LazyMojo, Alamosa, Average Cost: $26, Cuisines: Tea, Pizza, American, Fast Food\nDinner: -\nAccommodation: Harlem cozy nights, Denver, Price: $457, Room Type: Entire home/apt, Pet-friendly: Yes (assuming based on the absence of a \"No pets\" house rule)\n\nDay 6: March 16, 2022\nCurrent City: Denver\nTransportation: -\nBreakfast: -\nAttraction: Denver Zoo; Denver Botanic Gardens\nLunch: The Urban Socialite, Denver, Average Cost: $34, Cuisines: Cafe, Indian, Desserts, Italian\nDinner: Woods Spice, Denver, Average Cost: $69, Cuisines: Tea, Cafe, Mexican, Desserts\nAccommodation: Harlem cozy nights, Denver, Price: $457, Room Type: Entire home/apt, Pet-friendly: Yes\n\nDay 7: March 17, 2022\nCurrent City: from Denver to Indianapolis\nTransportation: Flight Number: F3910546, from Denver to Indianapolis, Departure Time: 17:33, Arrival Time: 21:46, Price: $462\nBreakfast: -\nAttraction: Denver Art Museum, Denver\nLunch: Kloof Street House, Denver, Average Cost: $53, Cuisines: Pizza, Bakery, BBQ, Fast Food, Mediterranean\nDinner: -\nAccommodation: -\n\nPlease note that the provided information does not include specific pet-friendly accommodations or the exact cuisine types for each restaurant. The assumption is made based on the absence of \"No pets\" in the house rules for accommodations. The total cost of transportation and accommodations is estimated and may vary. Additional costs for meals, attractions, and other expenses should be considered within the budget.", "gpt-4-1106-preview_direct_sole-planning_parsed_results": [{"day": 1, "current_city": "from Indianapolis to Grand Junction", "transportation": "Self-driving, Duration: 19 hours 23 mins, Distance: 2132 km, Cost: 106", "breakfast": "-", "attraction": "-", "lunch": "-", "dinner": "-", "accommodation": "NYC Apartment near Central Park!, Grand Junction"}, {"day": 2, "current_city": "Grand Junction", "transportation": "-", "breakfast": "-", "attraction": "Museum of the West, Museums of Western Colorado, Grand Junction", "lunch": "Austin's BBQ and Oyster Bar, Grand Junction", "dinner": "Punjab Da Pind, Grand Junction", "accommodation": "NYC Apartment near Central Park!, Grand Junction"}, {"day": 3, "current_city": "from Grand Junction to Alamosa", "transportation": "Self-driving, Duration: 4 hours 37 mins, Distance: 397 km, Cost: 19", "breakfast": "-", "attraction": "Eureka! McConnell Science Museum, Grand Junction", "lunch": "2 Dog, Grand Junction", "dinner": "-", "accommodation": "Comfortable studio suite in midtown Manhattan, Alamosa"}, {"day": 4, "current_city": "Alamosa", "transportation": "-", "breakfast": "-", "attraction": "San Luis Valley Museum, Alamosa", "lunch": "Riverwalk Cafe, Alamosa", "dinner": "Street Foods by Punjab Grill, Alamosa", "accommodation": "Comfortable studio suite in midtown Manhattan, Alamosa"}, {"day": 5, "current_city": "from Alamosa to Denver", "transportation": "Flight Number: F3837896, from Alamosa to Denver, Departure Time: 18:06, Arrival Time: 18:57, Cost: 57", "breakfast": "-", "attraction": "Cole Park, Alamosa", "lunch": "Cafe LazyMojo, Alamosa", "dinner": "-", "accommodation": "Harlem cozy nights, Denver"}, {"day": 6, "current_city": "Denver", "transportation": "-", "breakfast": "-", "attraction": "Denver Zoo, Denver;Denver Botanic Gardens, Denver", "lunch": "The Urban Socialite, Denver", "dinner": "Woods Spice, Denver", "accommodation": "Harlem cozy nights, Denver"}, {"day": 7, "current_city": "from Denver to Indianapolis", "transportation": "Flight Number: F3910546, from Denver to Indianapolis, Departure Time: 17:33, Arrival Time: 21:46, Cost: 462", "breakfast": "-", "attraction": "Denver Art Museum, Denver", "lunch": "Kloof Street House, Denver", "dinner": "-", "accommodation": "-"}]}]