[{"gpt-4-1106-preview_direct_sole-planning_results": "Travel Plan:\n\nDay 1: March 12, 2022\nCurrent City: from Oakland to Portland\nTransportation: Flight Number: F3860996, from Oakland to Portland, Departure Time: 13:26, Arrival Time: 14:50\nLunch: Osaka, Portland (Italian and Mediterranean options available)\nAttraction: Portland Art Museum, Portland\nDinner: Cactus Flower Cafe Navarre, Portland (Italian and Mediterranean options available)\nAccommodation: The ocean view room size 12x14, Portland\n\nDay 2: March 13, 2022\nCurrent City: Portland\nTransportation: -\nBreakfast: -\nAttraction: International Rose Test Garden, Portland\nLunch: Barbeque Nation, Portland (Mediterranean options available)\nAttraction: Oregon Zoo, Portland\nDinner: Nacho Mamas Burritos, Portland (Italian options available)\nAccommodation: The ocean view room size 12x14, Portland\n\nDay 3: March 14, 2022\nCurrent City: from Portland to Medford\nTransportation: Flight Number: F3861509, from Portland to Medford, Departure Time: 16:10, Arrival Time: 17:12\nBreakfast: -\nAttraction: Washington Park, Portland\nLunch: Big Chill, Portland (Italian and Mediterranean options available)\nDinner: Monarch Restaurant - Holiday Inn Jaipur City Centre, Medford (Mediterranean options available)\nAccommodation: The Fountain House, Medford\n\nDay 4: March 15, 2022\nCurrent City: Medford\nTransportation: -\nBreakfast: -\nAttraction: Medford Railroad Park, Medford\nLunch: Exotica, Medford (Mediterranean options available)\nAttraction: RoxyAnn Winery, Medford\nDinner: NIU by Vikings, Medford (Italian options available)\nAccommodation: The Fountain House, Medford\n\nDay 5: March 16, 2022\nCurrent City: from Medford to Eugene\nTransportation: Self-driving, duration: 2 hours 40 mins, cost: $13\nBreakfast: -\nAttraction: Crater Lake National Park Trust, Medford\nLunch: Tandooriwala, Medford (Mediterranean options available)\nDinner: Ammu's South Indian Restaurant, Eugene (Mediterranean options available)\nAccommodation: Perfect Vacation Rental for Family, Eugene\n\nDay 6: March 17, 2022\nCurrent City: Eugene\nTransportation: -\nBreakfast: -\nAttraction: Cascades Raptor Center, Eugene\nLunch: Upper Crust, Eugene (Italian and Mediterranean options available)\nAttraction: Hendricks Park, Eugene\nDinner: Moti Mahal, Eugene (Mediterranean options available)\nAccommodation: Perfect Vacation Rental for Family, Eugene\n\nDay 7: March 18, 2022\nCurrent City: from Eugene to Oakland\nTransportation: Flight Number: F4027025, from Eugene to Oakland, Departure Time: 17:20, Arrival Time: 18:42\nBreakfast: -\nAttraction: Eugene Science Center, Eugene\nLunch: Tea Lounge - Eros Hotel, Eugene (Mediterranean options available)\nDinner: -\nAccommodation: -\n\nPlease note that the budget for flights, accommodations, and meals should be monitored to ensure it does not exceed the total budget of $4,500. Attractions and meals were selected based on the preference for Italian and Mediterranean cuisines. Breakfast details were not provided due to the lack of specific restaurant information for breakfast options.", "gpt-4-1106-preview_direct_sole-planning_parsed_results": [{"day": 1, "current_city": "from Oakland to Portland", "transportation": "Flight Number: F3860996, from Oakland to Portland, Departure Time: 13:26, Arrival Time: 14:50", "breakfast": "-", "attraction": "Portland Art Museum, Portland;", "lunch": "Osaka, Portland", "dinner": "Cactus Flower Cafe Navarre, Portland", "accommodation": "The ocean view room size 12x14, Portland"}, {"day": 2, "current_city": "Portland", "transportation": "-", "breakfast": "-", "attraction": "International Rose Test Garden, Portland;Oregon Zoo, Portland;", "lunch": "Barbeque Nation, Portland", "dinner": "Nacho Mamas Burritos, Portland", "accommodation": "The ocean view room size 12x14, Portland"}, {"day": 3, "current_city": "from Portland to Medford", "transportation": "Flight Number: F3861509, from Portland to Medford, Departure Time: 16:10, Arrival Time: 17:12", "breakfast": "-", "attraction": "Washington Park, Portland;", "lunch": "Big Chill, Portland", "dinner": "Monarch Restaurant - Holiday Inn Jaipur City Centre, Medford", "accommodation": "The Fountain House, Medford"}, {"day": 4, "current_city": "Medford", "transportation": "-", "breakfast": "-", "attraction": "Medford Railroad Park, Medford;RoxyAnn Winery, Medford;", "lunch": "Exotica, Medford", "dinner": "NIU by Vikings, Medford", "accommodation": "The Fountain House, Medford"}, {"day": 5, "current_city": "from Medford to Eugene", "transportation": "Self-driving, duration: 2 hours 40 mins, Cost: 13", "breakfast": "-", "attraction": "Crater Lake National Park Trust, Medford;", "lunch": "Tandooriwala, Medford", "dinner": "Ammu's South Indian Restaurant, Eugene", "accommodation": "Perfect Vacation Rental for Family, Eugene"}, {"day": 6, "current_city": "Eugene", "transportation": "-", "breakfast": "-", "attraction": "Cascades Raptor Center, Eugene;Hendricks Park, Eugene;", "lunch": "Upper Crust, Eugene", "dinner": "Moti Mahal, Eugene", "accommodation": "Perfect Vacation Rental for Family, Eugene"}, {"day": 7, "current_city": "from Eugene to Oakland", "transportation": "Flight Number: F4027025, from Eugene to Oakland, Departure Time: 17:20, Arrival Time: 18:42", "breakfast": "-", "attraction": "Eugene Science Center, Eugene;", "lunch": "Tea Lounge - Eros Hotel, Eugene", "dinner": "-", "accommodation": "-"}]}]