[{"gpt-4-1106-preview_direct_sole-planning_results": "Travel Plan:\n\nDay 1: March 23, 2022\nCurrent City: from Houston to Salt Lake City\nTransportation: Flight Number: F3495303, from Houston to Salt Lake City, Departure Time: 06:01, Arrival Time: 07:56\nBreakfast: -\nAttraction: Liberty Park, Salt Lake City\nLunch: Sushi Loko, Salt Lake City\nDinner: Balada Mix, Salt Lake City\nAccommodation: Cozy apartment in Noho/ Soho, Salt Lake City\n\nDay 2: March 24, 2022\nCurrent City: Salt Lake City\nTransportation: -\nBreakfast: Makers & Bakers, Salt Lake City\nAttraction: Natural History Museum of Utah, Salt Lake City; Utah State Capitol, Salt Lake City\nLunch: Tikka Tonight, Salt Lake City\nDinner: Mainland China, Salt Lake City\nAccommodation: Cozy apartment in Noho/ Soho, Salt Lake City\n\nDay 3: March 25, 2022\nCurrent City: from Salt Lake City to Moab\nTransportation: Flight Number: F3809091, from Salt Lake City to Moab, Departure Time: 17:13, Arrival Time: 18:16\nBreakfast: Joey's Pizza, Salt Lake City\nAttraction: Temple Square, Salt Lake City\nLunch: Shree Rathnam, Salt Lake City\nDinner: -\nAccommodation: COZY COOL ROOM IN MANHATTAN APT / Manhattan, Moab\n\nDay 4: March 26, 2022\nCurrent City: Moab\nTransportation: -\nBreakfast: Cafe Hydro, Moab\nAttraction: Arches National Park, Moab; Dead Horse Point State Park, Moab\nLunch: Spice Kraft, Moab\nDinner: Mangosteen Cafe, Moab\nAccommodation: COZY COOL ROOM IN MANHATTAN APT / Manhattan, Moab\n\nDay 5: March 27, 2022\nCurrent City: from Moab to Vernal\nTransportation: Self-driving, from Moab to Vernal, duration: 3 hours 40 mins, distance: 349 km, cost: 17\nBreakfast: -\nAttraction: Moab Museum, Moab\nLunch: Sufiya Hotel, Moab\nDinner: -\nAccommodation: Luxurious & Spacious 1 Bedroom Apt, Vernal\n\nDay 6: March 28, 2022\nCurrent City: Vernal\nTransportation: -\nBreakfast: Republic of Chicken, Vernal\nAttraction: Utah Field House of Natural History State Park Museum, Vernal; Steinaker State Park, Vernal\nLunch: Pepper Sprout Incorporated, Vernal\nDinner: Prost Brew Pub, Vernal\nAccommodation: Luxurious & Spacious 1 Bedroom Apt, Vernal\n\nDay 7: March 29, 2022\nCurrent City: from Vernal to Houston\nTransportation: Self-driving, from Vernal to Houston, duration: 20 hours 31 mins, distance: 2,167 km, cost: 108\nBreakfast: -\nAttraction: -\nLunch: -\nDinner: -\nAccommodation: -", "gpt-4-1106-preview_direct_sole-planning_parsed_results": [{"day": 1, "current_city": "from Houston to Salt Lake City", "transportation": "Flight Number: F3495303, from Houston to Salt Lake City, Departure Time: 06:01, Arrival Time: 07:56", "breakfast": "-", "attraction": "Liberty Park, Salt Lake City;", "lunch": "Sushi Loko, Salt Lake City", "dinner": "Balada Mix, Salt Lake City", "accommodation": "Cozy apartment in Noho/ Soho, Salt Lake City"}, {"day": 2, "current_city": "Salt Lake City", "transportation": "-", "breakfast": "Makers & Bakers, Salt Lake City", "attraction": "Natural History Museum of Utah, Salt Lake City;Utah State Capitol, Salt Lake City;", "lunch": "Tikka Tonight, Salt Lake City", "dinner": "Mainland China, Salt Lake City", "accommodation": "Cozy apartment in Noho/ Soho, Salt Lake City"}, {"day": 3, "current_city": "from Salt Lake City to Moab", "transportation": "Flight Number: F3809091, from Salt Lake City to Moab, Departure Time: 17:13, Arrival Time: 18:16", "breakfast": "Joey's Pizza, Salt Lake City", "attraction": "Temple Square, Salt Lake City;", "lunch": "Shree Rathnam, Salt Lake City", "dinner": "-", "accommodation": "COZY COOL ROOM IN MANHATTAN APT / Manhattan, Moab"}, {"day": 4, "current_city": "Moab", "transportation": "-", "breakfast": "Cafe Hydro, Moab", "attraction": "Arches National Park, Moab;Dead Horse Point State Park, Moab;", "lunch": "Spice Kraft, Moab", "dinner": "Mangosteen Cafe, Moab", "accommodation": "COZY COOL ROOM IN MANHATTAN APT / Manhattan, Moab"}, {"day": 5, "current_city": "from Moab to Vernal", "transportation": "Self-driving, from Moab to Vernal, duration: 3 hours 40 mins, distance: 349 km, Cost: 17", "breakfast": "-", "attraction": "Moab Museum, Moab;", "lunch": "Sufiya Hotel, Moab", "dinner": "-", "accommodation": "Luxurious & Spacious 1 Bedroom Apt, Vernal"}, {"day": 6, "current_city": "Vernal", "transportation": "-", "breakfast": "Republic of Chicken, Vernal", "attraction": "Utah Field House of Natural History State Park Museum, Vernal;Steinaker State Park, Vernal;", "lunch": "Pepper Sprout Incorporated, Vernal", "dinner": "Prost Brew Pub, Vernal", "accommodation": "Luxurious & Spacious 1 Bedroom Apt, Vernal"}, {"day": 7, "current_city": "from Vernal to Houston", "transportation": "Self-driving, from Vernal to Houston, duration: 20 hours 31 mins, distance: 2,167 km, Cost: 108", "breakfast": "-", "attraction": "-", "lunch": "-", "dinner": "-", "accommodation": "-"}]}]