[{"gpt-4-1106-preview_direct_sole-planning_results": "Travel Plan:\n\nDay 1: March 5, 2022\nCurrent City: from Greer to Philadelphia\nTransportation: Flight Number: F3787785, from Greer to Philadelphia, Departure Time: 07:00, Arrival Time: 08:33\nBreakfast: -\nAttraction: Liberty Bell, Philadelphia\nLunch: Hong Kong Cafe, Philadelphia (Average Cost: $47)\nDinner: Red Ginger Sushi, Grill & Bar, Philadelphia (Average Cost: $98)\nAccommodation: Industrial Loft Living in NYC, Philadelphia (Price: $178)\n\nDay 2: March 6, 2022\nCurrent City: Philadelphia\nTransportation: -\nBreakfast: Marukame Udon, Philadelphia (Average Cost: $100)\nAttraction: The Franklin Institute, Philadelphia; Philadelphia Museum of Art, Philadelphia\nLunch: The Moon Under Water, Philadelphia (Average Cost: $94)\nDinner: Pind Balluchi, Philadelphia (Average Cost: $44)\nAccommodation: Industrial Loft Living in NYC, Philadelphia (Price: $178)\n\nDay 3: March 7, 2022\nCurrent City: from Philadelphia to State College\nTransportation: Flight Number: F3734033, from Philadelphia to State College, Departure Time: 09:38, Arrival Time: 10:48\nBreakfast: -\nAttraction: The Arboretum at Penn State, State College\nLunch: Los Agaves, State College (Average Cost: $39)\nDinner: Salsa's Mexican Restaurant, State College (Average Cost: $52)\nAccommodation: Beautiful, Newly Furnished, Luxury, Grand Central, State College (Price: $210)\n\nDay 4: March 8, 2022\nCurrent City: State College\nTransportation: -\nBreakfast: Amici Cafe, State College (Average Cost: $96)\nAttraction: Penn State All-Sports Museum, State College; Palmer Museum of Art, State College\nLunch: The Chocolate Heaven, State College (Average Cost: $45)\nDinner: Fitoor, State College (Average Cost: $48)\nAccommodation: Beautiful, Newly Furnished, Luxury, Grand Central, State College (Price: $210)\n\nDay 5: March 9, 2022\nCurrent City: from State College to Greer\nTransportation: Self-driving, from State College to Greer, duration: 9 hours 30 mins, cost: $49\nBreakfast: -\nAttraction: -\nLunch: -\nDinner: -\nAccommodation: -\n\nTotal Estimated Costs:\nFlights: $153 (Greer to Philadelphia) + $73 (Philadelphia to State College) = $226\nAccommodations: $178 (Philadelphia) x 2 nights + $210 (State College) x 2 nights = $776\nMeals and Attractions: $47 (Lunch Day 1) + $98 (Dinner Day 1) + $100 (Breakfast Day 2) + $94 (Lunch Day 2) + $44 (Dinner Day 2) + $39 (Lunch Day 3) + $52 (Dinner Day 3) + $96 (Breakfast Day 4) + $45 (Lunch Day 4) + $48 (Dinner Day 4) = $663\nTransportation (Self-driving from State College to Greer): $49\nTotal: $226 (Flights) + $776 (Accommodations) + $663 (Meals and Attractions) + $49 (Self-driving) = $1,714\n\nRemaining Budget: $3,400 - $1,714 = $1,686\n\nNote: The remaining budget can be used for additional meals, attractions, or any unforeseen expenses. Prices for meals are based on average costs and actual prices may vary. The accommodation in Philadelphia is listed as \"Industrial Loft Living in NYC\" which is likely a data error, but the price and city are correct for the purpose of this plan.", "gpt-4-1106-preview_direct_sole-planning_parsed_results": [{"day": 1, "current_city": "from Greer to Philadelphia", "transportation": "Flight Number: F3787785, from Greer to Philadelphia, Departure Time: 07:00, Arrival Time: 08:33", "breakfast": "-", "attraction": "Liberty Bell, Philadelphia;", "lunch": "Hong Kong Cafe, Philadelphia", "dinner": "Red Ginger Sushi, Grill & Bar, Philadelphia", "accommodation": "Industrial Loft Living in NYC, Philadelphia"}, {"day": 2, "current_city": "Philadelphia", "transportation": "-", "breakfast": "Marukame Udon, Philadelphia", "attraction": "The Franklin Institute, Philadelphia;Philadelphia Museum of Art, Philadelphia;", "lunch": "The Moon Under Water, Philadelphia", "dinner": "Pind Balluchi, Philadelphia", "accommodation": "Industrial Loft Living in NYC, Philadelphia"}, {"day": 3, "current_city": "from Philadelphia to State College", "transportation": "Flight Number: F3734033, from Philadelphia to State College, Departure Time: 09:38, Arrival Time: 10:48", "breakfast": "-", "attraction": "The Arboretum at Penn State, State College;", "lunch": "Los Agaves, State College", "dinner": "Salsa's Mexican Restaurant, State College", "accommodation": "Beautiful, Newly Furnished, Luxury, Grand Central, State College"}, {"day": 4, "current_city": "State College", "transportation": "-", "breakfast": "Amici Cafe, State College", "attraction": "Penn State All-Sports Museum, State College;Palmer Museum of Art, State College;", "lunch": "The Chocolate Heaven, State College", "dinner": "Fitoor, State College", "accommodation": "Beautiful, Newly Furnished, Luxury, Grand Central, State College"}, {"day": 5, "current_city": "from State College to Greer", "transportation": "Self-driving, from State College to Greer, duration: 9 hours 30 mins, Cost: 49", "breakfast": "-", "attraction": "-", "lunch": "-", "dinner": "-", "accommodation": "-"}]}]