[{"gpt-4-1106-preview_direct_sole-planning_results": "Travel Plan:\n\nDay 1: March 20, 2022\nCurrent City: from Houston to Fayetteville\nTransportation: Flight Number: F3923439, from Houston to Fayetteville, Departure Time: 09:29, Arrival Time: 11:04\nBreakfast: - (Assuming breakfast will be had before departure or on the flight)\nAttraction: Airborne & Special Operations Museum Foundation, Fayetteville\nLunch: The Great Indian Pub, Fayetteville (Offers a blend of American and Mediterranean cuisines)\nDinner: Fa Yian, Fayetteville (Offers Chinese cuisine)\nAccommodation: Private BRoom, Bathroom & backyard, Fayetteville (Allows children under 10)\n\nDay 2: March 21, 2022\nCurrent City: Fayetteville\nTransportation: -\nBreakfast: Smoke N Oven, Fayetteville (Offers bakery and cafe options)\nAttraction: Cape Fear Botanical Garden, Fayetteville; Clark Park Nature Center, Fayetteville\nLunch: Biryani By Kilo, Fayetteville (Offers Mediterranean cuisine)\nDinner: DiVine, Fayetteville (Offers a mix of cuisines including American and French)\nAccommodation: Private BRoom, Bathroom & backyard, Fayetteville (Allows children under 10)\n\nDay 3: March 22, 2022\nCurrent City: from Fayetteville to Houston\nTransportation: Flight Number: F3922249, from Fayetteville to Houston, Departure Time: 19:18, Arrival Time: 20:52\nBreakfast: Fresh n Refresh, Fayetteville (Offers cafe and Italian, which often includes Mediterranean dishes)\nAttraction: Fascinate-U Children's Museum, Fayetteville (Kid-friendly)\nLunch: Oriental Fusion, Fayetteville (Offers a blend of Asian cuisines, including Chinese)\nDinner: - (Assuming dinner will be had after arrival in Houston or on the flight)\nAccommodation: -\n\nPlease note that the specific flight numbers, restaurant names, and accommodation names are based on the provided data. The plan includes a mix of American, Mediterranean, French, and Chinese cuisines as requested and accommodates children under the age of 10. The budget has been considered, but actual prices should be verified at the time of booking as they may vary.", "gpt-4-1106-preview_direct_sole-planning_parsed_results": [{"days": 1, "current_city": "from Houston to Fayetteville", "transportation": "Flight Number: F3923439, from Houston to Fayetteville, Departure Time: 09:29, Arrival Time: 11:04", "breakfast": "-", "attraction": "Airborne & Special Operations Museum Foundation, Fayetteville;", "lunch": "The Great Indian Pub, Fayetteville", "dinner": "Fa Yian, Fayetteville", "accommodation": "Private BRoom, Bathroom & backyard, Fayetteville"}, {"days": 2, "current_city": "Fayetteville", "transportation": "-", "breakfast": "Smoke N Oven, Fayetteville", "attraction": "Cape Fear Botanical Garden, Fayetteville;Clark Park Nature Center, Fayetteville;", "lunch": "Biryani By Kilo, Fayetteville", "dinner": "DiVine, Fayetteville", "accommodation": "Private BRoom, Bathroom & backyard, Fayetteville"}, {"days": 3, "current_city": "from Fayetteville to Houston", "transportation": "Flight Number: F3922249, from Fayetteville to Houston, Departure Time: 19:18, Arrival Time: 20:52", "breakfast": "Fresh n Refresh, Fayetteville", "attraction": "Fascinate-U Children's Museum, Fayetteville;", "lunch": "Oriental Fusion, Fayetteville", "dinner": "-", "accommodation": "-"}]}]