[{"gpt-4-1106-preview_direct_sole-planning_results": "Travel Plan:\n\nDay 1: March 22, 2022\nCurrent City: from Sacramento to Wenatchee\nTransportation: Self-driving, Duration: 12 hours 38 mins, Distance: 1,234 km, Cost: $61\nBreakfast: -\nLunch: -\nDinner: Pesqueiro Eco Gourmet, Wenatchee (Cafe, Pizza, BBQ, Fast Food)\nAccommodation: Modern, Spacious Hideaway in Historic Brooklyn, Wenatchee (Entire home/apt, Price: $386)\n\nDay 2: March 23, 2022\nCurrent City: Wenatchee\nTransportation: -\nBreakfast: Chang Garden, Wenatchee (Tea, Cafe, Bakery, Pizza)\nAttraction: Ohme Gardens, Wenatchee\nLunch: Flying Tuk Tuk, Wenatchee (Tea, Bakery)\nDinner: Sagar Ratna, Wenatchee (Tea, Indian, Fast Food)\nAccommodation: Modern, Spacious Hideaway in Historic Brooklyn, Wenatchee (Entire home/apt, Price: $386)\n\nDay 3: March 24, 2022\nCurrent City: from Wenatchee to Yakima\nTransportation: Self-driving, Duration: 1 hour 55 mins, Distance: 172 km, Cost: $8\nBreakfast: -\nAttraction: Yakima Valley Museum, Yakima\nLunch: United Kitchens of India, Yakima (BBQ, Mediterranean, Fast Food)\nDinner: The Immigrant Cafe, Yakima (Cafe, Pizza, Bakery, BBQ)\nAccommodation: Spacious studio in LIC, Yakima (Entire home/apt, Price: $455)\n\nDay 4: March 25, 2022\nCurrent City: Yakima\nTransportation: -\nBreakfast: Sambo Kojin, Yakima (Tea, Seafood, Cafe, Fast Food)\nAttraction: Yakima Area Arboretum, Yakima\nLunch: Chew - Pan Asian Cafe, Yakima (Fast Food, Pizza, Seafood)\nDinner: The Centre Court, Yakima (Bakery, Pizza, Desserts, Fast Food)\nAccommodation: Spacious studio in LIC, Yakima (Entire home/apt, Price: $455)\n\nDay 5: March 26, 2022\nCurrent City: from Yakima to Sacramento\nTransportation: Self-driving, Duration: 10 hours 56 mins, Distance: 1,053 km, Cost: $52\nBreakfast: -\nLunch: -\nDinner: -\nAccommodation: -\n\nTotal Estimated Costs:\nTransportation: $61 (Day 1) + $8 (Day 3) + $52 (Day 5) = $121\nAccommodation: $386 (Day 1) + $386 (Day 2) + $455 (Day 3) + $455 (Day 4) = $1,682\nMeals and Attractions: Variable, to be managed within the remaining budget of $1,797 ($3,600 total budget - $1,803 spent on transportation and accommodation)\n\nPlease note that meal costs, attraction entry fees, and any additional transportation (e.g., local taxis) are not specified and should be managed within the remaining budget. The accommodation choices are based on the requirement for entire rooms and the exclusion of properties with restrictions such as no children under 10 or no pets, as per the provided data.", "gpt-4-1106-preview_direct_sole-planning_parsed_results": [{"day": 1, "current_city": "from Sacramento to Wenatchee", "transportation": "Self-driving, Duration: 12 hours 38 mins, Distance: 1,234 km, Cost: 61", "breakfast": "-", "lunch": "-", "dinner": "Pesqueiro Eco Gourmet, Wenatchee", "accommodation": "Modern, Spacious Hideaway in Historic Brooklyn, Wenatchee"}, {"day": 2, "current_city": "Wenatchee", "transportation": "-", "breakfast": "Chang Garden, Wenatchee", "attraction": "Ohme Gardens, Wenatchee;", "lunch": "Flying Tuk Tuk, Wenatchee", "dinner": "Sagar Ratna, Wenatchee", "accommodation": "Modern, Spacious Hideaway in Historic Brooklyn, Wenatchee"}, {"day": 3, "current_city": "from Wenatchee to Yakima", "transportation": "Self-driving, Duration: 1 hour 55 mins, Distance: 172 km, Cost: 8", "breakfast": "-", "attraction": "Yakima Valley Museum, Yakima;", "lunch": "United Kitchens of India, Yakima", "dinner": "The Immigrant Cafe, Yakima", "accommodation": "Spacious studio in LIC, Yakima"}, {"day": 4, "current_city": "Yakima", "transportation": "-", "breakfast": "Sambo Kojin, Yakima", "attraction": "Yakima Area Arboretum, Yakima;", "lunch": "Chew - Pan Asian Cafe, Yakima", "dinner": "The Centre Court, Yakima", "accommodation": "Spacious studio in LIC, Yakima"}, {"day": 5, "current_city": "from Yakima to Sacramento", "transportation": "Self-driving, Duration: 10 hours 56 mins, Distance: 1,053 km, Cost: 52", "breakfast": "-", "lunch": "-", "dinner": "-", "accommodation": "-"}]}]