[{"gpt-4-1106-preview_direct_sole-planning_results": "Travel Plan:\n\nDay 1: March 24, 2022\nCurrent City: from Provo to Phoenix\nTransportation: Flight Number: F3576799, from Provo to Phoenix, Departure Time: 15:09, Arrival Time: 15:34\nBreakfast: -\nLunch: -\nDinner: Pizza Hut, Phoenix (Tea, Chinese, Desserts, Seafood)\nAccommodation: Bright, Williamsburg bedroom with private balcony, Phoenix (Private room, No parties & No pets)\n\nDay 2: March 25, 2022\nCurrent City: Phoenix\nTransportation: -\nBreakfast: Subway, Phoenix (Cafe, Chinese, Seafood, Fast Food)\nAttraction: Phoenix Zoo, Phoenix\nLunch: Mama Loca, Phoenix (Desserts, Pizza, Italian, Bakery, Fast Food)\nAttraction: Desert Botanical Garden, Phoenix\nDinner: Vero Gusto, Phoenix (Desserts, Indian, BBQ)\nAccommodation: Bright, Williamsburg bedroom with private balcony, Phoenix (Private room, No parties & No pets)\n\nDay 3: March 26, 2022\nCurrent City: from Phoenix to Provo\nTransportation: Flight Number: F3578519, from Phoenix to Provo, Departure Time: 20:12, Arrival Time: 22:55\nBreakfast: Doughlicious, Phoenix (French, Pizza, BBQ)\nAttraction: Heard Museum, Phoenix\nLunch: Malabar Dosa Hut, Phoenix (Tea, Seafood, American, Italian)\nDinner: -\nAccommodation: -\n\nNote: The accommodation selected is pet-friendly as per the query, but the house rules state \"No pets.\" Since the query requests pet-friendly accommodations, this is a discrepancy. However, due to the lack of explicitly pet-friendly options in the provided data, this accommodation was chosen based on the private room preference. Please ensure to confirm the pet policy directly with the accommodation provider before booking.", "gpt-4-1106-preview_direct_sole-planning_parsed_results": [{"day": 1, "current_city": "from Provo to Phoenix", "transportation": "Flight Number: F3576799, from Provo to Phoenix, Departure Time: 15:09, Arrival Time: 15:34", "breakfast": "-", "attraction": "-", "lunch": "-", "dinner": "Pizza Hut, Phoenix", "accommodation": "Bright, Williamsburg bedroom with private balcony, Phoenix"}, {"day": 2, "current_city": "Phoenix", "transportation": "-", "breakfast": "Subway, Phoenix", "attraction": "Phoenix Zoo, Phoenix;Desert Botanical Garden, Phoenix;", "lunch": "Mama Loca, Phoenix", "dinner": "Vero Gusto, Phoenix", "accommodation": "Bright, Williamsburg bedroom with private balcony, Phoenix"}, {"day": 3, "current_city": "from Phoenix to Provo", "transportation": "Flight Number: F3578519, from Phoenix to Provo, Departure Time: 20:12, Arrival Time: 22:55", "breakfast": "Doughlicious, Phoenix", "attraction": "Heard Museum, Phoenix", "lunch": "Malabar Dosa Hut, Phoenix", "dinner": "-", "accommodation": "-"}]}]