[{"gpt-4-1106-preview_direct_sole-planning_results": "Travel Plan:\n\nDay 1: March 20, 2022\nCurrent City: from Asheville to Baltimore\nTransportation: Self-driving, Duration: 7 hours 43 mins, Distance: 819 km, Cost: $320 (40 x 8 people)\nBreakfast: - (Assuming breakfast is had before departure)\nAttraction: Inner Harbor, Baltimore (Free, family-friendly area)\nLunch: Los Pablos, Baltimore (Average Cost: $47 per person, Total: $376 for 8 people)\nDinner: Three Dots & A Dash, Baltimore (Average Cost: $47 per person, Total: $376 for 8 people)\nAccommodation: Contemporary Home Away from Home, Entire house (Price: $290 per night, suitable for children)\n\nDay 2: March 21, 2022\nCurrent City: Baltimore\nTransportation: -\nBreakfast: Mr. Dunderbak's Biergarten and Marketplatz, Baltimore (Average Cost: $74 per person, Total: $592 for 8 people)\nAttraction 1: National Aquarium, Baltimore (Phone: (410) 576-3800, Cost: $39.95 per adult, $29.95 per child under 11, Total: $279.60 for 2 adults and 6 children)\nAttraction 2: Port Discovery Children's Museum, Baltimore (Phone: (410) 727-8120, Cost: $17.95 per person, Total: $143.60 for 8 people)\nLunch: Farzi Cafe, Baltimore (Average Cost: $96 per person, Total: $768 for 8 people)\nDinner: The Retriever, Baltimore (Average Cost: $12 per person, Total: $96 for 8 people)\nAccommodation: Contemporary Home Away from Home, Entire house (Price: $290 per night, suitable for children)\n\nDay 3: March 22, 2022\nCurrent City: from Baltimore to Asheville\nTransportation: Self-driving, Duration: 7 hours 42 mins, Distance: 819 km, Cost: $320 (40 x 8 people)\nBreakfast: The Thai Bowl, Baltimore (Average Cost: $66 per person, Total: $528 for 8 people)\nAttraction: Maryland Science Center, Baltimore (Phone: (410) 685-2370, Cost: $25.95 per adult, $19.95 per child under 13, Total: $183.60 for 2 adults and 6 children)\nLunch: Shiv Saras Vyanjan, Baltimore (Average Cost: $65 per person, Total: $520 for 8 people)\nDinner: - (Assuming dinner is had after arrival back in Asheville)\nAccommodation: -\n\nTotal Estimated Costs:\nTransportation (Self-driving to and from Baltimore): $640\nAccommodation (2 nights): $580\nMeals: $3,256\nAttractions: $606.80\nTotal: $5,082.80\n\nRemaining Budget: $6,500 - $5,082.80 = $1,417.20\n\nNote: The remaining budget can be used for additional meals, attractions, or any unforeseen expenses. The costs for attractions are based on standard admission prices and may vary for special exhibits or events. All activities and dining options are chosen considering the presence of young children.", "gpt-4-1106-preview_direct_sole-planning_parsed_results": [{"day": 1, "current_city": "from Asheville to Baltimore", "transportation": "Self-driving, Duration: 7 hours 43 mins, Distance: 819 km, Cost: 320 (40 x 8 people)", "breakfast": "-", "attraction": "Inner Harbor, Baltimore", "lunch": "Los Pablos, Baltimore", "dinner": "Three Dots & A Dash, Baltimore", "accommodation": "Contemporary Home Away from Home, Baltimore"}, {"day": 2, "current_city": "Baltimore", "transportation": "-", "breakfast": "Mr. Dunderbak's Biergarten and Marketplatz, Baltimore", "attraction": "National Aquarium, Baltimore;Port Discovery Children's Museum, Baltimore", "lunch": "Farzi Cafe, Baltimore", "dinner": "The Retriever, Baltimore", "accommodation": "Contemporary Home Away from Home, Baltimore"}, {"day": 3, "current_city": "from Baltimore to Asheville", "transportation": "Self-driving, Duration: 7 hours 42 mins, Distance: 819 km, Cost: 320 (40 x 8 people)", "breakfast": "The Thai Bowl, Baltimore", "attraction": "Maryland Science Center, Baltimore", "lunch": "Shiv Saras Vyanjan, Baltimore", "dinner": "-", "accommodation": "-"}]}]