[{"gpt-4-1106-preview_direct_sole-planning_results": "Travel Plan:\nDay 1: March 10, 2022\nCurrent City: from Seattle to Dallas\nTransportation: Flight Number: F3669219, from Seattle to Dallas, Departure Time: 07:42, Arrival Time: 13:36\nBreakfast: -\nAttraction: The Sixth Floor Museum at Dealey Plaza, Dallas\nLunch: 1918 Bistro & Grill, Dallas\nDinner: Coconuts Fish Cafe, Dallas\nAccommodation: Luxury Williamsburg duplex, private roof terrace, Dallas\n\nDay 2: March 11, 2022\nCurrent City: Dallas\nTransportation: -\nBreakfast: Cafe Gatherings, Dallas\nAttraction: The Dallas World Aquarium, Dallas; Reunion Tower, Dallas\nLunch: Drifters Cafe, Dallas\nDinner: Uma Foodies' Hut, Dallas\nAccommodation: Luxury Williamsburg duplex, private roof terrace, Dallas\n\nDay 3: March 12, 2022\nCurrent City: from Dallas to Houston\nTransportation: Flight Number: F3667553, from Dallas to Houston, Departure Time: 07:06, Arrival Time: 08:21\nBreakfast: -\nAttraction: Space Center Houston, Houston\nLunch: The BrewMaster - The Mix Fine Dine, Houston\nDinner: Jalapenos, Houston\nAccommodation: Spacious, bright room, prime Williamsburg location, Houston\n\nDay 4: March 13, 2022\nCurrent City: Houston\nTransportation: -\nBreakfast: Cyber Adda 24, Houston\nAttraction: Houston Museum of Natural Science, Houston; The Museum of Fine Arts, Houston\nLunch: Pebble Street, Houston\nDinner: Al Arabian Express, Houston\nAccommodation: Spacious, bright room, prime Williamsburg location, Houston\n\nDay 5: March 14, 2022\nCurrent City: from Houston to San Antonio\nTransportation: Flight Number: F3877522, from Houston to San Antonio, Departure Time: 16:34, Arrival Time: 17:21\nBreakfast: Truth Coffee, Houston\nAttraction: San Antonio River Walk, San Antonio\nLunch: Cafe Le Rue @ The Landings, San Antonio\nDinner: Martin's BBQ, San Antonio\nAccommodation: Large apt in prime carol gardens, San Antonio\n\nDay 6: March 15, 2022\nCurrent City: San Antonio\nTransportation: -\nBreakfast: My Kind Of Cafe, San Antonio\nAttraction: SeaWorld San Antonio, San Antonio; The Alamo, San Antonio\nLunch: Barbeque Nation, San Antonio\nDinner: Cream Stone, San Antonio\nAccommodation: Large apt in prime carol gardens, San Antonio\n\nDay 7: March 16, 2022\nCurrent City: from San Antonio to Seattle\nTransportation: Flight Number: F3744881, from San Antonio to Seattle, Departure Time: 18:35, Arrival Time: 20:58\nBreakfast: Cafe Coffee Day, San Antonio\nAttraction: San Antonio Missions National Historical Park, San Antonio\nLunch: Big Jack's, San Antonio\nDinner: -\nAccommodation: -\n\nNote: The accommodations selected allow parties as per the request. The restaurants and attractions were chosen based on proximity and relevance to the cities visited. The flights were selected to fit the schedule and budget constraints. Breakfast on travel days is not included due to early flight times. The total cost of flights, accommodations, and estimated meal costs should be within the $11,000 budget, but please ensure to check the latest prices and availability.", "gpt-4-1106-preview_direct_sole-planning_parsed_results": [{"day": 1, "current_city": "from Seattle to Dallas", "transportation": "Flight Number: F3669219, from Seattle to Dallas, Departure Time: 07:42, Arrival Time: 13:36", "breakfast": "-", "attraction": "The Sixth Floor Museum at Dealey Plaza, Dallas", "lunch": "1918 Bistro & Grill, Dallas", "dinner": "Coconuts Fish Cafe, Dallas", "accommodation": "Luxury Williamsburg duplex, private roof terrace, Dallas"}, {"day": 2, "current_city": "Dallas", "transportation": "-", "breakfast": "Cafe Gatherings, Dallas", "attraction": "The Dallas World Aquarium, Dallas;Reunion Tower, Dallas", "lunch": "Drifters Cafe, Dallas", "dinner": "Uma Foodies' Hut, Dallas", "accommodation": "Luxury Williamsburg duplex, private roof terrace, Dallas"}, {"day": 3, "current_city": "from Dallas to Houston", "transportation": "Flight Number: F3667553, from Dallas to Houston, Departure Time: 07:06, Arrival Time: 08:21", "breakfast": "-", "attraction": "Space Center Houston, Houston", "lunch": "The BrewMaster - The Mix Fine Dine, Houston", "dinner": "Jalapenos, Houston", "accommodation": "Spacious, bright room, prime Williamsburg location, Houston"}, {"day": 4, "current_city": "Houston", "transportation": "-", "breakfast": "Cyber Adda 24, Houston", "attraction": "Houston Museum of Natural Science, Houston;The Museum of Fine Arts, Houston", "lunch": "Pebble Street, Houston", "dinner": "Al Arabian Express, Houston", "accommodation": "Spacious, bright room, prime Williamsburg location, Houston"}, {"day": 5, "current_city": "from Houston to San Antonio", "transportation": "Flight Number: F3877522, from Houston to San Antonio, Departure Time: 16:34, Arrival Time: 17:21", "breakfast": "Truth Coffee, Houston", "attraction": "San Antonio River Walk, San Antonio", "lunch": "Cafe Le Rue @ The Landings, San Antonio", "dinner": "Martin's BBQ, San Antonio", "accommodation": "Large apt in prime carol gardens, San Antonio"}, {"day": 6, "current_city": "San Antonio", "transportation": "-", "breakfast": "My Kind Of Cafe, San Antonio", "attraction": "SeaWorld San Antonio, San Antonio;The Alamo, San Antonio", "lunch": "Barbeque Nation, San Antonio", "dinner": "Cream Stone, San Antonio", "accommodation": "Large apt in prime carol gardens, San Antonio"}, {"day": 7, "current_city": "from San Antonio to Seattle", "transportation": "Flight Number: F3744881, from San Antonio to Seattle, Departure Time: 18:35, Arrival Time: 20:58", "breakfast": "Cafe Coffee Day, San Antonio", "attraction": "San Antonio Missions National Historical Park, San Antonio", "lunch": "Big Jack's, San Antonio", "dinner": "-", "accommodation": "-"}]}]