[{"gpt-4-1106-preview_direct_sole-planning_results": "Travel Plan:\n\nDay 1:\nCurrent City: from Sacramento to Atlanta\nTransportation: Flight Number: F3510904, from Sacramento to Atlanta, Departure Time: 06:55, Arrival Time: 14:09\nBreakfast: - (Assuming breakfast will be at Sacramento or on the flight)\nAttraction: Georgia Aquarium, Atlanta\nLunch: Saffron, Atlanta\nDinner: Baba Au Rhum, Atlanta\nAccommodation: Bright central designer's apt - steps to train!, Atlanta\n\nDay 2:\nCurrent City: Atlanta\nTransportation: -\nBreakfast: Adda, Atlanta\nAttraction: Atlanta Botanical Garden, Atlanta; World of Coca-Cola, Atlanta\nLunch: Chef Style, Atlanta\nDinner: Pizza Central, Atlanta\nAccommodation: Bright central designer's apt - steps to train!, Atlanta\n\nDay 3:\nCurrent City: from Atlanta to Sacramento\nTransportation: Flight Number: F3527027, from Atlanta to Sacramento, Departure Time: 08:56, Arrival Time: 10:42\nBreakfast: - (Assuming breakfast will be in Atlanta or on the flight)\nAttraction: - (No time for attractions due to early flight)\nLunch: - (Assuming lunch will be in Sacramento after arrival)\nDinner: - (Assuming dinner will be in Sacramento)\nAccommodation: -\n\nNote: The accommodation selected allows parties as per the house rules, and the total cost of flights, meals, and accommodation is within the provided budget of $4,700. Please ensure to confirm the availability and current prices of flights, meals, and accommodation as they are subject to change.", "gpt-4-1106-preview_direct_sole-planning_parsed_results": [{"day": 1, "current_city": "from Sacramento to Atlanta", "transportation": "Flight Number: F3510904, from Sacramento to Atlanta, Departure Time: 06:55, Arrival Time: 14:09", "breakfast": "-", "attraction": "Georgia Aquarium, Atlanta", "lunch": "Saffron, Atlanta", "dinner": "Baba Au Rhum, Atlanta", "accommodation": "Bright central designer's apt - steps to train!, Atlanta"}, {"day": 2, "current_city": "Atlanta", "transportation": "-", "breakfast": "Adda, Atlanta", "attraction": "Atlanta Botanical Garden, Atlanta;World of Coca-Cola, Atlanta", "lunch": "Chef Style, Atlanta", "dinner": "Pizza Central, Atlanta", "accommodation": "Bright central designer's apt - steps to train!, Atlanta"}, {"day": 3, "current_city": "from Atlanta to Sacramento", "transportation": "Flight Number: F3527027, from Atlanta to Sacramento, Departure Time: 08:56, Arrival Time: 10:42", "breakfast": "-", "attraction": "-", "lunch": "-", "dinner": "-", "accommodation": "-"}]}]