[{"gpt-4-1106-preview_direct_sole-planning_results": "Travel Plan:\nDay 1:\nCurrent City: from Kansas City to Pensacola\nTransportation: Self-driving, from Kansas City to Pensacola, Duration: 14 hours 4 mins, Distance: 1,433 km, Cost: $71\nBreakfast: -\nAttraction: -\nLunch: -\nDinner: Frog Hollow Tavern, Pensacola\nAccommodation: Amazing apartment near museum, gardens & park!, Pensacola\n\nDay 2:\nCurrent City: Pensacola\nTransportation: -\nBreakfast: Berry Patch Restaurant, Pensacola\nAttraction: Historic Pensacola Village, Pensacola; Pensacola Museum of Art, Pensacola.\nLunch: Bailey's Bar-B-Que, Pensacola\nDinner: Chicago Pizza, Pensacola\nAccommodation: Amazing apartment near museum, gardens & park!, Pensacola\n\nDay 3:\nCurrent City: from Pensacola to Kansas City\nTransportation: Self-driving, from Pensacola to Kansas City, Duration: 14 hours 0 mins, Distance: 1,447 km, Cost: $72\nBreakfast: -\nAttraction: -\nLunch: -\nDinner: -\nAccommodation: -\n\nNote: The budget of $900 covers the transportation costs for self-driving ($71 + $72 = $143), accommodation for two nights at $74 per night ($148 total), and estimated food and attraction expenses. The remaining budget should be sufficient for meals and entry fees to attractions, considering the average cost of meals at selected restaurants. However, the traveler should manage their budget carefully to ensure they do not exceed the $900 limit.", "gpt-4-1106-preview_direct_sole-planning_parsed_results": [{"day": 1, "current_city": "from Kansas City to Pensacola", "transportation": "Self-driving, from Kansas City to Pensacola, Duration: 14 hours 4 mins, Distance: 1,433 km, Cost: 71", "breakfast": "-", "attraction": "-", "lunch": "-", "dinner": "Frog Hollow Tavern, Pensacola", "accommodation": "Amazing apartment near museum, gardens & park!, Pensacola"}, {"day": 2, "current_city": "Pensacola", "transportation": "-", "breakfast": "Berry Patch Restaurant, Pensacola", "attraction": "Historic Pensacola Village, Pensacola;Pensacola Museum of Art, Pensacola;", "lunch": "Bailey's Bar-B-Que, Pensacola", "dinner": "Chicago Pizza, Pensacola", "accommodation": "Amazing apartment near museum, gardens & park!, Pensacola"}, {"day": 3, "current_city": "from Pensacola to Kansas City", "transportation": "Self-driving, from Pensacola to Kansas City, Duration: 14 hours 0 mins, Distance: 1,447 km, Cost: 72", "breakfast": "-", "attraction": "-", "lunch": "-", "dinner": "-", "accommodation": "-"}]}]