[{"gpt-4-1106-preview_direct_sole-planning_results": "Travel Plan:\n\nDay 1: March 10, 2022\nCurrent City: from Orlando to San Antonio\nTransportation: Flight Number: F4023176, from Orlando to San Antonio, Departure Time: 06:58, Arrival Time: 09:22\nBreakfast: -\nAttraction: San Antonio River Walk, San Antonio\nLunch: Cafe Le Rue @ The Landings, San Antonio\nDinner: Martin's BBQ, San Antonio\nAccommodation: Spacious, bright room, prime Williamsburg location, San Antonio\n\nDay 2: March 11, 2022\nCurrent City: San Antonio\nTransportation: -\nBreakfast: Barbeque Nation, San Antonio\nAttraction: The Alamo, San Antonio; San Antonio Missions National Historical Park, San Antonio\nLunch: Cream Stone, San Antonio\nDinner: The Kylin Experience - Holiday Inn, San Antonio\nAccommodation: Spacious, bright room, prime Williamsburg location, San Antonio\n\nDay 3: March 12, 2022\nCurrent City: from San Antonio to Houston\nTransportation: Flight Number: F3972674, from San Antonio to Houston, Departure Time: 06:38, Arrival Time: 07:24\nBreakfast: -\nAttraction: Space Center Houston, Houston; Houston Museum of Natural Science, Houston\nLunch: Matchbox, Houston\nDinner: The BrewMaster - The Mix Fine Dine, Houston\nAccommodation: Sunny and Airy near Manhattan, Houston\n\nDay 4: March 13, 2022\nCurrent City: Houston\nTransportation: -\nBreakfast: Vinayaka Mylari, Houston\nAttraction: Hermann Park, Houston; Houston Zoo, Houston\nLunch: Pebble Street, Houston\nDinner: Truth Coffee, Houston\nAccommodation: Sunny and Airy near Manhattan, Houston\n\nDay 5: March 14, 2022\nCurrent City: from Houston to Orlando\nTransportation: Flight Number: F3978032, from Houston to Orlando, Departure Time: 12:33, Arrival Time: 15:25\nBreakfast: Jalapenos, Houston\nAttraction: Gerald D. Hines Waterwall Park, Houston\nLunch: -\nDinner: -\nAccommodation: -\n\nPlease note that the budget has been considered for flights, accommodations, and meals. Attractions are chosen based on proximity and significance, and meals are selected from restaurants with a variety of cuisines. The accommodation choices are based on a single occupancy and the preference for a private room or entire home/apt as available within the budget. The flight times are chosen to maximize daytime activities in each city.", "gpt-4-1106-preview_direct_sole-planning_parsed_results": [{"day": 1, "current_city": "from Orlando to San Antonio", "transportation": "Flight Number: F4023176, from Orlando to San Antonio, Departure Time: 06:58, Arrival Time: 09:22", "breakfast": "-", "attraction": "San Antonio River Walk, San Antonio", "lunch": "Cafe Le Rue @ The Landings, San Antonio", "dinner": "Martin's BBQ, San Antonio", "accommodation": "Spacious, bright room, prime Williamsburg location, San Antonio"}, {"day": 2, "current_city": "San Antonio", "transportation": "-", "breakfast": "Barbeque Nation, San Antonio", "attraction": "The Alamo, San Antonio;San Antonio Missions National Historical Park, San Antonio", "lunch": "Cream Stone, San Antonio", "dinner": "The Kylin Experience - Holiday Inn, San Antonio", "accommodation": "Spacious, bright room, prime Williamsburg location, San Antonio"}, {"day": 3, "current_city": "from San Antonio to Houston", "transportation": "Flight Number: F3972674, from San Antonio to Houston, Departure Time: 06:38, Arrival Time: 07:24", "breakfast": "-", "attraction": "Space Center Houston, Houston;Houston Museum of Natural Science, Houston", "lunch": "Matchbox, Houston", "dinner": "The BrewMaster - The Mix Fine Dine, Houston", "accommodation": "Sunny and Airy near Manhattan, Houston"}, {"day": 4, "current_city": "Houston", "transportation": "-", "breakfast": "Vinayaka Mylari, Houston", "attraction": "Hermann Park, Houston;Houston Zoo, Houston", "lunch": "Pebble Street, Houston", "dinner": "Truth Coffee, Houston", "accommodation": "Sunny and Airy near Manhattan, Houston"}, {"day": 5, "current_city": "from Houston to Orlando", "transportation": "Flight Number: F3978032, from Houston to Orlando, Departure Time: 12:33, Arrival Time: 15:25", "breakfast": "Jalapenos, Houston", "attraction": "Gerald D. Hines Waterwall Park, Houston", "lunch": "-", "dinner": "-", "accommodation": "-"}]}]