[{"gpt-4-1106-preview_direct_sole-planning_results": "Travel Plan:\nDay 1:\nCurrent City: from Atlanta to Bemidji\nTransportation: Taxi, from Atlanta to Bemidji, Duration: 19 hours 53 mins, Distance: 2,166 km, Cost: $2,166\nBreakfast: -\nAttraction: Paul Bunyan & Babe the Blue Ox Statues, Bemidji\nLunch: Pig and Whistle, Bemidji\nDinner: Flying Cakes, Bemidji\nAccommodation: Warm Artistic Wburg Loft Off 4 Train Lines, Bemidji (Cost: $831, Entire home/apt, allows parties)\n\nDay 2:\nCurrent City: Bemidji\nTransportation: -\nBreakfast: Outback Bar and Grill - Leisure Inn, Bemidji\nAttraction: Headwaters Science Center, Bemidji; Diamond Point Park, Bemidji.\nLunch: Chao Chinese Bistro - Holiday Inn Jaipur City Centre, Bemidji\nDinner: Southy, Bemidji\nAccommodation: Warm Artistic Wburg Loft Off 4 Train Lines, Bemidji\n\nDay 3:\nCurrent City: from Bemidji to Minneapolis\nTransportation: Flight Number: F3849472, from Bemidji to Minneapolis, Departure Time: 08:21, Arrival Time: 09:23, Cost: $86 x 3 = $258\nBreakfast: Bhaja Govindam, Bemidji\nAttraction: Minneapolis Sculpture Garden, Minneapolis; Minneapolis Institute of Art, Minneapolis.\nLunch: The Cafe, Minneapolis\nDinner: Malo, Minneapolis\nAccommodation: Entire 1 Bedroom Apartment in Midtown Manhattan, Minneapolis (Cost: $107, Entire home/apt, allows parties)\n\nDay 4:\nCurrent City: Minneapolis\nTransportation: -\nBreakfast: Court Avenue Brewing Company, Minneapolis\nAttraction: Mill City Museum, Minneapolis; Mill Ruins Park, Minneapolis.\nLunch: Troll Tavern, Minneapolis\nDinner: Texas Roadhouse, Minneapolis\nAccommodation: Entire 1 Bedroom Apartment in Midtown Manhattan, Minneapolis\n\nDay 5:\nCurrent City: from Minneapolis to Atlanta\nTransportation: Flight Number: F3781929, from Minneapolis to Atlanta, Departure Time: 05:32, Arrival Time: 08:59, Cost: $191 x 3 = $573\nBreakfast: Monkeypod Kitchen by Merriman, Minneapolis\nAttraction: Weisman Art Museum, Minneapolis (before departure if time allows).\nLunch: -\nDinner: -\nAccommodation: -\n\nTotal Estimated Cost:\nTaxi to Bemidji: $2,166\nAccommodation in Bemidji (2 nights): $831 x 2 = $1,662\nFlight to Minneapolis: $258\nAccommodation in Minneapolis (2 nights): $107 x 2 = $214\nFlight to Atlanta: $573\nMeals and Miscellaneous: $3,027 (remaining budget)\n\nTotal: $7,900\n\nPlease note that the costs for meals and miscellaneous expenses are estimated to fit within the remaining budget. Actual costs may vary. The accommodation options selected allow for parties and are entire homes/apartments, as requested.", "gpt-4-1106-preview_direct_sole-planning_parsed_results": [{"day": 1, "current_city": "from Atlanta to Bemidji", "transportation": "Taxi, from Atlanta to Bemidji, Duration: 19 hours 53 mins, Distance: 2,166 km, Cost: 2166", "breakfast": "-", "attraction": "Paul Bunyan & Babe the Blue Ox Statues, Bemidji", "lunch": "Pig and Whistle, Bemidji", "dinner": "Flying Cakes, Bemidji", "accommodation": "Warm Artistic Wburg Loft Off 4 Train Lines, Bemidji"}, {"day": 2, "current_city": "Bemidji", "transportation": "-", "breakfast": "Outback Bar and Grill - Leisure Inn, Bemidji", "attraction": "Headwaters Science Center, Bemidji;Diamond Point Park, Bemidji", "lunch": "Chao Chinese Bistro - Holiday Inn Jaipur City Centre, Bemidji", "dinner": "Southy, Bemidji", "accommodation": "Warm Artistic Wburg Loft Off 4 Train Lines, Bemidji"}, {"day": 3, "current_city": "from Bemidji to Minneapolis", "transportation": "Flight Number: F3849472, from Bemidji to Minneapolis, Departure Time: 08:21, Arrival Time: 09:23, Cost: 258", "breakfast": "Bhaja Govindam, Bemidji", "attraction": "Minneapolis Sculpture Garden, Minneapolis;Minneapolis Institute of Art, Minneapolis", "lunch": "The Cafe, Minneapolis", "dinner": "Malo, Minneapolis", "accommodation": "Entire 1 Bedroom Apartment in Midtown Manhattan, Minneapolis"}, {"day": 4, "current_city": "Minneapolis", "transportation": "-", "breakfast": "Court Avenue Brewing Company, Minneapolis", "attraction": "Mill City Museum, Minneapolis;Mill Ruins Park, Minneapolis", "lunch": "Troll Tavern, Minneapolis", "dinner": "Texas Roadhouse, Minneapolis", "accommodation": "Entire 1 Bedroom Apartment in Midtown Manhattan, Minneapolis"}, {"day": 5, "current_city": "from Minneapolis to Atlanta", "transportation": "Flight Number: F3781929, from Minneapolis to Atlanta, Departure Time: 05:32, Arrival Time: 08:59, Cost: 573", "breakfast": "Monkeypod Kitchen by Merriman, Minneapolis", "attraction": "Weisman Art Museum, Minneapolis", "lunch": "-", "dinner": "-", "accommodation": "-"}]}]