[{"gpt-4-1106-preview_direct_sole-planning_results": "Travel Plan:\n\nDay 1: March 8, 2022\nCurrent City: from Denver to Amarillo\nTransportation: Self-driving, from Denver to Amarillo, duration: 6 hours 29 mins, distance: 699 km, cost: $34 x 5 people = $170\nBreakfast: - (Assuming breakfast is had before departure)\nAttraction: Cadillac Ranch, Amarillo\nLunch: The Cinnamon Kitchen, Amarillo (Cuisines: Desserts, Tea, Pizza, Chinese, Seafood)\nDinner: Sigree Global Grill, Amarillo (Cuisines: Chinese, BBQ, Cafe, Desserts)\nAccommodation: STUNNING, HUGE 1 bed apartment, steps from train!, Amarillo (price: $900, allows smoking)\n\nDay 2: March 9, 2022\nCurrent City: Amarillo\nTransportation: -\nBreakfast: Wood Box Cafe, Amarillo (Cuisines: Desserts, French, Fast Food, Cafe, American)\nAttraction: Amarillo Botanical Gardens, Amarillo; Amarillo Zoo, Amarillo\nLunch: Anand Restaurant, Amarillo (Cuisines: Fast Food, Seafood, Desserts, Italian)\nDinner: Punjabi Chaap Corner, Amarillo (Cuisines: Desserts, Pizza, Italian, Bakery, Fast Food)\nAccommodation: STUNNING, HUGE 1 bed apartment, steps from train!, Amarillo (price: $900, allows smoking)\n\nDay 3: March 10, 2022\nCurrent City: from Amarillo to Lubbock\nTransportation: Self-driving, from Amarillo to Lubbock, duration: 1 hour 47 mins, distance: 197 km, cost: $9 x 5 people = $45\nBreakfast: Kanha North & South Indian Veg., Amarillo (Cuisines: Tea, Cafe, BBQ, Fast Food)\nAttraction: Buddy Holly Center, Lubbock; National Ranching Heritage Center, Lubbock\nLunch: Grand Barbeque Buffet Restaurant, Lubbock (Cuisines: Tea, French, Fast Food, Cafe, Seafood)\nDinner: Paris 6 Classique, Lubbock (Cuisines: Desserts, Cafe, Pizza, Mexican, BBQ, Chinese)\nAccommodation: Private bedroom in UWS Apartment, Lubbock (price: $709, allows smoking)\n\nDay 4: March 11, 2022\nCurrent City: Lubbock\nTransportation: -\nBreakfast: The Town House Cafe, Lubbock (Cuisines: Tea, American, BBQ, Cafe, Indian, Seafood)\nAttraction: American Windmill Museum, Lubbock; Prairie Dog Town, Lubbock\nLunch: Mosaic - Country Inn & Suites By Carlson, Lubbock (Cuisines: Chinese, Indian, Desserts, Seafood)\nDinner: Sultanat, Lubbock (Cuisines: Chinese, Bakery, BBQ, Cafe)\nAccommodation: Private bedroom in UWS Apartment, Lubbock (price: $709, allows smoking)\n\nDay 5: March 12, 2022\nCurrent City: from Lubbock to Denver\nTransportation: Self-driving, from Lubbock to Denver, duration: 8 hours 14 mins, distance: 881 km, cost: $44 x 5 people = $220\nBreakfast: - (Assuming breakfast is had before departure)\nAttraction: - (Traveling back to Denver)\nLunch: - (On the road)\nDinner: - (Assuming arrival in Denver is after dinner time)\nAccommodation: -\n\nTotal Estimated Cost:\nAccommodation: $900 x 2 nights (Amarillo) + $709 x 2 nights (Lubbock) = $3,218\nTransportation: $170 (Denver to Amarillo) + $45 (Amarillo to Lubbock) + $220 (Lubbock to Denver) = $435\nFood and Attractions: Variable, but for estimation purposes, let's allocate $100 per person per day for food and attractions. For 5 people over 5 days, this would be $2,500.\nMiscellaneous (e.g., gas, parking): Let's allocate $947 for additional expenses.\n\nTotal Estimated Cost: $3,218 (Accommodation) + $435 (Transportation) + $2,500 (Food and Attractions) + $947 (Miscellaneous) = $7,100\n\nPlease note that the costs for food, attractions, and miscellaneous expenses are estimates and may vary. The accommodation options selected allow smoking as per the requirement. The plan avoids flights for transportation, using self-driving as the mode of travel between cities.", "gpt-4-1106-preview_direct_sole-planning_parsed_results": [{"day": 1, "current_city": "from Denver to Amarillo", "transportation": "Self-driving, from Denver to Amarillo, Duration: 6 hours 29 mins, Distance: 699 km, Cost: 170", "breakfast": "-", "attraction": "Cadillac Ranch, Amarillo;", "lunch": "The Cinnamon Kitchen, Amarillo", "dinner": "Sigree Global Grill, Amarillo", "accommodation": "STUNNING, HUGE 1 bed apartment, steps from train!, Amarillo"}, {"day": 2, "current_city": "Amarillo", "transportation": "-", "breakfast": "Wood Box Cafe, Amarillo", "attraction": "Amarillo Botanical Gardens, Amarillo;Amarillo Zoo, Amarillo;", "lunch": "Anand Restaurant, Amarillo", "dinner": "Punjabi Chaap Corner, Amarillo", "accommodation": "STUNNING, HUGE 1 bed apartment, steps from train!, Amarillo"}, {"day": 3, "current_city": "from Amarillo to Lubbock", "transportation": "Self-driving, from Amarillo to Lubbock, Duration: 1 hour 47 mins, Distance: 197 km, Cost: 45", "breakfast": "Kanha North & South Indian Veg., Amarillo", "attraction": "Buddy Holly Center, Lubbock;National Ranching Heritage Center, Lubbock;", "lunch": "Grand Barbeque Buffet Restaurant, Lubbock", "dinner": "Paris 6 Classique, Lubbock", "accommodation": "Private bedroom in UWS Apartment, Lubbock"}, {"day": 4, "current_city": "Lubbock", "transportation": "-", "breakfast": "The Town House Cafe, Lubbock", "attraction": "American Windmill Museum, Lubbock;Prairie Dog Town, Lubbock;", "lunch": "Mosaic - Country Inn & Suites By Carlson, Lubbock", "dinner": "Sultanat, Lubbock", "accommodation": "Private bedroom in UWS Apartment, Lubbock"}, {"day": 5, "current_city": "from Lubbock to Denver", "transportation": "Self-driving, from Lubbock to Denver, Duration: 8 hours 14 mins, Distance: 881 km, Cost: 220", "breakfast": "-", "attraction": "-", "lunch": "-", "dinner": "-", "accommodation": "-"}]}]