[{"gpt-4-1106-preview_direct_sole-planning_results": "Travel Plan:\n\nDay 1: March 1, 2022\nCurrent City: from Memphis to Minneapolis\nTransportation: Flight Number: F3836157, from Memphis to Minneapolis, Departure Time: 05:57, Arrival Time: 08:10\nBreakfast: -\nAttraction: Minneapolis Sculpture Garden, Minneapolis\nLunch: The Cafe, Minneapolis (Average Cost: $14 per person)\nDinner: Court Avenue Brewing Company, Minneapolis (Average Cost: $31 per person)\nAccommodation: ROOM TWO, Minneapolis (Price: $112 per night)\n\nDay 2: March 2, 2022\nCurrent City: Minneapolis\nTransportation: -\nBreakfast: The Cafe, Minneapolis\nAttraction: Minneapolis Institute of Art, Minneapolis; Mill City Museum, Minneapolis\nLunch: Malo, Minneapolis (Average Cost: $80 per person)\nDinner: Troll Tavern, Minneapolis (Average Cost: $71 per person)\nAccommodation: ROOM TWO, Minneapolis\n\nDay 3: March 3, 2022\nCurrent City: from Minneapolis to Gustavus\nTransportation: Taxi, from Minneapolis to Gustavus, Duration: 1 hour 9 mins, Cost: $110\nBreakfast: -\nAttraction: Glacier Bay National Park Visitor Center, Gustavus\nLunch: Hofer's Bakery & Cafe, Gustavus (Average Cost: $34 per person)\nDinner: That Madras Place, Gustavus (Average Cost: $36 per person)\nAccommodation: Large Private Room in 3 bdr apt-East Village, Gustavus (Price: $684 per night)\n\nDay 4: March 4, 2022\nCurrent City: Gustavus\nTransportation: -\nBreakfast: Hofer's Bakery & Cafe, Gustavus\nAttraction: NatVenture Tours, Gustavus; Sea Wolf Adventures, Gustavus\nLunch: On The Rocks - The Atrium, Gustavus (Average Cost: $60 per person)\nDinner: Tobasco Kitchen, Gustavus (Average Cost: $21 per person)\nAccommodation: Large Private Room in 3 bdr apt-East Village, Gustavus\n\nDay 5: March 5, 2022\nCurrent City: from Gustavus to Memphis\nTransportation: Self-driving, from Gustavus to Memphis, Duration: 12 hours 3 mins, Cost: $64\nBreakfast: -\nAttraction: -\nLunch: -\nDinner: -\nAccommodation: -\n\nTotal Estimated Costs:\nFlights: $260 x 4 = $1040\nTaxi to Gustavus: $110\nAccommodation in Minneapolis: $112 x 4 nights = $448\nAccommodation in Gustavus: $684 x 2 nights = $1368\nMeals and Attractions: Estimated $200 per person per day x 4 people x 4 days = $3200\nSelf-driving from Gustavus to Memphis: $64\nTotal Estimated Cost: $1040 + $110 + $448 + $1368 + $3200 + $64 = $6230\n\nRemaining Budget: $13,800 - $6230 = $7570\n\nPlease note that the costs for meals and attractions are estimated and actual expenses may vary. The remaining budget can be used for additional activities, shopping, or saved for incidental expenses.", "gpt-4-1106-preview_direct_sole-planning_parsed_results": [{"day": 1, "current_city": "from Memphis to Minneapolis", "transportation": "Flight Number: F3836157, from Memphis to Minneapolis, Departure Time: 05:57, Arrival Time: 08:10", "breakfast": "-", "attraction": "Minneapolis Sculpture Garden, Minneapolis;", "lunch": "The Cafe, Minneapolis", "dinner": "Court Avenue Brewing Company, Minneapolis", "accommodation": "ROOM TWO, Minneapolis"}, {"day": 2, "current_city": "Minneapolis", "transportation": "-", "breakfast": "The Cafe, Minneapolis", "attraction": "Minneapolis Institute of Art, Minneapolis; Mill City Museum, Minneapolis;", "lunch": "Malo, Minneapolis", "dinner": "Troll Tavern, Minneapolis", "accommodation": "ROOM TWO, Minneapolis"}, {"day": 3, "current_city": "from Minneapolis to Gustavus", "transportation": "Taxi, from Minneapolis to Gustavus, Duration: 1 hour 9 mins, Cost: 110", "breakfast": "-", "attraction": "Glacier Bay National Park Visitor Center, Gustavus;", "lunch": "Hofer's Bakery & Cafe, Gustavus", "dinner": "That Madras Place, Gustavus", "accommodation": "Large Private Room in 3 bdr apt-East Village, Gustavus"}, {"day": 4, "current_city": "Gustavus", "transportation": "-", "breakfast": "Hofer's Bakery & Cafe, Gustavus", "attraction": "NatVenture Tours, Gustavus; Sea Wolf Adventures, Gustavus;", "lunch": "On The Rocks - The Atrium, Gustavus", "dinner": "Tobasco Kitchen, Gustavus", "accommodation": "Large Private Room in 3 bdr apt-East Village, Gustavus"}, {"day": 5, "current_city": "from Gustavus to Memphis", "transportation": "Self-driving, from Gustavus to Memphis, Duration: 12 hours 3 mins, Cost: 64", "breakfast": "-", "attraction": "-", "lunch": "-", "dinner": "-", "accommodation": "-"}]}]