[{"gpt-4-1106-preview_direct_sole-planning_results": "Travel Plan:\nDay 1:\nCurrent City: from Fort Lauderdale to Milwaukee\nTransportation: Self-driving, from Fort Lauderdale to Milwaukee, Duration: 21 hours 8 mins, Distance: 2,340 km, Cost: $117\nBreakfast: -\nAttraction: -\nLunch: -\nDinner: -\nAccommodation: Affordable bedroom in the East Village!, Milwaukee, Price: $184, Room Type: Private room\n\nDay 2:\nCurrent City: Milwaukee\nTransportation: -\nBreakfast: Cool Basil, Milwaukee, Average Cost: $40, Cuisines: Chinese, Pizza, French, Fast Food, Cafe, Aggregate Rating: 4.1\nAttraction: Milwaukee Art Museum, Milwaukee, Address: 700 N Art Museum Dr, Milwaukee, WI 53202, USA\nLunch: The Chinese Kitchen, Milwaukee, Average Cost: $23, Cuisines: Fast Food, Bakery, Mediterranean, Italian, Aggregate Rating: 3.1\nDinner: Shankar Sweets, Milwaukee, Average Cost: $66, Cuisines: Tea, Bakery, Pizza, Fast Food, Aggregate Rating: 0.0\nAccommodation: Affordable bedroom in the East Village!, Milwaukee, Price: $184, Room Type: Private room\n\nDay 3:\nCurrent City: from Milwaukee to Fort Lauderdale\nTransportation: Flight Number: F3942425, from Milwaukee to Fort Lauderdale, Price: $289, Departure Time: 06:07, Arrival Time: 10:25, ActualElapsedTime: 3 hours 18 minutes\nBreakfast: -\nAttraction: Milwaukee Public Museum, Milwaukee, Address: 800 W Wells St, Milwaukee, WI 53233, USA\nLunch: Berco's, Milwaukee, Average Cost: $91, Cuisines: Desserts, Pizza, Italian, Cafe, Seafood, Aggregate Rating: 3.8\nDinner: -\nAccommodation: -\n\nTotal Estimated Costs:\nSelf-driving to Milwaukee: $117\nAccommodation (2 nights): $184 x 2 = $368\nFlight to Fort Lauderdale: $289\nMeals and Attractions (Estimated): $40 (Breakfast) + $23 (Lunch) + $66 (Dinner) + $91 (Lunch) = $220\nTotal: $117 + $368 + $289 + $220 = $994\n\nRemaining Budget: $1,100 - $994 = $106\n\nNote: The remaining budget can be used for additional meals, attractions, or any incidental expenses. The dinner on Day 2 is chosen from a restaurant with an unknown aggregate rating due to budget constraints. The breakfast and dinner on Day 3 are not included due to the early flight and the assumption that meals will be had upon arrival in Fort Lauderdale or during the flight.", "gpt-4-1106-preview_direct_sole-planning_parsed_results": [{"day": 1, "current_city": "from Fort Lauderdale to Milwaukee", "transportation": "Self-driving, from Fort Lauderdale to Milwaukee, Duration: 21 hours 8 mins, Distance: 2340 km, Cost: 117", "breakfast": "-", "attraction": "-", "lunch": "-", "dinner": "-", "accommodation": "Affordable bedroom in the East Village!, Milwaukee"}, {"day": 2, "current_city": "Milwaukee", "transportation": "-", "breakfast": "Cool Basil, Milwaukee", "attraction": "Milwaukee Art Museum, Milwaukee", "lunch": "The Chinese Kitchen, Milwaukee", "dinner": "Shankar Sweets, Milwaukee", "accommodation": "Affordable bedroom in the East Village!, Milwaukee"}, {"day": 3, "current_city": "from Milwaukee to Fort Lauderdale", "transportation": "Flight Number: F3942425, from Milwaukee to Fort Lauderdale, Departure Time: 06:07, Arrival Time: 10:25, Cost: 289", "breakfast": "-", "attraction": "Milwaukee Public Museum, Milwaukee", "lunch": "Berco's, Milwaukee", "dinner": "-", "accommodation": "-"}]}]