[{"gpt-4-1106-preview_direct_sole-planning_results": "Travel Plan:\nDay 1: March 8, 2022\nCurrent City: from Louisville to Pellston\nTransportation: Self-driving, from Louisville to Pellston, duration: 8 hours 24 mins, distance: 939 km, cost: $46\nBreakfast: -\nLunch: -\nDinner: Johnnie Mars, Pellston (Average Cost: $33)\nAccommodation: Beautiful apartment ~25min from Times Square, Pellston (Price: $571, Room Type: Entire home/apt)\n\nDay 2: March 9, 2022\nCurrent City: Pellston\nTransportation: -\nBreakfast: Aroos Damascus, Pellston (Average Cost: $44)\nAttraction: Pellston Pioneer Park, Pellston\nLunch: Sagar Gaire Fast Food, Pellston (Average Cost: $64)\nDinner: The Great Kabab Factory - Park Plaza, Pellston (Average Cost: $84)\nAccommodation: Beautiful apartment ~25min from Times Square, Pellston (Price: $571, Room Type: Entire home/apt)\n\nDay 3: March 10, 2022\nCurrent City: from Pellston to Kalamazoo\nTransportation: Self-driving, from Pellston to Kalamazoo, duration: 4 hours 4 mins, distance: 407 km, cost: $20\nBreakfast: The Plaza Solitaire, Pellston (Average Cost: $72)\nAttraction: Pellston Historical Society Museum, Pellston\nLunch: Premier Bite, Pellston (Average Cost: $53)\nDinner: Django, Kalamazoo (Average Cost: $65)\nAccommodation: East 63rd street, Studio Serviced Apartment, Kalamazoo (Price: $417, Room Type: Entire home/apt)\n\nDay 4: March 11, 2022\nCurrent City: Kalamazoo\nTransportation: -\nBreakfast: Giulios Greek & Italian Restaurant, Kalamazoo (Average Cost: $76)\nAttraction: Kalamazoo Valley Museum, Kalamazoo\nLunch: Cha cTea, Kalamazoo (Average Cost: $77)\nDinner: Taco Bell, Kalamazoo (Average Cost: $54)\nAccommodation: East 63rd street, Studio Serviced Apartment, Kalamazoo (Price: $417, Room Type: Entire home/apt)\n\nDay 5: March 12, 2022\nCurrent City: from Kalamazoo to Detroit\nTransportation: Flight Number: F3639554, from Kalamazoo to Detroit, Departure Time: 05:26, Arrival Time: 06:54, Price: $54\nBreakfast: Oxy Lounge, Kalamazoo (Average Cost: $65)\nAttraction: Kalamazoo Institute of Arts, Kalamazoo\nLunch: Tamasha In Tafree, Kalamazoo (Average Cost: $11)\nDinner: Southern Bliss Bakery, Detroit (Average Cost: $28)\nAccommodation: Comfy King Bed Feet from Subway, Detroit (Price: $568, Room Type: Private room)\n\nDay 6: March 13, 2022\nCurrent City: Detroit\nTransportation: -\nBreakfast: A Dong Restaurant, Detroit (Average Cost: $40)\nAttraction: Detroit Institute of Arts, Detroit\nLunch: Chye Seng Huat Hardware, Detroit (Average Cost: $94)\nDinner: BMG - All Day Dining, Detroit (Average Cost: $15)\nAccommodation: Comfy King Bed Feet from Subway, Detroit (Price: $568, Room Type: Private room)\n\nDay 7: March 14, 2022\nCurrent City: from Detroit to Louisville\nTransportation: Flight Number: F3831148, from Detroit to Louisville, Departure Time: 20:55, Arrival Time: 22:12, Price: $103\nBreakfast: Cafe And More, Detroit (Average Cost: $41)\nAttraction: Detroit Historical Museum, Detroit\nLunch: Mitalis Kitchen, Detroit (Average Cost: $28)\nDinner: -\nAccommodation: -\n\nTotal Estimated Costs:\nTransportation: $46 (self-driving to Pellston) + $20 (self-driving to Kalamazoo) + $54 (flight to Detroit) + $103 (flight to Louisville) = $223\nAccommodation: $571 x 2 (Pellston) + $417 x 2 (Kalamazoo) + $568 x 2 (Detroit) = $3,150\nMeals and Attractions: Variable (to be calculated based on choices from the restaurants and attractions listed, ensuring the total does not exceed the remaining budget of $16,027)\n\nNote: The costs for meals and attractions are not fully calculated in this plan. The remaining budget after accounting for transportation and accommodation should be allocated to cover these expenses, ensuring the total cost does not exceed the budget of $19,400. Prices for meals are based on average costs per person at each restaurant, and the group should manage their spending according to the budget.", "gpt-4-1106-preview_direct_sole-planning_parsed_results": [{"day": 1, "current_city": "from Louisville to Pellston", "transportation": "Self-driving, from Louisville to Pellston, duration: 8 hours 24 mins, distance: 939 km, Cost: 46", "breakfast": "-", "attraction": "-", "lunch": "-", "dinner": "Johnnie Mars, Pellston", "accommodation": "Beautiful apartment ~25min from Times Square, Pellston"}, {"day": 2, "current_city": "Pellston", "transportation": "-", "breakfast": "Aroos Damascus, Pellston", "attraction": "Pellston Pioneer Park, Pellston;", "lunch": "Sagar Gaire Fast Food, Pellston", "dinner": "The Great Kabab Factory - Park Plaza, Pellston", "accommodation": "Beautiful apartment ~25min from Times Square, Pellston"}, {"day": 3, "current_city": "from Pellston to Kalamazoo", "transportation": "Self-driving, from Pellston to Kalamazoo, duration: 4 hours 4 mins, distance: 407 km, Cost: 20", "breakfast": "The Plaza Solitaire, Pellston", "attraction": "Pellston Historical Society Museum, Pellston;", "lunch": "Premier Bite, Pellston", "dinner": "Django, Kalamazoo", "accommodation": "East 63rd street, Studio Serviced Apartment, Kalamazoo"}, {"day": 4, "current_city": "Kalamazoo", "transportation": "-", "breakfast": "Giulios Greek & Italian Restaurant, Kalamazoo", "attraction": "Kalamazoo Valley Museum, Kalamazoo;", "lunch": "Cha cTea, Kalamazoo", "dinner": "Taco Bell, Kalamazoo", "accommodation": "East 63rd street, Studio Serviced Apartment, Kalamazoo"}, {"day": 5, "current_city": "from Kalamazoo to Detroit", "transportation": "Flight Number: F3639554, from Kalamazoo to Detroit, Departure Time: 05:26, Arrival Time: 06:54, Cost: 54", "breakfast": "Oxy Lounge, Kalamazoo", "attraction": "Kalamazoo Institute of Arts, Kalamazoo;", "lunch": "Tamasha In Tafree, Kalamazoo", "dinner": "Southern Bliss Bakery, Detroit", "accommodation": "Comfy King Bed Feet from Subway, Detroit"}, {"day": 6, "current_city": "Detroit", "transportation": "-", "breakfast": "A Dong Restaurant, Detroit", "attraction": "Detroit Institute of Arts, Detroit;", "lunch": "Chye Seng Huat Hardware, Detroit", "dinner": "BMG - All Day Dining, Detroit", "accommodation": "Comfy King Bed Feet from Subway, Detroit"}, {"day": 7, "current_city": "from Detroit to Louisville", "transportation": "Flight Number: F3831148, from Detroit to Louisville, Departure Time: 20:55, Arrival Time: 22:12, Cost: 103", "breakfast": "Cafe And More, Detroit", "attraction": "Detroit Historical Museum, Detroit;", "lunch": "Mitalis Kitchen, Detroit", "dinner": "-", "accommodation": "-"}]}]