[{"gpt-4-1106-preview_direct_sole-planning_results": "Travel Plan:\nDay 1:\nCurrent City: from St. Petersburg to Rockford\nTransportation: Flight Number: F3573659, from St. Petersburg to Rockford, Departure Time: 15:40, Arrival Time: 17:04\nBreakfast: -\nLunch: -\nDinner: Coco Bambu, Rockford (Average Cost: $72)\nAccommodation: Private Room in a two bedroom apt., Rockford (Price: $210 per night)\n\nDay 2:\nCurrent City: Rockford\nTransportation: -\nBreakfast: Dunkin' Donuts, Rockford (Average Cost: $24)\nAttraction: Anderson Japanese Gardens, Rockford; Burpee Museum of Natural History, Rockford.\nLunch: Flying Mango, Rockford (Average Cost: $20)\nDinner: Cafe Southall, Rockford (Average Cost: $56)\nAccommodation: Private Room in a two bedroom apt., Rockford (Price: $210 per night)\n\nDay 3:\nCurrent City: from Rockford to St. Petersburg\nTransportation: Flight Number: F3573120, from Rockford to St. Petersburg, Departure Time: 19:00, Arrival Time: 22:43\nBreakfast: Subway, Rockford (Average Cost: $26)\nAttraction: Discovery Center Museum, Rockford.\nLunch: Moets Arabica, Rockford (Average Cost: $43)\nDinner: -\nAccommodation: -\n\nTotal Estimated Costs:\nFlight to Rockford: $474\nFlight from Rockford: $346\nAccommodation: $210 x 2 nights = $420\nDinner Day 1: $72\nBreakfast Day 2: $24\nLunch Day 2: $20\nDinner Day 2: $56\nBreakfast Day 3: $26\nLunch Day 3: $43\nTotal: $1481\n\nRemaining Budget: $1700 - $1481 = $219\n\nNote: The remaining budget can be used for additional meals, local transportation, or any other personal expenses. Prices for meals are based on the average cost from the provided restaurant data. The accommodation choice is within the budget and review rate, and the room type fits a single person. Attractions were chosen based on proximity and variety, ensuring a rich experience of Rockford's cultural and natural offerings.", "gpt-4-1106-preview_direct_sole-planning_parsed_results": [{"day": 1, "current_city": "from St. Petersburg to Rockford", "transportation": "Flight Number: F3573659, from St. Petersburg to Rockford, Departure Time: 15:40, Arrival Time: 17:04", "breakfast": "-", "attraction": "-", "lunch": "-", "dinner": "Coco Bambu, Rockford", "accommodation": "Private Room in a two bedroom apt., Rockford"}, {"day": 2, "current_city": "Rockford", "transportation": "-", "breakfast": "Dunkin' Donuts, Rockford", "attraction": "Anderson Japanese Gardens, Rockford;Burpee Museum of Natural History, Rockford;", "lunch": "Flying Mango, Rockford", "dinner": "Cafe Southall, Rockford", "accommodation": "Private Room in a two bedroom apt., Rockford"}, {"day": 3, "current_city": "from Rockford to St. Petersburg", "transportation": "Flight Number: F3573120, from Rockford to St. Petersburg, Departure Time: 19:00, Arrival Time: 22:43", "breakfast": "Subway, Rockford", "attraction": "Discovery Center Museum, Rockford.", "lunch": "Moets Arabica, Rockford", "dinner": "-", "accommodation": "-"}]}]