[{"gpt-4-1106-preview_direct_sole-planning_results": "Travel Plan:\n\nDay 1: March 25, 2022\nCurrent City: from Santa Ana to Abilene\nTransportation: Self-driving, from Santa Ana to Abilene, Duration: 18 hours 6 mins, Distance: 2,002 km, Cost: $100\nBreakfast: -\nAttraction: -\nLunch: -\nDinner: -\nAccommodation: Joyce and Donovan's, Room for One, Abilene (Children under 10 allowed, considering the group can book multiple rooms)\n\nDay 2: March 26, 2022\nCurrent City: Abilene\nTransportation: -\nBreakfast: Thai Garden, Abilene\nAttraction: The Grace Museum, Abilene; Frontier Texas!, Abilene\nLunch: Crispy Crust, Abilene\nDinner: Finger Licious, Abilene\nAccommodation: Joyce and Donovan's, Room for One, Abilene\n\nDay 3: March 27, 2022\nCurrent City: from Abilene to Amarillo\nTransportation: Self-driving, from Abilene to Amarillo, Duration: 4 hours 10 mins, Distance: 446 km, Cost: $22\nBreakfast: Thai Garden, Abilene\nAttraction: Cadillac Ranch, Amarillo; Amarillo Botanical Gardens, Amarillo\nLunch: The Cinnamon Kitchen, Amarillo\nDinner: Komachi, Amarillo\nAccommodation: Harlem Humble Abode - 1 bedroom - Cute and Quaint, Amarillo (Children under 10 allowed)\n\nDay 4: March 28, 2022\nCurrent City: Amarillo\nTransportation: -\nBreakfast: Kanha North & South Indian Veg., Amarillo\nAttraction: Amarillo Zoo, Amarillo; Don Harrington Discovery Center, Amarillo\nLunch: Sigree Global Grill, Amarillo\nDinner: Anand Restaurant, Amarillo\nAccommodation: Harlem Humble Abode - 1 bedroom - Cute and Quaint, Amarillo\n\nDay 5: March 29, 2022\nCurrent City: from Amarillo to Lubbock\nTransportation: Self-driving, from Amarillo to Lubbock, Duration: 1 hour 47 mins, Distance: 197 km, Cost: $9\nBreakfast: Kanha North & South Indian Veg., Amarillo\nAttraction: Buddy Holly Center, Lubbock; National Ranching Heritage Center, Lubbock\nLunch: Paris 6 Classique, Lubbock\nDinner: 3 Squares Diner, Lubbock\nAccommodation: Private bedroom in UWS Apartment, Lubbock (Children under 10 allowed)\n\nDay 6: March 30, 2022\nCurrent City: Lubbock\nTransportation: -\nBreakfast: Cantinho da Gula, Lubbock\nAttraction: American Windmill Museum, Lubbock; Mackenzie Main City Park, Lubbock\nLunch: Grand Barbeque Buffet Restaurant, Lubbock\nDinner: Mosaic - Country Inn & Suites By Carlson, Lubbock\nAccommodation: Private bedroom in UWS Apartment, Lubbock\n\nDay 7: March 31, 2022\nCurrent City: from Lubbock to Santa Ana\nTransportation: Self-driving, from Lubbock to Santa Ana, Duration: 16 hours 28 mins, Distance: 1,780 km, Cost: $89\nBreakfast: Cantinho da Gula, Lubbock\nAttraction: -\nLunch: -\nDinner: -\nAccommodation: -\n\nTotal Estimated Cost Breakdown:\n- Transportation (Self-driving total): $100 + $22 + $9 + $89 = $220\n- Accommodation (Assuming an average of $100 per night per room, 2 rooms needed): $100 x 2 rooms x 6 nights = $1200\n- Meals and Attractions (Assuming an average of $50 per person per meal, 3 meals a day for 4 people, plus $20 per person for attractions): $50 x 4 people x 3 meals x 7 days + $20 x 4 people x 7 days = $4200 + $560 = $4760\n\nTotal Estimated Cost: $220 (Transportation) + $1200 (Accommodation) + $4760 (Meals and Attractions) = $6180\n\nNote: The estimated cost exceeds the budget by $380. To stay within budget, consider reducing meal costs, choosing less expensive attractions, or finding more affordable accommodation.", "gpt-4-1106-preview_direct_sole-planning_parsed_results": [{"day": 1, "current_city": "from Santa Ana to Abilene", "transportation": "Self-driving, from Santa Ana to Abilene, Duration: 18 hours 6 mins, Distance: 2002 km, Cost: 100", "breakfast": "-", "attraction": "-", "lunch": "-", "dinner": "-", "accommodation": "Joyce and Donovan's, Room for One, Abilene"}, {"day": 2, "current_city": "Abilene", "transportation": "-", "breakfast": "Thai Garden, Abilene", "attraction": "The Grace Museum, Abilene;Frontier Texas!, Abilene;", "lunch": "Crispy Crust, Abilene", "dinner": "Finger Licious, Abilene", "accommodation": "Joyce and Donovan's, Room for One, Abilene"}, {"day": 3, "current_city": "from Abilene to Amarillo", "transportation": "Self-driving, from Abilene to Amarillo, Duration: 4 hours 10 mins, Distance: 446 km, Cost: 22", "breakfast": "Thai Garden, Abilene", "attraction": "Cadillac Ranch, Amarillo;Amarillo Botanical Gardens, Amarillo;", "lunch": "The Cinnamon Kitchen, Amarillo", "dinner": "Komachi, Amarillo", "accommodation": "Harlem Humble Abode - 1 bedroom - Cute and Quaint, Amarillo"}, {"day": 4, "current_city": "Amarillo", "transportation": "-", "breakfast": "Kanha North & South Indian Veg., Amarillo", "attraction": "Amarillo Zoo, Amarillo;Don Harrington Discovery Center, Amarillo;", "lunch": "Sigree Global Grill, Amarillo", "dinner": "Anand Restaurant, Amarillo", "accommodation": "Harlem Humble Abode - 1 bedroom - Cute and Quaint, Amarillo"}, {"day": 5, "current_city": "from Amarillo to Lubbock", "transportation": "Self-driving, from Amarillo to Lubbock, Duration: 1 hour 47 mins, Distance: 197 km, Cost: 9", "breakfast": "Kanha North & South Indian Veg., Amarillo", "attraction": "Buddy Holly Center, Lubbock;National Ranching Heritage Center, Lubbock;", "lunch": "Paris 6 Classique, Lubbock", "dinner": "3 Squares Diner, Lubbock", "accommodation": "Private bedroom in UWS Apartment, Lubbock"}, {"day": 6, "current_city": "Lubbock", "transportation": "-", "breakfast": "Cantinho da Gula, Lubbock", "attraction": "American Windmill Museum, Lubbock;Mackenzie Main City Park, Lubbock;", "lunch": "Grand Barbeque Buffet Restaurant, Lubbock", "dinner": "Mosaic - Country Inn & Suites By Carlson, Lubbock", "accommodation": "Private bedroom in UWS Apartment, Lubbock"}, {"day": 7, "current_city": "from Lubbock to Santa Ana", "transportation": "Self-driving, from Lubbock to Santa Ana, Duration: 16 hours 28 mins, Distance: 1780 km, Cost: 89", "breakfast": "Cantinho da Gula, Lubbock", "attraction": "-", "lunch": "-", "dinner": "-", "accommodation": "-"}]}]