[{"gpt-4-1106-preview_direct_sole-planning_results": "Travel Plan:\n\nDay 1: March 16, 2022\nCurrent City: from Fort Lauderdale to Norfolk\nTransportation: Self-driving, from Fort Lauderdale to Norfolk, Duration: 13 hours 26 mins, Distance: 1,510 km, Cost: $75\nBreakfast: -\nLunch: -\nDinner: Sunshine Family Restaurant, Norfolk (American cuisine)\nAccommodation: Airports Sleep Inn, Norfolk (Price: $697, Room Type: Private room)\n\nDay 2: March 17, 2022\nCurrent City: Norfolk\nTransportation: -\nBreakfast: Sunshine Family Restaurant, Norfolk\nAttraction: Norfolk Botanical Garden, Norfolk; Chrysler Museum of Art, Norfolk\nLunch: Henry Campbell's Steakhouse, Norfolk (French cuisine)\nDinner: Jonathan's Kitchen - Holiday Inn Express & Suites, Norfolk (American cuisine)\nAccommodation: Airports Sleep Inn, Norfolk (Price: $697, Room Type: Private room)\n\nDay 3: March 18, 2022\nCurrent City: from Norfolk to Fort Lauderdale\nTransportation: Self-driving, from Norfolk to Fort Lauderdale, Duration: 13 hours 30 mins, Distance: 1,513 km, Cost: $75\nBreakfast: -\nAttraction: -\nLunch: -\nDinner: -\nAccommodation: -\n\nTotal Estimated Costs:\nTransportation (Self-driving to and from Norfolk): $150\nAccommodation (2 nights at Airports Sleep Inn): $1394\nMeals and Attractions: Estimated $756 (remaining budget)\n\nNote: The meal and attraction costs are estimated to fit within the remaining budget after accounting for transportation and accommodation. Actual prices may vary, and it is recommended to book in advance and check for the latest prices and availability. The travel plan does not include specific meal times or attraction visit durations, as these can be adjusted based on personal preferences and operating hours.", "gpt-4-1106-preview_direct_sole-planning_parsed_results": [{"day": 1, "current_city": "from Fort Lauderdale to Norfolk", "transportation": "Self-driving, from Fort Lauderdale to Norfolk, Duration: 13 hours 26 mins, Distance: 1,510 km, Cost: 75", "breakfast": "-", "lunch": "-", "dinner": "Sunshine Family Restaurant, Norfolk", "accommodation": "Airports Sleep Inn, Norfolk"}, {"day": 2, "current_city": "Norfolk", "transportation": "-", "breakfast": "Sunshine Family Restaurant, Norfolk", "attraction": "Norfolk Botanical Garden, Norfolk;Chrysler Museum of Art, Norfolk;", "lunch": "Henry Campbell's Steakhouse, Norfolk", "dinner": "Jonathan's Kitchen - Holiday Inn Express & Suites, Norfolk", "accommodation": "Airports Sleep Inn, Norfolk"}, {"day": 3, "current_city": "from Norfolk to Fort Lauderdale", "transportation": "Self-driving, from Norfolk to Fort Lauderdale, Duration: 13 hours 30 mins, Distance: 1,513 km, Cost: 75", "breakfast": "-", "attraction": "-", "lunch": "-", "dinner": "-", "accommodation": "-"}]}]