[{"gpt-4-1106-preview_direct_sole-planning_results": "Travel Plan:\n\nDay 1: March 15, 2022\nCurrent City: from Washington to Orlando\nTransportation: Flight Number: F3755232, from Washington to Orlando, Departure Time: 06:54, Arrival Time: 09:10\nBreakfast: - (Assuming breakfast will be had before the flight or during the flight if available)\nAttraction: The Wheel at ICON Park, Orlando\nLunch: Fuji Japanese Steakhouse, Orlando\nDinner: Turquoise Villa, Orlando\nAccommodation: Sixth Ave Chelsea, Studio Serviced Apartment, Orlando\n\nDay 2: March 16, 2022\nCurrent City: Orlando\nTransportation: -\nBreakfast: Indochi Cafe & Restaurant, Orlando\nAttraction: Universal Orlando Resort, Orlando; The Wizarding World of Harry Potter - Diagon Alley, Orlando\nLunch: The Tandoori Times, Orlando\nDinner: Crust N Cakes, Orlando\nAccommodation: Sixth Ave Chelsea, Studio Serviced Apartment, Orlando\n\nDay 3: March 17, 2022\nCurrent City: from Orlando to Washington\nTransportation: Flight Number: F3910463, from Orlando to Washington, Departure Time: 06:59, Arrival Time: 09:01\nBreakfast: - (Assuming breakfast will be had before the flight or during the flight if available)\nAttraction: Gatorland, Orlando (Depending on time before the flight)\nLunch: - (Assuming lunch will be had after arrival in Washington or during the flight if available)\nDinner: - (After arrival back in Washington)\nAccommodation: -\n\nPlease note that the flight prices, restaurant average costs, and accommodation prices have been considered to ensure the total budget does not exceed $2,000. Breakfast and lunch on the last day are not planned due to the early flight, and travelers are expected to have returned to Washington by dinner time.", "gpt-4-1106-preview_direct_sole-planning_parsed_results": [{"day": 1, "current_city": "from Washington to Orlando", "transportation": "Flight Number: F3755232, from Washington to Orlando, Departure Time: 06:54, Arrival Time: 09:10", "breakfast": "-", "attraction": "The Wheel at ICON Park, Orlando", "lunch": "Fuji Japanese Steakhouse, Orlando", "dinner": "Turquoise Villa, Orlando", "accommodation": "Sixth Ave Chelsea, Studio Serviced Apartment, Orlando"}, {"day": 2, "current_city": "Orlando", "transportation": "-", "breakfast": "Indochi Cafe & Restaurant, Orlando", "attraction": "Universal Orlando Resort, Orlando; The Wizarding World of Harry Potter - Diagon Alley, Orlando", "lunch": "The Tandoori Times, Orlando", "dinner": "Crust N Cakes, Orlando", "accommodation": "Sixth Ave Chelsea, Studio Serviced Apartment, Orlando"}, {"day": 3, "current_city": "from Orlando to Washington", "transportation": "Flight Number: F3910463, from Orlando to Washington, Departure Time: 06:59, Arrival Time: 09:01", "breakfast": "-", "attraction": "Gatorland, Orlando", "lunch": "-", "dinner": "-", "accommodation": "-"}]}]