[{"gpt-4-1106-preview_direct_sole-planning_results": "Travel Plan:\n\nDay 1: March 20, 2022\nCurrent City: from Greensboro to Buffalo\nTransportation: Self-driving, duration: 9 hours 40 mins, cost: $51\nBreakfast: -\nLunch: -\nDinner: Shokitini, Buffalo (Chinese cuisine)\nAccommodation: Cozy Studio in Heart of Ft Greene, Buffalo (price: $200)\n\nDay 2: March 21, 2022\nCurrent City: Buffalo\nTransportation: -\nBreakfast: Punjab Grill, Buffalo (Indian cuisine)\nAttraction: The Buffalo Zoo, Buffalo\nLunch: Tibby's New Orleans Kitchen, Buffalo (French cuisine)\nAttraction: Buffalo and Erie County Botanical Gardens, Buffalo\nDinner: Red Mango, Buffalo (American cuisine)\nAccommodation: Cozy Studio in Heart of Ft Greene, Buffalo (price: $200)\n\nDay 3: March 22, 2022\nCurrent City: from Buffalo to Niagara Falls\nTransportation: Self-driving, duration: 26 mins, cost: $1\nBreakfast: -\nAttraction: Journey Behind the Falls, Niagara Falls\nLunch: Tony Roma's, Niagara Falls (American cuisine)\nAttraction: Niagara SkyWheel, Niagara Falls\nDinner: Izakaya Kikufuji, Niagara Falls (Chinese cuisine)\nAccommodation: Sunny Bedroom In The Heart of Bushwick, Niagara Falls (price: $893)\n\nDay 4: March 23, 2022\nCurrent City: Niagara Falls\nTransportation: -\nBreakfast: Barista Creme Lavazza, Niagara Falls (French cuisine)\nAttraction: Cave of the Winds, Niagara Falls\nLunch: Raju Dhaba, Niagara Falls (Indian cuisine)\nAttraction: White Water Walk, Niagara Falls\nDinner: Scratch, Niagara Falls (American cuisine)\nAccommodation: Sunny Bedroom In The Heart of Bushwick, Niagara Falls (price: $893)\n\nDay 5: March 24, 2022\nCurrent City: from Niagara Falls to New York\nTransportation: Self-driving, duration: 6 hours 29 mins, cost: $32\nBreakfast: -\nLunch: -\nDinner: Seasons 52 Fresh Grill, New York (French cuisine)\nAccommodation: A Contemporary Homelike Stay in the Best of BK, New York (price: $228)\n\nDay 6: March 25, 2022\nCurrent City: New York\nTransportation: -\nBreakfast: Lord of the Drinks Forum, New York (Indian cuisine)\nAttraction: Top of The Rock, New York\nLunch: Gurgaon Hights, New York (American cuisine)\nAttraction: Central Park, New York\nDinner: Green Chick Chop, New York (Chinese cuisine)\nAccommodation: A Contemporary Homelike Stay in the Best of BK, New York (price: $228)\n\nDay 7: March 26, 2022\nCurrent City: from New York to Greensboro\nTransportation: Self-driving, duration: 8 hours 19 mins, cost: $43\nBreakfast: -\nLunch: -\nDinner: -\nAccommodation: -\n\nTotal Estimated Costs:\nAccommodations: $2,642 (6 nights)\nTransportation: $127 (Self-driving)\nFood & Attractions: Estimated $1,031 (Assuming an average of $50 per meal for 2 people, 3 meals a day for 6 days, plus $100 for attractions)\nTotal: $3,800\n\nNote: The costs for food and attractions are estimated averages and may vary. The accommodation prices are based on the provided data, and the transportation costs are calculated from the self-driving option as no flights were to be taken. The plan includes a mix of Chinese, French, American, and Indian cuisines as requested.", "gpt-4-1106-preview_direct_sole-planning_parsed_results": [{"day": 1, "current_city": "from Greensboro to Buffalo", "transportation": "Self-driving, Duration: 9 hours 40 mins, Cost: 51", "breakfast": "-", "attraction": "-", "lunch": "-", "dinner": "Shokitini, Buffalo", "accommodation": "Cozy Studio in Heart of Ft Greene, Buffalo"}, {"day": 2, "current_city": "Buffalo", "transportation": "-", "breakfast": "Punjab Grill, Buffalo", "attraction": "The Buffalo Zoo, Buffalo;Buffalo and Erie County Botanical Gardens, Buffalo;", "lunch": "Tibby's New Orleans Kitchen, Buffalo", "dinner": "Red Mango, Buffalo", "accommodation": "Cozy Studio in Heart of Ft Greene, Buffalo"}, {"day": 3, "current_city": "from Buffalo to Niagara Falls", "transportation": "Self-driving, Duration: 26 mins, Cost: 1", "breakfast": "-", "attraction": "Journey Behind the Falls, Niagara Falls;Niagara SkyWheel, Niagara Falls;", "lunch": "Tony Roma's, Niagara Falls", "dinner": "Izakaya Kikufuji, Niagara Falls", "accommodation": "Sunny Bedroom In The Heart of Bushwick, Niagara Falls"}, {"day": 4, "current_city": "Niagara Falls", "transportation": "-", "breakfast": "Barista Creme Lavazza, Niagara Falls", "attraction": "Cave of the Winds, Niagara Falls;White Water Walk, Niagara Falls;", "lunch": "Raju Dhaba, Niagara Falls", "dinner": "Scratch, Niagara Falls", "accommodation": "Sunny Bedroom In The Heart of Bushwick, Niagara Falls"}, {"day": 5, "current_city": "from Niagara Falls to New York", "transportation": "Self-driving, Duration: 6 hours 29 mins, Cost: 32", "breakfast": "-", "attraction": "-", "lunch": "-", "dinner": "Seasons 52 Fresh Grill, New York", "accommodation": "A Contemporary Homelike Stay in the Best of BK, New York"}, {"day": 6, "current_city": "New York", "transportation": "-", "breakfast": "Lord of the Drinks Forum, New York", "attraction": "Top of The Rock, New York;Central Park, New York;", "lunch": "Gurgaon Hights, New York", "dinner": "Green Chick Chop, New York", "accommodation": "A Contemporary Homelike Stay in the Best of BK, New York"}, {"day": 7, "current_city": "from New York to Greensboro", "transportation": "Self-driving, Duration: 8 hours 19 mins, Cost: 43", "breakfast": "-", "attraction": "-", "lunch": "-", "dinner": "-", "accommodation": "-"}]}]