[{"gpt-4-1106-preview_direct_sole-planning_results": "Travel Plan:\n\nDay 1: March 19, 2022\nCurrent City: from Moline to Abilene\nTransportation: Self-driving, Duration: 14 hours 27 mins, Distance: 1,618 km, Cost: $80\nBreakfast: -\nLunch: -\nDinner: Thai Garden, Abilene (Cafe, American, Desserts)\nAccommodation: Apartment minutes from manhattan, Abilene (Entire home/apt, Price: $295)\n\nDay 2: March 20, 2022\nCurrent City: Abilene\nTransportation: -\nBreakfast: Thai Garden, Abilene (Cafe, American, Desserts)\nAttraction: The Grace Museum, Abilene; Frontier Texas!, Abilene.\nLunch: Crispy Crust, Abilene (Desserts, Bakery, Cafe, American, Seafood)\nDinner: Mediumwelldone, Abilene (Tea, French, BBQ, Cafe, Seafood)\nAccommodation: Apartment minutes from manhattan, Abilene (Entire home/apt, Price: $295)\n\nDay 3: March 21, 2022\nCurrent City: from Abilene to Amarillo\nTransportation: Self-driving, Duration: 4 hours 10 mins, Distance: 446 km, Cost: $22\nBreakfast: Thai Garden, Abilene (Cafe, American, Desserts)\nAttraction: Abilene Zoo, Abilene.\nLunch: Finger Licious, Abilene (Fast Food, Cafe, BBQ, Seafood)\nDinner: The Cinnamon Kitchen, Amarillo (Desserts, Tea, Pizza, Chinese, Seafood)\nAccommodation: Gramercy Park restful, cozy, sun-filled home, Amarillo (Entire home/apt, Price: $968)\n\nDay 4: March 22, 2022\nCurrent City: Amarillo\nTransportation: -\nBreakfast: The Cinnamon Kitchen, Amarillo (Desserts, Tea, Pizza, Chinese, Seafood)\nAttraction: Cadillac Ranch, Amarillo; Amarillo Botanical Gardens, Amarillo.\nLunch: Komachi, Amarillo (Desserts, Tea, Fast Food, Chinese, Mediterranean)\nDinner: Sigree Global Grill, Amarillo (Chinese, BBQ, Cafe, Desserts)\nAccommodation: Gramercy Park restful, cozy, sun-filled home, Amarillo (Entire home/apt, Price: $968)\n\nDay 5: March 23, 2022\nCurrent City: from Amarillo to Lubbock\nTransportation: Self-driving, Duration: 1 hour 47 mins, Distance: 197 km, Cost: $9\nBreakfast: The Cinnamon Kitchen, Amarillo (Desserts, Tea, Pizza, Chinese, Seafood)\nAttraction: Amarillo Museum of Art, Amarillo.\nLunch: Anand Restaurant, Amarillo (Fast Food, Seafood, Desserts, Italian)\nDinner: Paris 6 Classique, Lubbock (Desserts, Cafe, Pizza, Mexican, BBQ, Chinese)\nAccommodation: Private bedroom in UWS Apartment, Lubbock (Private room, Price: $709)\n\nDay 6: March 24, 2022\nCurrent City: Lubbock\nTransportation: -\nBreakfast: Paris 6 Classique, Lubbock (Desserts, Cafe, Pizza, Mexican, BBQ, Chinese)\nAttraction: Buddy Holly Center, Lubbock; National Ranching Heritage Center, Lubbock.\nLunch: Grand Barbeque Buffet Restaurant, Lubbock (Tea, French, Fast Food, Cafe, Seafood)\nDinner: Sultanat, Lubbock (Chinese, Bakery, BBQ, Cafe)\nAccommodation: Private bedroom in UWS Apartment, Lubbock (Private room, Price: $709)\n\nDay 7: March 25, 2022\nCurrent City: from Lubbock to Moline\nTransportation: Self-driving, Duration: 15 hours 14 mins, Distance: 1,704 km, Cost: $85\nBreakfast: Paris 6 Classique, Lubbock (Desserts, Cafe, Pizza, Mexican, BBQ, Chinese)\nAttraction: American Windmill Museum, Lubbock.\nLunch: 3 Squares Diner, Lubbock (Pizza, Indian, Fast Food)\nDinner: -\nAccommodation: -\n\nTotal Estimated Cost: Transportation ($80 + $22 + $9 + $85 = $196) + Accommodations ($295 x 2 + $968 x 2 + $709 x 2 = $3944) + Estimated Food and Attractions ($500) = $4640\n\nNote: The estimated food and attractions cost is a rough estimate to cover meals and entry fees for attractions. The actual cost may vary. Remaining budget can be used for additional meals, attractions, or unforeseen expenses.", "gpt-4-1106-preview_direct_sole-planning_parsed_results": [{"day": 1, "current_city": "from Moline to Abilene", "transportation": "Self-driving, Duration: 14 hours 27 mins, Distance: 1,618 km, Cost: 80", "breakfast": "-", "attraction": "-", "lunch": "-", "dinner": "Thai Garden, Abilene", "accommodation": "Apartment minutes from manhattan, Abilene"}, {"day": 2, "current_city": "Abilene", "transportation": "-", "breakfast": "Thai Garden, Abilene", "attraction": "The Grace Museum, Abilene;Frontier Texas!, Abilene;", "lunch": "Crispy Crust, Abilene", "dinner": "Mediumwelldone, Abilene", "accommodation": "Apartment minutes from manhattan, Abilene"}, {"day": 3, "current_city": "from Abilene to Amarillo", "transportation": "Self-driving, Duration: 4 hours 10 mins, Distance: 446 km, Cost: 22", "breakfast": "Thai Garden, Abilene", "attraction": "Abilene Zoo, Abilene", "lunch": "Finger Licious, Abilene", "dinner": "The Cinnamon Kitchen, Amarillo", "accommodation": "Gramercy Park restful, cozy, sun-filled home, Amarillo"}, {"day": 4, "current_city": "Amarillo", "transportation": "-", "breakfast": "The Cinnamon Kitchen, Amarillo", "attraction": "Cadillac Ranch, Amarillo;Amarillo Botanical Gardens, Amarillo;", "lunch": "Komachi, Amarillo", "dinner": "Sigree Global Grill, Amarillo", "accommodation": "Gramercy Park restful, cozy, sun-filled home, Amarillo"}, {"day": 5, "current_city": "from Amarillo to Lubbock", "transportation": "Self-driving, Duration: 1 hour 47 mins, Distance: 197 km, Cost: 9", "breakfast": "The Cinnamon Kitchen, Amarillo", "attraction": "Amarillo Museum of Art, Amarillo", "lunch": "Anand Restaurant, Amarillo", "dinner": "Paris 6 Classique, Lubbock", "accommodation": "Private bedroom in UWS Apartment, Lubbock"}, {"day": 6, "current_city": "Lubbock", "transportation": "-", "breakfast": "Paris 6 Classique, Lubbock", "attraction": "Buddy Holly Center, Lubbock;National Ranching Heritage Center, Lubbock;", "lunch": "Grand Barbeque Buffet Restaurant, Lubbock", "dinner": "Sultanat, Lubbock", "accommodation": "Private bedroom in UWS Apartment, Lubbock"}, {"day": 7, "current_city": "from Lubbock to Moline", "transportation": "Self-driving, Duration: 15 hours 14 mins, Distance: 1,704 km, Cost: 85", "breakfast": "Paris 6 Classique, Lubbock", "attraction": "American Windmill Museum, Lubbock", "lunch": "3 Squares Diner, Lubbock", "dinner": "-", "accommodation": "-"}]}]