[{"gpt-4-1106-preview_direct_sole-planning_results": "Travel Plan:\nDay 1:\nCurrent City: from Las Vegas to Denver\nTransportation: Flight Number: F3877524, from Las Vegas to Denver, Departure Time: 13:49, Arrival Time: 16:29\nBreakfast: -\nAttraction: Denver Art Museum, Denver\nLunch: The Urban Socialite, Denver\nDinner: The Fatty Bao - Asian Gastro Bar, Denver\nAccommodation: *NO GUEST SERVICE FEE* Luxury Studio Suite w/ Free Continental Breakfast, Denver\n\nDay 2:\nCurrent City: Denver\nTransportation: -\nBreakfast: Included with accommodation\nAttraction: Denver Zoo, Denver; Denver Botanic Gardens, Denver.\nLunch: Nukkadwala, Denver\nDinner: Cafe Diva, Denver\nAccommodation: *NO GUEST SERVICE FEE* Luxury Studio Suite w/ Free Continental Breakfast, Denver\n\nDay 3:\nCurrent City: from Denver to Las Vegas\nTransportation: Flight Number: F3563366, from Denver to Las Vegas, Departure Time: 15:57, Arrival Time: 16:45\nBreakfast: Included with accommodation\nAttraction: Denver Museum of Nature & Science, Denver.\nLunch: Woods Spice, Denver\nDinner: -\nAccommodation: -", "gpt-4-1106-preview_direct_sole-planning_parsed_results": [{"day": 1, "current_city": "from Las Vegas to Denver", "transportation": "Flight Number: F3877524, from Las Vegas to Denver, Departure Time: 13:49, Arrival Time: 16:29", "breakfast": "-", "attraction": "Denver Art Museum, Denver;", "lunch": "The Urban Socialite, Denver", "dinner": "The Fatty Bao - Asian Gastro Bar, Denver", "accommodation": "*NO GUEST SERVICE FEE* Luxury Studio Suite w/ Free Continental Breakfast, Denver"}, {"day": 2, "current_city": "Denver", "transportation": "-", "breakfast": "Included with accommodation", "attraction": "Denver Zoo, Denver;Denver Botanic Gardens, Denver;", "lunch": "Nukkadwala, Denver", "dinner": "Cafe Diva, Denver", "accommodation": "*NO GUEST SERVICE FEE* Luxury Studio Suite w/ Free Continental Breakfast, Denver"}, {"day": 3, "current_city": "from Denver to Las Vegas", "transportation": "Flight Number: F3563366, from Denver to Las Vegas, Departure Time: 15:57, Arrival Time: 16:45", "breakfast": "Included with accommodation", "attraction": "Denver Museum of Nature & Science, Denver;", "lunch": "Woods Spice, Denver", "dinner": "-", "accommodation": "-"}]}]