[{"gpt-4-1106-preview_direct_sole-planning_results": "Travel Plan:\n\nDay 1: March 13, 2022\nCurrent City: from Asheville to New York\nTransportation: Flight Number: F3641730, from Asheville to New York, Departure Time: 13:49, Arrival Time: 15:40\nBreakfast: -\nLunch: -\nDinner: Shokitini, New York (Mexican, Chinese cuisines available)\nAccommodation: Versatile private room in Harlem/Hamilton Heights!, New York\n\nDay 2: March 14, 2022\nCurrent City: New York\nTransportation: -\nBreakfast: Seasons 52 Fresh Grill, New York\nAttraction: Statue of Liberty, New York; Empire State Building, New York\nLunch: Gurgaon Hights, New York (Mexican cuisine available)\nDinner: Rambhog, New York (Chinese cuisine available)\nAccommodation: Versatile private room in Harlem/Hamilton Heights!, New York\n\nDay 3: March 15, 2022\nCurrent City: from New York to Buffalo\nTransportation: Flight Number: F3641101, from New York to Buffalo, Departure Time: 11:59, Arrival Time: 13:09\nBreakfast: -\nAttraction: The Buffalo Zoo, Buffalo; Buffalo and Erie County Botanical Gardens, Buffalo\nLunch: Tibby's New Orleans Kitchen, Buffalo (Mexican cuisine available)\nDinner: Shama Chicken Corner, Buffalo (Chinese cuisine available)\nAccommodation: Cozy Studio in Heart of Ft Greene, Buffalo\n\nDay 4: March 16, 2022\nCurrent City: Buffalo\nTransportation: -\nBreakfast: Shokitini, Buffalo (Chinese cuisine available)\nAttraction: Buffalo AKG Art Museum, Buffalo; Canalside, Buffalo\nLunch: Pinch Of Spice, Buffalo (Mexican cuisine available)\nDinner: Punjab Grill, Buffalo (Chinese cuisine available)\nAccommodation: Cozy Studio in Heart of Ft Greene, Buffalo\n\nDay 5: March 17, 2022\nCurrent City: from Buffalo to Asheville\nTransportation: Self-driving, from Buffalo to Asheville, duration: 10 hours 29 mins, distance: 1,110 km, cost: 55\nBreakfast: -\nAttraction: -\nLunch: -\nDinner: -\nAccommodation: -\n\n**Note: The accommodation prices, flight costs, and meal costs have not been provided in the data. Therefore, the selections were made based on the assumption that they fit within the budget of $4,700 for 2 people. Please ensure to check the actual prices and availability when booking.", "gpt-4-1106-preview_direct_sole-planning_parsed_results": [{"day": 1, "current_city": "from Asheville to New York", "transportation": "Flight Number: F3641730, from Asheville to New York, Departure Time: 13:49, Arrival Time: 15:40", "breakfast": "-", "attraction": "-", "lunch": "-", "dinner": "Shokitini, New York", "accommodation": "Versatile private room in Harlem/Hamilton Heights!, New York"}, {"day": 2, "current_city": "New York", "transportation": "-", "breakfast": "Seasons 52 Fresh Grill, New York", "attraction": "Statue of Liberty, New York;Empire State Building, New York;", "lunch": "Gurgaon Hights, New York", "dinner": "Rambhog, New York", "accommodation": "Versatile private room in Harlem/Hamilton Heights!, New York"}, {"day": 3, "current_city": "from New York to Buffalo", "transportation": "Flight Number: F3641101, from New York to Buffalo, Departure Time: 11:59, Arrival Time: 13:09", "breakfast": "-", "attraction": "The Buffalo Zoo, Buffalo;Buffalo and Erie County Botanical Gardens, Buffalo;", "lunch": "Tibby's New Orleans Kitchen, Buffalo", "dinner": "Shama Chicken Corner, Buffalo", "accommodation": "Cozy Studio in Heart of Ft Greene, Buffalo"}, {"day": 4, "current_city": "Buffalo", "transportation": "-", "breakfast": "Shokitini, Buffalo", "attraction": "Buffalo AKG Art Museum, Buffalo;Canalside, Buffalo;", "lunch": "Pinch Of Spice, Buffalo", "dinner": "Punjab Grill, Buffalo", "accommodation": "Cozy Studio in Heart of Ft Greene, Buffalo"}, {"day": 5, "current_city": "from Buffalo to Asheville", "transportation": "Self-driving, from Buffalo to Asheville, duration: 10 hours 29 mins, distance: 1110 km, Cost: 55", "breakfast": "-", "attraction": "-", "lunch": "-", "dinner": "-", "accommodation": "-"}]}]