[{"gpt-4-1106-preview_direct_sole-planning_results": "Travel Plan:\n\nDay 1: March 17, 2022\nCurrent City: from St. Louis to San Diego\nTransportation: Flight Number: F4025732, from St. Louis to San Diego, Departure Time: 16:42, Arrival Time: 18:31\nBreakfast: -\nLunch: -\nDinner: Open Yard, San Diego (Chinese cuisine)\nAccommodation: Spacious Room in Large 2 Bedroom Prewar Apartment, San Diego (Price: $585)\n\nDay 2: March 18, 2022\nCurrent City: San Diego\nTransportation: -\nBreakfast: Open Yard, San Diego (Chinese cuisine)\nAttraction: Cabrillo National Monument, San Diego\nLunch: Open Yard, San Diego (Chinese cuisine)\nDinner: Open Yard, San Diego (Chinese cuisine)\nAccommodation: Spacious Room in Large 2 Bedroom Prewar Apartment, San Diego (Price: $585)\n\nDay 3: March 19, 2022\nCurrent City: from San Diego to San Francisco\nTransportation: Flight Number: F3819496, from San Diego to San Francisco, Departure Time: 06:14, Arrival Time: 07:43\nBreakfast: -\nAttraction: Golden Gate Bridge, San Francisco\nLunch: Tokyo Sushi, San Francisco (American cuisine)\nDinner: Tokyo Sushi, San Francisco (American cuisine)\nAccommodation: Cozy, spacious Studio located on Upper East Side, San Francisco (Price: $756)\n\nDay 4: March 20, 2022\nCurrent City: San Francisco\nTransportation: -\nBreakfast: Tokyo Sushi, San Francisco (American cuisine)\nAttraction: Exploratorium, San Francisco\nLunch: Tokyo Sushi, San Francisco (American cuisine)\nDinner: Tokyo Sushi, San Francisco (American cuisine)\nAccommodation: Cozy, spacious Studio located on Upper East Side, San Francisco (Price: $756)\n\nDay 5: March 21, 2022\nCurrent City: from San Francisco to Long Beach\nTransportation: Self-driving, duration: 6 hours 12 mins, cost: $32\nBreakfast: Tokyo Sushi, San Francisco (American cuisine)\nAttraction: Aquarium of the Pacific, Long Beach\nLunch: Giuseppe's Pizza & Italian Specialities, Long Beach (American cuisine)\nDinner: Giuseppe's Pizza & Italian Specialities, Long Beach (American cuisine)\nAccommodation: NYC High End Upper East Side Central Park Gem Home, Long Beach (Price: $119)\n\nDay 6: March 22, 2022\nCurrent City: Long Beach\nTransportation: -\nBreakfast: Giuseppe's Pizza & Italian Specialities, Long Beach (American cuisine)\nAttraction: The Queen Mary, Long Beach\nLunch: Giuseppe's Pizza & Italian Specialities, Long Beach (American cuisine)\nDinner: Giuseppe's Pizza & Italian Specialities, Long Beach (American cuisine)\nAccommodation: NYC High End Upper East Side Central Park Gem Home, Long Beach (Price: $119)\n\nDay 7: March 23, 2022\nCurrent City: from Long Beach to St. Louis\nTransportation: Flight Number: F3986547, from Long Beach to St. Louis, Departure Time: 07:04, Arrival Time: 12:37\nBreakfast: -\nAttraction: -\nLunch: -\nDinner: -\nAccommodation: -\n\nTotal Estimated Cost Breakdown:\nFlights: $430 (St. Louis to San Diego) + $210 (San Diego to San Francisco) + $370 (Long Beach to St. Louis) = $1,010\nAccommodations: $585 (2 nights in San Diego) + $756 (2 nights in San Francisco) + $119 (2 nights in Long Beach) = $2,055\nTransportation (Self-driving from San Francisco to Long Beach): $32\nDining & Attractions: Variable, to be managed within the remaining budget of $6,403\n\nNote: Dining and attraction costs are not specified due to variability and personal choice. The remaining budget should cover these expenses, as well as any additional transportation costs within the cities. Please ensure to book restaurants and attractions in advance to secure availability and potentially better pricing.", "gpt-4-1106-preview_direct_sole-planning_parsed_results": [{"day": 1, "current_city": "from St. Louis to San Diego", "transportation": "Flight Number: F4025732, from St. Louis to San Diego, Departure Time: 16:42, Arrival Time: 18:31", "breakfast": "-", "attraction": "-", "lunch": "-", "dinner": "Open Yard, San Diego", "accommodation": "Spacious Room in Large 2 Bedroom Prewar Apartment, San Diego"}, {"day": 2, "current_city": "San Diego", "transportation": "-", "breakfast": "Open Yard, San Diego", "attraction": "Cabrillo National Monument, San Diego;", "lunch": "Open Yard, San Diego", "dinner": "Open Yard, San Diego", "accommodation": "Spacious Room in Large 2 Bedroom Prewar Apartment, San Diego"}, {"day": 3, "current_city": "from San Diego to San Francisco", "transportation": "Flight Number: F3819496, from San Diego to San Francisco, Departure Time: 06:14, Arrival Time: 07:43", "breakfast": "-", "attraction": "Golden Gate Bridge, San Francisco;", "lunch": "Tokyo Sushi, San Francisco", "dinner": "Tokyo Sushi, San Francisco", "accommodation": "Cozy, spacious Studio located on Upper East Side, San Francisco"}, {"day": 4, "current_city": "San Francisco", "transportation": "-", "breakfast": "Tokyo Sushi, San Francisco", "attraction": "Exploratorium, San Francisco;", "lunch": "Tokyo Sushi, San Francisco", "dinner": "Tokyo Sushi, San Francisco", "accommodation": "Cozy, spacious Studio located on Upper East Side, San Francisco"}, {"day": 5, "current_city": "from San Francisco to Long Beach", "transportation": "Self-driving, Duration: 6 hours 12 mins, Cost: 32", "breakfast": "Tokyo Sushi, San Francisco", "attraction": "Aquarium of the Pacific, Long Beach;", "lunch": "Giuseppe's Pizza & Italian Specialities, Long Beach", "dinner": "Giuseppe's Pizza & Italian Specialities, Long Beach", "accommodation": "NYC High End Upper East Side Central Park Gem Home, Long Beach"}, {"day": 6, "current_city": "Long Beach", "transportation": "-", "breakfast": "Giuseppe's Pizza & Italian Specialities, Long Beach", "attraction": "The Queen Mary, Long Beach;", "lunch": "Giuseppe's Pizza & Italian Specialities, Long Beach", "dinner": "Giuseppe's Pizza & Italian Specialities, Long Beach", "accommodation": "NYC High End Upper East Side Central Park Gem Home, Long Beach"}, {"day": 7, "current_city": "from Long Beach to St. Louis", "transportation": "Flight Number: F3986547, from Long Beach to St. Louis, Departure Time: 07:04, Arrival Time: 12:37", "breakfast": "-", "attraction": "-", "lunch": "-", "dinner": "-", "accommodation": "-"}]}]