[{"gpt-4-1106-preview_cot_sole-planning_results": "Travel Plan:\n\nDay 1: March 8, 2022\nCurrent City: from Louisville to Pellston\nTransportation: Self-driving, duration: 8 hours 24 mins, distance: 939 km, cost: $46 x 4 people = $184\nBreakfast: - (Assuming breakfast is had before departure)\nAttraction: - (Traveling most of the day)\nLunch: - (On the road)\nDinner: Johnnie Mars, Pellston (Average Cost: $33 per person)\nAccommodation: Beautiful apartment ~25min from Times Square, Pellston (price: $571 per night)\n\nDay 2: March 9, 2022\nCurrent City: Pellston\nTransportation: -\nBreakfast: Aroos Damascus, Pellston (Average Cost: $44 per person)\nAttraction: Pellston Pioneer Park, Pellston Historical Society Museum\nLunch: Sagar Gaire Fast Food, Pellston (Average Cost: $64 per person)\nDinner: The Great Kabab Factory - Park Plaza, Pellston (Average Cost: $84 per person)\nAccommodation: Beautiful apartment ~25min from Times Square, Pellston (price: $571 per night)\n\nDay 3: March 10, 2022\nCurrent City: from Pellston to Kalamazoo\nTransportation: Self-driving, duration: 4 hours 4 mins, distance: 407 km, cost: $20 x 4 people = $80\nBreakfast: - (Assuming breakfast is had at the accommodation)\nAttraction: - (Traveling most of the day)\nLunch: - (On the road)\nDinner: Django, Kalamazoo (Average Cost: $65 per person)\nAccommodation: East 63rd street, Studio Serviced Apartment, Kalamazoo (price: $417 per night)\n\nDay 4: March 11, 2022\nCurrent City: Kalamazoo\nTransportation: -\nBreakfast: Giulios Greek & Italian Restaurant, Kalamazoo (Average Cost: $76 per person)\nAttraction: Kalamazoo Valley Museum, Kalamazoo Institute of Arts\nLunch: Cha cTea, Kalamazoo (Average Cost: $77 per person)\nDinner: Taco Bell, Kalamazoo (Average Cost: $54 per person)\nAccommodation: East 63rd street, Studio Serviced Apartment, Kalamazoo (price: $417 per night)\n\nDay 5: March 12, 2022\nCurrent City: from Kalamazoo to Detroit\nTransportation: Flight Number: F3639554, from Kalamazoo to Detroit, Departure Time: 05:26, Arrival Time: 06:54, Price: $54 x 4 people = $216\nBreakfast: - (Assuming breakfast is had at the accommodation)\nAttraction: Detroit Institute of Arts, Detroit Historical Museum\nLunch: A Dong Restaurant, Detroit (Average Cost: $40 per person)\nDinner: Chye Seng Huat Hardware, Detroit (Average Cost: $94 per person)\nAccommodation: Cozy 1 bedroom in the heart of Fort Greene, Detroit (price: $751 per night)\n\nDay 6: March 13, 2022\nCurrent City: Detroit\nTransportation: -\nBreakfast: Southern Bliss Bakery, Detroit (Average Cost: $28 per person)\nAttraction: Campus Martius Park, Motown Museum\nLunch: BMG - All Day Dining, Detroit (Average Cost: $15 per person)\nDinner: Cafe And More, Detroit (Average Cost: $41 per person)\nAccommodation: Cozy 1 bedroom in the heart of Fort Greene, Detroit (price: $751 per night)\n\nDay 7: March 14, 2022\nCurrent City: from Detroit to Louisville\nTransportation: Flight Number: F3831148, from Detroit to Louisville, Departure Time: 20:55, Arrival Time: 22:12, Price: $103 x 4 people = $412\nBreakfast: Mitalis Kitchen, Detroit (Average Cost: $28 per person)\nAttraction: Detroit Zoo, Michigan Science Center\nLunch: Vapour Pub & Brewery, Detroit (Average Cost: $80 per person)\nDinner: - (Assuming dinner is had after arrival in Louisville)\nAccommodation: -\n\nTotal Estimated Cost Breakdown:\nAccommodations: $571 x 2 nights (Pellston) + $417 x 2 nights (Kalamazoo) + $751 x 2 nights (Detroit) = $5,478\nTransportation: $184 (to Pellston) + $80 (to Kalamazoo) + $216 (to Detroit) + $412 (return to Louisville) = $892\nMeals and Attractions: Estimated $200 per person per day x 4 people x 7 days = $5,600\nTotal Estimated Cost: $5,478 (Accommodations) + $892 (Transportation) + $5,600 (Meals/Attractions) = $11,970\n\nRemaining Budget: $19,400 - $11,970 = $7,430\n\nNote: The remaining budget can be used for additional meals, attractions, souvenirs, or unforeseen expenses. The meal costs are average and may vary. Attractions that do not have an entry fee are not included in the cost. Transportation costs are based on the provided data. Flight prices are per person.", "gpt-4-1106-preview_cot_sole-planning_parsed_results": [{"day": 1, "current_city": "from Louisville to Pellston", "transportation": "Self-driving, duration: 8 hours 24 mins, distance: 939 km, Cost: 184", "breakfast": "-", "attraction": "-", "lunch": "-", "dinner": "Johnnie Mars, Pellston", "accommodation": "Beautiful apartment ~25min from Times Square, Pellston"}, {"day": 2, "current_city": "Pellston", "transportation": "-", "breakfast": "Aroos Damascus, Pellston", "attraction": "Pellston Pioneer Park, Pellston;Pellston Historical Society Museum, Pellston;", "lunch": "Sagar Gaire Fast Food, Pellston", "dinner": "The Great Kabab Factory - Park Plaza, Pellston", "accommodation": "Beautiful apartment ~25min from Times Square, Pellston"}, {"day": 3, "current_city": "from Pellston to Kalamazoo", "transportation": "Self-driving, duration: 4 hours 4 mins, distance: 407 km, Cost: 80", "breakfast": "-", "attraction": "-", "lunch": "-", "dinner": "Django, Kalamazoo", "accommodation": "East 63rd street, Studio Serviced Apartment, Kalamazoo"}, {"day": 4, "current_city": "Kalamazoo", "transportation": "-", "breakfast": "Giulios Greek & Italian Restaurant, Kalamazoo", "attraction": "Kalamazoo Valley Museum, Kalamazoo;Kalamazoo Institute of Arts, Kalamazoo;", "lunch": "Cha cTea, Kalamazoo", "dinner": "Taco Bell, Kalamazoo", "accommodation": "East 63rd street, Studio Serviced Apartment, Kalamazoo"}, {"day": 5, "current_city": "from Kalamazoo to Detroit", "transportation": "Flight Number: F3639554, from Kalamazoo to Detroit, Departure Time: 05:26, Arrival Time: 06:54, Cost: 216", "breakfast": "-", "attraction": "Detroit Institute of Arts, Detroit;Detroit Historical Museum, Detroit;", "lunch": "A Dong Restaurant, Detroit", "dinner": "Chye Seng Huat Hardware, Detroit", "accommodation": "Cozy 1 bedroom in the heart of Fort Greene, Detroit"}, {"day": 6, "current_city": "Detroit", "transportation": "-", "breakfast": "Southern Bliss Bakery, Detroit", "attraction": "Campus Martius Park, Detroit;Motown Museum, Detroit;", "lunch": "BMG - All Day Dining, Detroit", "dinner": "Cafe And More, Detroit", "accommodation": "Cozy 1 bedroom in the heart of Fort Greene, Detroit"}, {"day": 7, "current_city": "from Detroit to Louisville", "transportation": "Flight Number: F3831148, from Detroit to Louisville, Departure Time: 20:55, Arrival Time: 22:12, Cost: 412", "breakfast": "Mitalis Kitchen, Detroit", "attraction": "Detroit Zoo, Detroit;Michigan Science Center, Detroit;", "lunch": "Vapour Pub & Brewery, Detroit", "dinner": "-", "accommodation": "-"}]}]