[{"gpt-4-1106-preview_cot_sole-planning_results": "Travel Plan:\n\nDay 1: March 17, 2022\nCurrent City: from St. Louis to San Diego\nTransportation: Flight Number: F4025732, from St. Louis to San Diego, Departure Time: 16:42, Arrival Time: 18:31\nBreakfast: - (Assuming breakfast is in St. Louis and not part of the travel plan)\nAttraction: Cabrillo National Monument, San Diego\nLunch: Open Yard, San Diego (Chinese, Pizza, Cafe, Desserts)\nDinner: Gopala, San Diego (Pizza, Mexican, BBQ, American, Seafood)\nAccommodation: Spacious Room in Large 2 Bedroom Prewar Apartment, San Diego (Price: $585)\n\nDay 2: March 18, 2022\nCurrent City: San Diego\nTransportation: -\nBreakfast: Open Yard, San Diego\nAttraction: SeaWorld San Diego; Old Town San Diego\nLunch: Bikaner Sweets, San Diego (Bakery, Pizza, Indian, Fast Food)\nDinner: The Lost Mughal, San Diego (Tea, Cafe, Italian)\nAccommodation: Spacious Room in Large 2 Bedroom Prewar Apartment, San Diego\n\nDay 3: March 19, 2022\nCurrent City: from San Diego to San Francisco\nTransportation: Flight Number: F3819496, from San Diego to San Francisco, Departure Time: 06:14, Arrival Time: 07:43\nBreakfast: - (Assuming breakfast is in San Diego before the flight)\nAttraction: Golden Gate Bridge; Exploratorium\nLunch: Tokyo Sushi, San Francisco (Cafe, Pizza, BBQ)\nDinner: The Chic, San Francisco (Chinese, Bakery, Indian, Cafe)\nAccommodation: Cozy, spacious Studio located on Upper East Side, San Francisco (Price: $756)\n\nDay 4: March 20, 2022\nCurrent City: San Francisco\nTransportation: -\nBreakfast: Bonne Bouche, San Francisco (Tea, Chinese, American, Cafe)\nAttraction: San Francisco Museum of Modern Art; Union Square\nLunch: Coffee & Chai Co., San Francisco (Tea, Mexican, BBQ, Cafe, Seafood)\nDinner: Empress, San Francisco (Pizza, BBQ, Mediterranean, Fast Food)\nAccommodation: Cozy, spacious Studio located on Upper East Side, San Francisco\n\nDay 5: March 21, 2022\nCurrent City: from San Francisco to Long Beach\nTransportation: Self-driving, duration: 6 hours 12 mins, distance: 651 km, cost: $32\nBreakfast: - (Assuming breakfast is in San Francisco before departure)\nAttraction: Aquarium of the Pacific, Long Beach\nLunch: Giuseppe's Pizza & Italian Specialities, Long Beach (Bakery, Fast Food, Cafe, Indian, Mediterranean, Seafood)\nDinner: Greek Village, Long Beach (Desserts, Italian, Bakery, BBQ, Chinese)\nAccommodation: NYC High End Upper East Side Central Park Gem Home, Long Beach (Price: $119)\n\nDay 6: March 22, 2022\nCurrent City: Long Beach\nTransportation: -\nBreakfast: Giuseppe's Pizza & Italian Specialities, Long Beach\nAttraction: The Queen Mary; ShoreLine Aquatic Park\nLunch: Fuji Bay Japanese Restaurant, Long Beach (Tea, Cafe, Mexican, Fast Food)\nDinner: The Chicken Dinesty, Long Beach (French, Pizza, Seafood)\nAccommodation: NYC High End Upper East Side Central Park Gem Home, Long Beach\n\nDay 7: March 23, 2022\nCurrent City: from Long Beach to St. Louis\nTransportation: Flight Number: F3986547, from Long Beach to St. Louis, Departure Time: 07:04, Arrival Time: 12:37\nBreakfast: - (Assuming breakfast is in Long Beach before the flight)\nAttraction: - (Assuming the rest of the day is for travel and not part of the travel plan)\nLunch: - (Assuming lunch is on the flight or after arrival in St. Louis)\nDinner: - (Assuming dinner is in St. Louis and not part of the travel plan)\nAccommodation: -\n\nPlease note that the prices for flights, accommodations, and car rental have been included where available. The costs for meals, attractions, and any additional transportation or personal expenses have not been detailed and should be considered within the remaining budget. The total cost of listed expenses (flights and accommodations) is $2,972. Remaining budget for other expenses is $6,528.", "gpt-4-1106-preview_cot_sole-planning_parsed_results": [{"day": 1, "current_city": "from St. Louis to San Diego", "transportation": "Flight Number: F4025732, from St. Louis to San Diego, Departure Time: 16:42, Arrival Time: 18:31", "breakfast": "-", "attraction": "Cabrillo National Monument, San Diego;", "lunch": "Open Yard, San Diego", "dinner": "Gopala, San Diego", "accommodation": "Spacious Room in Large 2 Bedroom Prewar Apartment, San Diego"}, {"day": 2, "current_city": "San Diego", "transportation": "-", "breakfast": "Open Yard, San Diego", "attraction": "SeaWorld San Diego;Old Town San Diego;", "lunch": "Bikaner Sweets, San Diego", "dinner": "The Lost Mughal, San Diego", "accommodation": "Spacious Room in Large 2 Bedroom Prewar Apartment, San Diego"}, {"day": 3, "current_city": "from San Diego to San Francisco", "transportation": "Flight Number: F3819496, from San Diego to San Francisco, Departure Time: 06:14, Arrival Time: 07:43", "breakfast": "-", "attraction": "Golden Gate Bridge;Exploratorium;", "lunch": "Tokyo Sushi, San Francisco", "dinner": "The Chic, San Francisco", "accommodation": "Cozy, spacious Studio located on Upper East Side, San Francisco"}, {"day": 4, "current_city": "San Francisco", "transportation": "-", "breakfast": "Bonne Bouche, San Francisco", "attraction": "San Francisco Museum of Modern Art;Union Square;", "lunch": "Coffee & Chai Co., San Francisco", "dinner": "Empress, San Francisco", "accommodation": "Cozy, spacious Studio located on Upper East Side, San Francisco"}, {"day": 5, "current_city": "from San Francisco to Long Beach", "transportation": "Self-driving, duration: 6 hours 12 mins, distance: 651 km, Cost: 32", "breakfast": "-", "attraction": "Aquarium of the Pacific, Long Beach;", "lunch": "Giuseppe's Pizza & Italian Specialities, Long Beach", "dinner": "Greek Village, Long Beach", "accommodation": "NYC High End Upper East Side Central Park Gem Home, Long Beach"}, {"day": 6, "current_city": "Long Beach", "transportation": "-", "breakfast": "Giuseppe's Pizza & Italian Specialities, Long Beach", "attraction": "The Queen Mary;ShoreLine Aquatic Park;", "lunch": "Fuji Bay Japanese Restaurant, Long Beach", "dinner": "The Chicken Dinesty, Long Beach", "accommodation": "NYC High End Upper East Side Central Park Gem Home, Long Beach"}, {"day": 7, "current_city": "from Long Beach to St. Louis", "transportation": "Flight Number: F3986547, from Long Beach to St. Louis, Departure Time: 07:04, Arrival Time: 12:37", "breakfast": "-", "attraction": "-", "lunch": "-", "dinner": "-", "accommodation": "-"}]}]