[{"gpt-4-1106-preview_cot_sole-planning_results": "Travel Plan:\n\nDay 1: March 16, 2022\nCurrent City: from Punta Gorda to Marquette\nTransportation: Self-driving, Duration: 19 hours 48 mins, Distance: 2,198 km, Cost: $109\nBreakfast: -\nLunch: -\nDinner: -\nAccommodation: Huge Private Room Near Prospect Park, Marquette, Price: $73, Room Type: Private room\n\nDay 2: March 17, 2022\nCurrent City: Marquette\nTransportation: -\nBreakfast: The Chop House, Marquette, Average Cost: $81\nAttraction: Presque Isle Park, Marquette\nLunch: Taste of Balingup, Marquette, Average Cost: $35\nAttraction: Marquette Harbor Lighthouse, Marquette\nDinner: Dovetail, Marquette, Average Cost: $95\nAccommodation: Huge Private Room Near Prospect Park, Marquette, Price: $73, Room Type: Private room\n\nDay 3: March 18, 2022\nCurrent City: from Marquette to Madison\nTransportation: Self-driving, Duration: 1 hour 17 mins, Distance: 126 km, Cost: $6\nBreakfast: Papa Mexicano, Marquette, Average Cost: $17\nAttraction: Upper Peninsula Children's Museum, Marquette\nLunch: Eat N Treat, Marquette, Average Cost: $15\nDinner: Ifthar, Marquette, Average Cost: $67\nAccommodation: Oversized bedroom with living space, Madison, Price: $908, Room Type: Private room\n\nDay 4: March 19, 2022\nCurrent City: Madison\nTransportation: -\nBreakfast: 99 North Restaurant, Madison, Average Cost: $62\nAttraction: Madison Children's Museum, Madison\nLunch: Unique Food Hut, Madison, Average Cost: $38\nAttraction: Chazen Museum of Art, Madison\nDinner: Chini Bowl, Madison, Average Cost: $26\nAccommodation: Oversized bedroom with living space, Madison, Price: $908, Room Type: Private room\n\nDay 5: March 20, 2022\nCurrent City: from Madison to Devils Lake\nTransportation: Self-driving, Duration: 56 mins, Distance: 70.7 km, Cost: $3\nBreakfast: Tibb's Frankie, Madison, Average Cost: $75\nAttraction: Olbrich Botanical Gardens, Madison\nLunch: Daawat-e! Amritsar, Madison, Average Cost: $53\nDinner: Barbeque Nation, Madison, Average Cost: $38\nAccommodation: Charming Cobble Hill Brownstone Apartment, Devils Lake, Price: $220, Room Type: Entire home/apt\n\nDay 6: March 21, 2022\nCurrent City: Devils Lake\nTransportation: -\nBreakfast: Boise Fry Company, Devils Lake, Average Cost: $99\nAttraction: Lake Region Heritage Center, Devils Lake\nLunch: AB's Absolute Barbecues, Devils Lake, Average Cost: $80\nAttraction: Roosevelt Park, Devils Lake\nDinner: Din Tai Fung, Devils Lake, Average Cost: $100\nAccommodation: Charming Cobble Hill Brownstone Apartment, Devils Lake, Price: $220, Room Type: Entire home/apt\n\nDay 7: March 22, 2022\nCurrent City: from Devils Lake to Punta Gorda\nTransportation: Self-driving, Duration: 21 hours 4 mins, Distance: 2,346 km, Cost: $117\nBreakfast: Dakshin Bistro, Devils Lake, Average Cost: $42\nLunch: -\nDinner: -\nAccommodation: -\n\nTotal Estimated Costs:\nTransportation: $109 (to Marquette) + $6 (to Madison) + $3 (to Devils Lake) + $117 (back to Punta Gorda) = $235\nAccommodation: $73 (2 nights in Marquette) + $908 (2 nights in Madison) + $220 (2 nights in Devils Lake) = $2402\nMeals and Attractions: Estimated $200 per day x 6 days = $1200\nTotal: $2402 (Accommodation) + $235 (Transportation) + $1200 (Meals/Attractions) = $3837\n\nRemaining Budget: $5700 - $3837 = $1863\n\nPlease note that the costs for meals and attractions are estimated and actual costs may vary. The remaining budget can be used for additional meals, attractions, souvenirs, or unforeseen expenses.", "gpt-4-1106-preview_cot_sole-planning_parsed_results": [{"day": 1, "current_city": "from Punta Gorda to Marquette", "transportation": "Self-driving, Duration: 19 hours 48 mins, Distance: 2198 km, Cost: 109", "breakfast": "-", "attraction": "-", "lunch": "-", "dinner": "-", "accommodation": "Huge Private Room Near Prospect Park, Marquette"}, {"day": 2, "current_city": "Marquette", "transportation": "-", "breakfast": "The Chop House, Marquette", "attraction": "Presque Isle Park, Marquette;Marquette Harbor Lighthouse, Marquette;", "lunch": "Taste of Balingup, Marquette", "dinner": "Dovetail, Marquette", "accommodation": "Huge Private Room Near Prospect Park, Marquette"}, {"day": 3, "current_city": "from Marquette to Madison", "transportation": "Self-driving, Duration: 1 hour 17 mins, Distance: 126 km, Cost: 6", "breakfast": "Papa Mexicano, Marquette", "attraction": "Upper Peninsula Children's Museum, Marquette", "lunch": "Eat N Treat, Marquette", "dinner": "Ifthar, Marquette", "accommodation": "Oversized bedroom with living space, Madison"}, {"day": 4, "current_city": "Madison", "transportation": "-", "breakfast": "99 North Restaurant, Madison", "attraction": "Madison Children's Museum, Madison;Chazen Museum of Art, Madison;", "lunch": "Unique Food Hut, Madison", "dinner": "Chini Bowl, Madison", "accommodation": "Oversized bedroom with living space, Madison"}, {"day": 5, "current_city": "from Madison to Devils Lake", "transportation": "Self-driving, Duration: 56 mins, Distance: 70.7 km, Cost: 3", "breakfast": "Tibb's Frankie, Madison", "attraction": "Olbrich Botanical Gardens, Madison", "lunch": "Daawat-e! Amritsar, Madison", "dinner": "Barbeque Nation, Madison", "accommodation": "Charming Cobble Hill Brownstone Apartment, Devils Lake"}, {"day": 6, "current_city": "Devils Lake", "transportation": "-", "breakfast": "Boise Fry Company, Devils Lake", "attraction": "Lake Region Heritage Center, Devils Lake;Roosevelt Park, Devils Lake;", "lunch": "AB's Absolute Barbecues, Devils Lake", "dinner": "Din Tai Fung, Devils Lake", "accommodation": "Charming Cobble Hill Brownstone Apartment, Devils Lake"}, {"day": 7, "current_city": "from Devils Lake to Punta Gorda", "transportation": "Self-driving, Duration: 21 hours 4 mins, Distance: 2346 km, Cost: 117", "breakfast": "Dakshin Bistro, Devils Lake", "attraction": "-", "lunch": "-", "dinner": "-", "accommodation": "-"}]}]