[{"gpt-4-1106-preview_cot_sole-planning_results": "Travel Plan:\n\nDay 1: March 1, 2022\nCurrent City: from Baton Rouge to Abilene\nTransportation: Self-driving, from Baton Rouge to Abilene, duration: 8 hours 50 mins, distance: 976 km, cost: $48\nBreakfast: -\nLunch: -\nDinner: Thai Garden, Abilene\nAccommodation: Joyce and Donovan's, Room for One, Abilene\n\nDay 2: March 2, 2022\nCurrent City: Abilene\nTransportation: -\nBreakfast: Thai Garden, Abilene\nAttraction: The Grace Museum, Abilene; Frontier Texas!, Abilene\nLunch: Crispy Crust, Abilene\nAttraction: Historic Fort Phantom Hill, Abilene\nDinner: Finger Licious, Abilene\nAccommodation: Joyce and Donovan's, Room for One, Abilene\n\nDay 3: March 3, 2022\nCurrent City: from Abilene to Amarillo\nTransportation: Self-driving, from Abilene to Amarillo, duration: 4 hours 10 mins, distance: 446 km, cost: $22\nBreakfast: Mx Corn, Abilene\nAttraction: Cadillac Ranch, Amarillo; Amarillo Botanical Gardens, Amarillo\nLunch: The Cinnamon Kitchen, Amarillo\nAttraction: Amarillo Zoo, Amarillo\nDinner: Komachi, Amarillo\nAccommodation: Harlem Humble Abode - 1 bedroom - Cute and Quaint, Amarillo\n\nDay 4: March 4, 2022\nCurrent City: Amarillo\nTransportation: -\nBreakfast: Sigree Global Grill, Amarillo\nAttraction: Don Harrington Discovery Center, Amarillo; Texas Air & Space Museum, Amarillo\nLunch: Anand Restaurant, Amarillo\nAttraction: Amarillo Museum of Art, Amarillo\nDinner: Wood Box Cafe, Amarillo\nAccommodation: Harlem Humble Abode - 1 bedroom - Cute and Quaint, Amarillo\n\nDay 5: March 5, 2022\nCurrent City: from Amarillo to Baton Rouge\nTransportation: Self-driving, from Amarillo to Baton Rouge, duration: 11 hours 42 mins, distance: 1,270 km, cost: $63\nBreakfast: Punjabi Chaap Corner, Amarillo\nLunch: -\nDinner: -\nAccommodation: -\n\nTotal Estimated Costs:\nTransportation: $48 (to Abilene) + $22 (to Amarillo) + $63 (back to Baton Rouge) = $133\nAccommodation: $83 (Abilene) x 2 nights + $409 (Amarillo) x 2 nights = $984\nMeals and Miscellaneous: $2,300 (total budget) - $133 (transportation) - $984 (accommodation) = $1,183 left for meals, attractions, and other expenses.\n\nPlease note that the prices for meals and attractions are not provided, so the remaining budget should cover these costs as well as any additional transportation within the cities (e.g., taxis, public transport). The traveler should monitor their spending to ensure they stay within budget.", "gpt-4-1106-preview_cot_sole-planning_parsed_results": [{"day": 1, "current_city": "from Baton Rouge to Abilene", "transportation": "Self-driving, from Baton Rouge to Abilene, duration: 8 hours 50 mins, distance: 976 km, Cost: 48", "breakfast": "-", "attraction": "-", "lunch": "-", "dinner": "Thai Garden, Abilene", "accommodation": "Joyce and Donovan's, Room for One, Abilene"}, {"day": 2, "current_city": "Abilene", "transportation": "-", "breakfast": "Thai Garden, Abilene", "attraction": "The Grace Museum, Abilene;Frontier Texas!, Abilene;Historic Fort Phantom Hill, Abilene;", "lunch": "Crispy Crust, Abilene", "dinner": "Finger Licious, Abilene", "accommodation": "Joyce and Donovan's, Room for One, Abilene"}, {"day": 3, "current_city": "from Abilene to Amarillo", "transportation": "Self-driving, from Abilene to Amarillo, duration: 4 hours 10 mins, distance: 446 km, Cost: 22", "breakfast": "Mx Corn, Abilene", "attraction": "Cadillac Ranch, Amarillo;Amarillo Botanical Gardens, Amarillo;Amarillo Zoo, Amarillo;", "lunch": "The Cinnamon Kitchen, Amarillo", "dinner": "Komachi, Amarillo", "accommodation": "Harlem Humble Abode - 1 bedroom - Cute and Quaint, Amarillo"}, {"day": 4, "current_city": "Amarillo", "transportation": "-", "breakfast": "Sigree Global Grill, Amarillo", "attraction": "Don Harrington Discovery Center, Amarillo;Texas Air & Space Museum, Amarillo;Amarillo Museum of Art, Amarillo;", "lunch": "Anand Restaurant, Amarillo", "dinner": "Wood Box Cafe, Amarillo", "accommodation": "Harlem Humble Abode - 1 bedroom - Cute and Quaint, Amarillo"}, {"day": 5, "current_city": "from Amarillo to Baton Rouge", "transportation": "Self-driving, from Amarillo to Baton Rouge, duration: 11 hours 42 mins, distance: 1,270 km, Cost: 63", "breakfast": "Punjabi Chaap Corner, Amarillo", "attraction": "-", "lunch": "-", "dinner": "-", "accommodation": "-"}]}]