[{"gpt-4-1106-preview_cot_sole-planning_results": "Travel Plan:\n\nDay 1: March 13, 2022\nCurrent City: from Asheville to New York\nTransportation: Flight Number: F3641730, from Asheville to New York, Departure Time: 13:49, Arrival Time: 15:40\nBreakfast: - (Assuming breakfast is had before departure)\nAttraction: Times Square, New York\nLunch: Seasons 52 Fresh Grill, New York (Mexican cuisine available)\nDinner: Shokitini, New York (Chinese cuisine available)\nAccommodation: Versatile private room in Harlem/Hamilton Heights!, New York\n\nDay 2: March 14, 2022\nCurrent City: New York\nTransportation: -\nBreakfast: Sir John Bakery Cafe, New York\nAttraction: Statue of Liberty, New York; The High Line, New York\nLunch: Gurgaon Hights, New York (Mexican cuisine available)\nDinner: Goosebumps, New York (Chinese cuisine available)\nAccommodation: Versatile private room in Harlem/Hamilton Heights!, New York\n\nDay 3: March 15, 2022\nCurrent City: from New York to Buffalo\nTransportation: Flight Number: F3641101, from New York to Buffalo, Departure Time: 11:59, Arrival Time: 13:09\nBreakfast: Green Chick Chop, New York\nAttraction: Buffalo Naval Park, Buffalo; The Buffalo Zoo, Buffalo\nLunch: Tibby's New Orleans Kitchen, Buffalo (Mexican cuisine available)\nDinner: Shama Chicken Corner, Buffalo (Chinese cuisine available)\nAccommodation: Cozy Studio in Heart of Ft Greene, Buffalo\n\nDay 4: March 16, 2022\nCurrent City: Buffalo\nTransportation: -\nBreakfast: Punjab Grill, Buffalo\nAttraction: Buffalo and Erie County Botanical Gardens, Buffalo; Frank Lloyd Wright's Martin House, Buffalo\nLunch: Red Mango, Buffalo (Mexican cuisine available)\nDinner: Chopsticks, Buffalo (Chinese cuisine available)\nAccommodation: Cozy Studio in Heart of Ft Greene, Buffalo\n\nDay 5: March 17, 2022\nCurrent City: from Buffalo to Asheville\nTransportation: Self-driving, from Buffalo to Asheville, duration: 10 hours 29 mins, distance: 1,110 km, cost: 55\nBreakfast: Ammu's South Indian Restaurant, Buffalo\nAttraction: - (The day will be spent traveling back to Asheville)\nLunch: - (Assuming lunch on the road)\nDinner: - (Assuming dinner on the road or after arrival)\nAccommodation: -\n\nPlease note that the accommodation prices, flight costs, and meal costs have been estimated to fit within the $4,700 budget for 2 people. The attractions chosen are based on the preference for Mexican and Chinese cuisines and the availability of attractions in each city. The transportation options are chosen based on the provided flight information and the preference for self-driving on the return trip.", "gpt-4-1106-preview_cot_sole-planning_parsed_results": [{"day": 1, "current_city": "from Asheville to New York", "transportation": "Flight Number: F3641730, from Asheville to New York, Departure Time: 13:49, Arrival Time: 15:40", "breakfast": "-", "attraction": "Times Square, New York", "lunch": "Seasons 52 Fresh Grill, New York", "dinner": "Shokitini, New York", "accommodation": "Versatile private room in Harlem/Hamilton Heights!, New York"}, {"day": 2, "current_city": "New York", "transportation": "-", "breakfast": "Sir John Bakery Cafe, New York", "attraction": "Statue of Liberty, New York;The High Line, New York", "lunch": "Gurgaon Hights, New York", "dinner": "Goosebumps, New York", "accommodation": "Versatile private room in Harlem/Hamilton Heights!, New York"}, {"day": 3, "current_city": "from New York to Buffalo", "transportation": "Flight Number: F3641101, from New York to Buffalo, Departure Time: 11:59, Arrival Time: 13:09", "breakfast": "Green Chick Chop, New York", "attraction": "Buffalo Naval Park, Buffalo;The Buffalo Zoo, Buffalo", "lunch": "Tibby's New Orleans Kitchen, Buffalo", "dinner": "Shama Chicken Corner, Buffalo", "accommodation": "Cozy Studio in Heart of Ft Greene, Buffalo"}, {"day": 4, "current_city": "Buffalo", "transportation": "-", "breakfast": "Punjab Grill, Buffalo", "attraction": "Buffalo and Erie County Botanical Gardens, Buffalo;Frank Lloyd Wright's Martin House, Buffalo", "lunch": "Red Mango, Buffalo", "dinner": "Chopsticks, Buffalo", "accommodation": "Cozy Studio in Heart of Ft Greene, Buffalo"}, {"day": 5, "current_city": "from Buffalo to Asheville", "transportation": "Self-driving, from Buffalo to Asheville, duration: 10 hours 29 mins, distance: 1,110 km, Cost: 55", "breakfast": "Ammu's South Indian Restaurant, Buffalo", "attraction": "-", "lunch": "-", "dinner": "-", "accommodation": "-"}]}]