[{"gpt-4-1106-preview_cot_sole-planning_results": "Travel Plan:\n\nDay 1: March 11, 2022\nCurrent City: from Indianapolis to Grand Junction\nTransportation: Self-driving, from Indianapolis to Grand Junction, duration: 19 hours 23 mins, distance: 2,132 km, cost: $106 (fuel cost)\nBreakfast: - (Assuming breakfast is had before departure)\nAttraction: - (Traveling, no attractions planned)\nLunch: - (On the road, travelers can stop at a convenient location)\nDinner: - (On the road, travelers can stop at a convenient location)\nAccommodation: NYC Apartment near Central Park!, Grand Junction, price: $1118 x 2 nights = $2236 (Pet-friendly, entire home/apt)\n\nDay 2: March 12, 2022\nCurrent City: Grand Junction\nTransportation: -\nBreakfast: Punjab Da Pind, Grand Junction, Average Cost: $52\nAttraction: Museum of the West, Museums of Western Colorado, Grand Junction\nLunch: Austin's BBQ and Oyster Bar, Grand Junction, Average Cost: $15\nAttraction: Western Colorado Botanical Gardens, Grand Junction\nDinner: 2 Dog, Grand Junction, Average Cost: $29\nAccommodation: NYC Apartment near Central Park!, Grand Junction\n\nDay 3: March 13, 2022\nCurrent City: from Grand Junction to Alamosa\nTransportation: Self-driving, from Grand Junction to Alamosa, duration: 4 hours 37 mins, distance: 397 km, cost: $19 (fuel cost)\nBreakfast: Thakur Bakers, Grand Junction, Average Cost: $100\nAttraction: Canyon View Park, Grand Junction\nLunch: - (On the road, travelers can stop at a convenient location)\nDinner: Atlanta Highway Seafood Market, Alamosa, Average Cost: $68\nAccommodation: Comfortable studio suite in midtown Manhattan, Alamosa, price: $67 x 2 nights = $134 (Pet-friendly, entire home/apt)\n\nDay 4: March 14, 2022\nCurrent City: Alamosa\nTransportation: -\nBreakfast: Riverwalk Cafe, Alamosa, Average Cost: $97\nAttraction: San Luis Valley Museum | Alamosa\nLunch: Coffee to Cocktail Bar - Hyatt Place, Alamosa, Average Cost: $35\nAttraction: Alamosa National Wildlife Refuge and Visitor Center\nDinner: Burger Singh, Alamosa, Average Cost: $95\nAccommodation: Comfortable studio suite in midtown Manhattan, Alamosa\n\nDay 5: March 15, 2022\nCurrent City: from Alamosa to Denver\nTransportation: Flight Number: F3837896, from Alamosa to Denver, Price: $57 x 5 = $285, DepTime: 18:06, ArrTime: 18:57\nBreakfast: Cafe LazyMojo, Alamosa, Average Cost: $26\nAttraction: Cole Park, Alamosa\nLunch: - (Assuming lunch is skipped due to flight)\nDinner: The Urban Socialite, Denver, Average Cost: $34\nAccommodation: Harlem cozy nights, Denver, price: $457 x 2 nights = $914 (Pet-friendly, entire home/apt)\n\nDay 6: March 16, 2022\nCurrent City: Denver\nTransportation: -\nBreakfast: The Fatty Bao - Asian Gastro Bar, Denver, Average Cost: $93\nAttraction: Denver Zoo\nLunch: Woods Spice, Denver, Average Cost: $69\nAttraction: Denver Botanic Gardens\nDinner: Tasty Fare, Denver, Average Cost: $79\nAccommodation: Harlem cozy nights, Denver\n\nDay 7: March 17, 2022\nCurrent City: from Denver to Indianapolis\nTransportation: Flight Number: F3910546, from Denver to Indianapolis, Price: $462 x 5 = $2310, DepTime: 17:33, ArrTime: 21:46\nBreakfast: Rain Tree Grill, Denver, Average Cost: $94\nAttraction: Denver Art Museum\nLunch: - (Assuming lunch is skipped due to flight)\nDinner: - (Assuming dinner is had upon arrival in Indianapolis)\nAccommodation: -\n\nTotal Estimated Cost Breakdown:\nTransportation (Self-driving fuel): $106 + $19 = $125\nTransportation (Flights): $285 + $2310 = $2595\nAccommodations: $2236 + $134 + $914 = $3284\nMeals and Attractions (Estimated Average Cost per meal $50 x 3 meals x 6 days for 5 people): $50 x 3 x 6 x 5 = $4500\nTotal Estimated Cost: $125 + $2595 + $3284 + $4500 = $10504\n\nRemaining Budget: $15,100 - $10,504 = $4596\n\nNote: The remaining budget can be used for additional meals, attractions, or any incidental expenses. The meal costs are estimated averages and may vary. Attractions that do not have an entry fee are chosen to keep the costs within budget. The plan assumes that the travelers have a pet-friendly vehicle for self-driving.", "gpt-4-1106-preview_cot_sole-planning_parsed_results": [{"day": 1, "current_city": "from Indianapolis to Grand Junction", "transportation": "Self-driving, from Indianapolis to Grand Junction, duration: 19 hours 23 mins, distance: 2132 km, Cost: 106", "breakfast": "-", "attraction": "-", "lunch": "-", "dinner": "-", "accommodation": "NYC Apartment near Central Park!, Grand Junction"}, {"day": 2, "current_city": "Grand Junction", "transportation": "-", "breakfast": "Punjab Da Pind, Grand Junction", "attraction": "Museum of the West, Museums of Western Colorado, Grand Junction;Western Colorado Botanical Gardens, Grand Junction;", "lunch": "Austin's BBQ and Oyster Bar, Grand Junction", "dinner": "2 Dog, Grand Junction", "accommodation": "NYC Apartment near Central Park!, Grand Junction"}, {"day": 3, "current_city": "from Grand Junction to Alamosa", "transportation": "Self-driving, from Grand Junction to Alamosa, duration: 4 hours 37 mins, distance: 397 km, Cost: 19", "breakfast": "Thakur Bakers, Grand Junction", "attraction": "Canyon View Park, Grand Junction", "lunch": "-", "dinner": "Atlanta Highway Seafood Market, Alamosa", "accommodation": "Comfortable studio suite in midtown Manhattan, Alamosa"}, {"day": 4, "current_city": "Alamosa", "transportation": "-", "breakfast": "Riverwalk Cafe, Alamosa", "attraction": "San Luis Valley Museum, Alamosa;Alamosa National Wildlife Refuge and Visitor Center, Alamosa;", "lunch": "Coffee to Cocktail Bar - Hyatt Place, Alamosa", "dinner": "Burger Singh, Alamosa", "accommodation": "Comfortable studio suite in midtown Manhattan, Alamosa"}, {"day": 5, "current_city": "from Alamosa to Denver", "transportation": "Flight Number: F3837896, from Alamosa to Denver, Cost: 285, Departure Time: 18:06, Arrival Time: 18:57", "breakfast": "Cafe LazyMojo, Alamosa", "attraction": "Cole Park, Alamosa", "lunch": "-", "dinner": "The Urban Socialite, Denver", "accommodation": "Harlem cozy nights, Denver"}, {"day": 6, "current_city": "Denver", "transportation": "-", "breakfast": "The Fatty Bao - Asian Gastro Bar, Denver", "attraction": "Denver Zoo, Denver;Denver Botanic Gardens, Denver;", "lunch": "Woods Spice, Denver", "dinner": "Tasty Fare, Denver", "accommodation": "Harlem cozy nights, Denver"}, {"day": 7, "current_city": "from Denver to Indianapolis", "transportation": "Flight Number: F3910546, from Denver to Indianapolis, Cost: 2310, Departure Time: 17:33, Arrival Time: 21:46", "breakfast": "Rain Tree Grill, Denver", "attraction": "Denver Art Museum, Denver", "lunch": "-", "dinner": "-", "accommodation": "-"}]}]