[{"gpt-4-1106-preview_cot_sole-planning_results": "Travel Plan:\n\nDay 1: March 16, 2022\nCurrent City: from St. Petersburg to Rockford\nTransportation: Flight Number: F3573659, from St. Petersburg to Rockford, Departure Time: 15:40, Arrival Time: 17:04\nAccommodation: Spacious 3BDR Prime Location!, Rockford - $1030 (for the entire stay)\nDinner: Coco Bambu, Rockford - Average Cost: $72\n\nDay 2: March 17, 2022\nCurrent City: Rockford\nBreakfast: Dunkin' Donuts, Rockford - Average Cost: $24\nAttraction 1: Anderson Japanese Gardens, Rockford\nLunch: Flying Mango, Rockford - Average Cost: $20\nAttraction 2: Discovery Center Museum, Rockford\nDinner: Eggspectation - Jaypee Vasant Continental, Rockford - Average Cost: $77\n\nDay 3: March 18, 2022\nCurrent City: from Rockford to St. Petersburg\nBreakfast: Cafe Coffee Day, Rockford - Average Cost: $28\nAttraction: Burpee Museum of Natural History, Rockford\nLunch: Gajalee Sea Food, Rockford - Average Cost: $49\nTransportation: Flight Number: F3573120, from Rockford to St. Petersburg, Departure Time: 19:00, Arrival Time: 22:43\nAccommodation: -\n\nTotal Estimated Costs:\nFlight to Rockford: $474\nAccommodation: $1030 (for 3 nights)\nMeals: $72 (Dinner Day 1) + $24 (Breakfast Day 2) + $20 (Lunch Day 2) + $77 (Dinner Day 2) + $28 (Breakfast Day 3) + $49 (Lunch Day 3) = $270\nFlight from Rockford: $346\nTotal: $474 + $1030 + $270 + $346 = $2120\n\nNote: The total estimated cost exceeds the budget of $1,700. To adjust the plan within the budget, consider changing the accommodation to a more affordable option or reducing meal costs by choosing less expensive restaurants.", "gpt-4-1106-preview_cot_sole-planning_parsed_results": [{"day": 1, "current_city": "from St. Petersburg to Rockford", "transportation": "Flight Number: F3573659, from St. Petersburg to Rockford, Departure Time: 15:40, Arrival Time: 17:04", "breakfast": "-", "attraction": "-", "lunch": "-", "dinner": "Coco Bambu, Rockford", "accommodation": "Spacious 3BDR Prime Location!, Rockford"}, {"day": 2, "current_city": "Rockford", "transportation": "-", "breakfast": "Dunkin' Donuts, Rockford", "attraction": "Anderson Japanese Gardens, Rockford;Discovery Center Museum, Rockford;", "lunch": "Flying Mango, Rockford", "dinner": "Eggspectation - Jaypee Vasant Continental, Rockford", "accommodation": "Spacious 3BDR Prime Location!, Rockford"}, {"day": 3, "current_city": "from Rockford to St. Petersburg", "transportation": "Flight Number: F3573120, from Rockford to St. Petersburg, Departure Time: 19:00, Arrival Time: 22:43", "breakfast": "Cafe Coffee Day, Rockford", "attraction": "Burpee Museum of Natural History, Rockford", "lunch": "Gajalee Sea Food, Rockford", "dinner": "-", "accommodation": "-"}]}]