[{"gpt-4-1106-preview_cot_sole-planning_results": "Travel Plan:\n\nDay 1: March 24, 2022\nCurrent City: from Gulfport to Dallas\nTransportation: Flight Number: F3609002, from Gulfport to Dallas, Departure Time: 11:42, Arrival Time: 13:20\nAccommodation: E. W'burg Private Room near subway, Dallas ($272.00 per night)\nDinner: Coconuts Fish Cafe, Dallas (Average Cost: $38)\n\nDay 2: March 25, 2022\nCurrent City: Dallas\nBreakfast: Cafe Gatherings, Dallas (Average Cost: $17)\nAttraction: The Dallas World Aquarium, Dallas\nLunch: 1918 Bistro & Grill, Dallas (Average Cost: $90)\nAttraction: The Sixth Floor Museum at Dealey Plaza, Dallas\nDinner: Yanki Sizzlers, Dallas (Average Cost: $96)\n\nDay 3: March 26, 2022\nCurrent City: from Dallas to San Angelo\nTransportation: Flight Number: F3594272, from Dallas to San Angelo, Departure Time: 08:31, Arrival Time: 09:32\nAccommodation: INCREDIBLE TOWNHOUSE 4 STORIES 5 BEDROOMS 3 BATH, San Angelo ($338.00 per night)\nLunch: DePalma's Italian Cafe - Downtown, San Angelo (Average Cost: $38)\nAttraction: San Angelo Museum of Fine Arts, San Angelo\nDinner: Chinese Food, San Angelo (Average Cost: $88)\n\nDay 4: March 27, 2022\nCurrent City: San Angelo\nBreakfast: 6 Ballygunge Place, San Angelo (Average Cost: $48)\nAttraction: Fort Concho National Historic Landmark, San Angelo\nLunch: Needs Gourmet, San Angelo (Average Cost: $83)\nAttraction: San Angelo State Park, San Angelo\nDinner: District 6, San Angelo (Average Cost: $19)\n\nDay 5: March 28, 2022\nCurrent City: from San Angelo to Houston\nTransportation: Self-driving, from San Angelo to Houston, duration: 5 hours 46 mins, distance: 586 km, cost: $29\nAccommodation: Sunny and Airy near Manhattan, Houston ($499.00 per night)\nLunch: Jalapenos, Houston (Average Cost: $57)\nAttraction: Space Center Houston, Houston\nDinner: Super Bakery, Houston (Average Cost: $30)\n\nDay 6: March 29, 2022\nCurrent City: Houston\nBreakfast: Matchbox, Houston (Average Cost: $33)\nAttraction: Houston Museum of Natural Science, Houston\nLunch: The BrewMaster - The Mix Fine Dine, Houston (Average Cost: $52)\nAttraction: Houston Zoo, Houston\nDinner: Vinayaka Mylari, Houston (Average Cost: $14)\n\nDay 7: March 30, 2022\nCurrent City: from Houston to Gulfport\nTransportation: Flight Number: F3917573, from Houston to Gulfport, Departure Time: 21:46, Arrival Time: 23:05\nBreakfast: Al Arabian Express, Houston (Average Cost: $74)\nAttraction: The Museum of Fine Arts, Houston\nLunch: Pebble Street, Houston (Average Cost: $73)\n- End of Travel Plan -\n\nTotal Estimated Costs:\nFlights: $222 (Gulfport to Dallas) + $47 (Dallas to San Angelo) + $147 (Houston to Gulfport) = $416\nAccommodations: $272 (1 night in Dallas) + $338 (1 night in San Angelo) + $499 (2 nights in Houston) = $1608\nTransportation (Self-driving): $29 (San Angelo to Houston)\nMeals & Attractions: Estimated $100 per day x 7 days = $700\nTotal = $416 (Flights) + $1608 (Accommodations) + $29 (Transportation) + $700 (Meals & Attractions) = $2753\n\nRemaining Budget: $4200 - $2753 = $1447\n\nNote: The remaining budget can be used for additional meals, attractions, souvenirs, or unforeseen expenses. Prices for meals are average costs and may vary. Attractions that do not have an entrance fee listed are assumed to be free or within the remaining budget. The accommodation prices are based on the provided data and may vary depending on availability and booking time. The plan does not include transportation within cities, which should be considered within the remaining budget.", "gpt-4-1106-preview_cot_sole-planning_parsed_results": [{"day": 1, "current_city": "from Gulfport to Dallas", "transportation": "Flight Number: F3609002, from Gulfport to Dallas, Departure Time: 11:42, Arrival Time: 13:20", "breakfast": "-", "attraction": "-", "lunch": "-", "dinner": "Coconuts Fish Cafe, Dallas", "accommodation": "E. W'burg Private Room near subway, Dallas"}, {"day": 2, "current_city": "Dallas", "transportation": "-", "breakfast": "Cafe Gatherings, Dallas", "attraction": "The Dallas World Aquarium, Dallas;The Sixth Floor Museum at Dealey Plaza, Dallas;", "lunch": "1918 Bistro & Grill, Dallas", "dinner": "Yanki Sizzlers, Dallas", "accommodation": "-"}, {"day": 3, "current_city": "from Dallas to San Angelo", "transportation": "Flight Number: F3594272, from Dallas to San Angelo, Departure Time: 08:31, Arrival Time: 09:32", "breakfast": "-", "attraction": "San Angelo Museum of Fine Arts, San Angelo;", "lunch": "DePalma's Italian Cafe - Downtown, San Angelo", "dinner": "Chinese Food, San Angelo", "accommodation": "INCREDIBLE TOWNHOUSE 4 STORIES 5 BEDROOMS 3 BATH, San Angelo"}, {"day": 4, "current_city": "San Angelo", "transportation": "-", "breakfast": "6 Ballygunge Place, San Angelo", "attraction": "Fort Concho National Historic Landmark, San Angelo;San Angelo State Park, San Angelo;", "lunch": "Needs Gourmet, San Angelo", "dinner": "District 6, San Angelo", "accommodation": "-"}, {"day": 5, "current_city": "from San Angelo to Houston", "transportation": "Self-driving, from San Angelo to Houston, duration: 5 hours 46 mins, distance: 586 km, Cost: 29", "breakfast": "-", "attraction": "Space Center Houston, Houston;", "lunch": "Jalapenos, Houston", "dinner": "Super Bakery, Houston", "accommodation": "Sunny and Airy near Manhattan, Houston"}, {"day": 6, "current_city": "Houston", "transportation": "-", "breakfast": "Matchbox, Houston", "attraction": "Houston Museum of Natural Science, Houston;Houston Zoo, Houston;", "lunch": "The BrewMaster - The Mix Fine Dine, Houston", "dinner": "Vinayaka Mylari, Houston", "accommodation": "-"}, {"day": 7, "current_city": "from Houston to Gulfport", "transportation": "Flight Number: F3917573, from Houston to Gulfport, Departure Time: 21:46, Arrival Time: 23:05", "breakfast": "Al Arabian Express, Houston", "attraction": "The Museum of Fine Arts, Houston;", "lunch": "Pebble Street, Houston", "dinner": "-", "accommodation": "-"}]}]