[{"gpt-4-1106-preview_cot_sole-planning_results": "Travel Plan:\n\nDay 1: March 15, 2022\nCurrent City: from Sault Ste. Marie to Pellston\nTransportation: Self-driving, Duration: 1 hour 16 mins, Distance: 122 km, Cost: $6\nBreakfast: -\nAttraction: Pellston Pioneer Park, Pellston\nLunch: Johnnie Mars, Pellston, Average Cost: $33\nAttraction: Pellston Historical Society Museum, Pellston\nDinner: Aroos Damascus, Pellston, Average Cost: $44\nAccommodation: Beautiful apartment ~25min from Times Square, Pellston, Price: $571, Entire home/apt\n\nDay 2: March 16, 2022\nCurrent City: Pellston\nTransportation: -\nBreakfast: Sagar Gaire Fast Food, Pellston, Average Cost: $64\nAttraction: Philip J. Braun Nature Preserve, Pellston\nLunch: The Great Kabab Factory - Park Plaza, Pellston, Average Cost: $84\nAttraction: Petoskey State Park, Pellston\nDinner: The Plaza Solitaire, Pellston, Average Cost: $72\nAccommodation: Beautiful apartment ~25min from Times Square, Pellston, Price: $571, Entire home/apt\n\nDay 3: March 17, 2022\nCurrent City: from Pellston to Traverse City\nTransportation: Self-driving, Duration: 1 hour 49 mins, Distance: 137 km, Cost: $6\nBreakfast: Premier Bite, Pellston, Average Cost: $53\nAttraction: Clinch Park, Traverse City\nLunch: Famous Dave's, Traverse City, Average Cost: $39\nAttraction: Great Lakes Children's Museum, Traverse City\nDinner: Daily Eats, Traverse City, Average Cost: $44\nAccommodation: Heart of Soho! Cute studio with clean finishes!, Traverse City, Price: $969, Entire home/apt\n\nDay 4: March 18, 2022\nCurrent City: Traverse City\nTransportation: -\nBreakfast: Arigato Sushi, Traverse City, Average Cost: $96\nAttraction: World's Largest Cherry Pie Pan, Traverse City\nLunch: Tasty Bites, Traverse City, Average Cost: $27\nAttraction: Hippie Tree, Traverse City\nDinner: India on my Plate - Fortune Select Excalibur, Traverse City, Average Cost: $53\nAccommodation: Heart of Soho! Cute studio with clean finishes!, Traverse City, Price: $969, Entire home/apt\n\nDay 5: March 19, 2022\nCurrent City: from Traverse City to Alpena\nTransportation: Self-driving, Duration: 2 hours 29 mins, Distance: 204 km, Cost: $10\nBreakfast: Desserts 83, Traverse City, Average Cost: $78\nAttraction: Great Lakes Maritime Heritage Center, Alpena\nLunch: A & A Pagliai's Pizza, Alpena, Average Cost: $72\nAttraction: Besser Museum for Northeast Michigan, Alpena\nDinner: @Mango, Alpena, Average Cost: $38\nAccommodation: Ultimate 50th Floor Downtown Penthouse - 4000SqFt, Alpena, Price: $1043, Entire home/apt\n\nDay 6: March 20, 2022\nCurrent City: Alpena\nTransportation: -\nBreakfast: Shudh Restaurant, Alpena, Average Cost: $56\nAttraction: Mich-e-ke-wis Park, Alpena\nLunch: Maplai, Alpena, Average Cost: $63\nAttraction: Bay View Park, Alpena\nDinner: Zaffran - The Bristol Hotel, Alpena, Average Cost: $33\nAccommodation: Ultimate 50th Floor Downtown Penthouse - 4000SqFt, Alpena, Price: $1043, Entire home/apt\n\nDay 7: March 21, 2022\nCurrent City: from Alpena to Sault Ste. Marie\nTransportation: Self-driving, Duration: 2 hours 39 mins, Distance: 247 km, Cost: $12\nBreakfast: Kylin Express, Alpena, Average Cost: $30\nAttraction: Island Park, Alpena\nLunch: Jain Chawal Wale, Alpena, Average Cost: $20\nAttraction: Alpena Wildlife Sanctuary, Alpena\nDinner: -\nAccommodation: -\n\nTotal Estimated Cost Breakdown:\nAccommodation: $571 * 2 (Pellston) + $969 * 2 (Traverse City) + $1043 * 2 (Alpena) = $5146\nMeals: $33 + $44 + $64 + $84 + $72 + $53 + $39 + $44 + $96 + $27 + $53 + $78 + $72 + $38 + $56 + $63 + $33 + $30 + $20 = $1015\nTransportation: $6 (Sault Ste. Marie to Pellston) + $6 (Pellston to Traverse City) + $10 (Traverse City to Alpena) + $12 (Alpena to Sault Ste. Marie) = $34\nTotal Estimated Cost: $5146 (Accommodation) + $1015 (Meals) + $34 (Transportation) = $6195\n\nRemaining Budget: $12,700 - $6195 = $6505\n\nPlease note that the costs for attractions and any additional personal expenses are not included in this estimate. Also, the meal costs are based on average costs per meal per person, and actual costs may vary. The remaining budget can be used for these expenses.", "gpt-4-1106-preview_cot_sole-planning_parsed_results": [{"day": 1, "current_city": "from Sault Ste. Marie to Pellston", "transportation": "Self-driving, Duration: 1 hour 16 mins, Distance: 122 km, Cost: 6", "breakfast": "-", "attraction": "Pellston Pioneer Park, Pellston;Pellston Historical Society Museum, Pellston;", "lunch": "Johnnie Mars, Pellston", "dinner": "Aroos Damascus, Pellston", "accommodation": "Beautiful apartment ~25min from Times Square, Pellston"}, {"day": 2, "current_city": "Pellston", "transportation": "-", "breakfast": "Sagar Gaire Fast Food, Pellston", "attraction": "Philip J. Braun Nature Preserve, Pellston;Petoskey State Park, Pellston;", "lunch": "The Great Kabab Factory - Park Plaza, Pellston", "dinner": "The Plaza Solitaire, Pellston", "accommodation": "Beautiful apartment ~25min from Times Square, Pellston"}, {"day": 3, "current_city": "from Pellston to Traverse City", "transportation": "Self-driving, Duration: 1 hour 49 mins, Distance: 137 km, Cost: 6", "breakfast": "Premier Bite, Pellston", "attraction": "Clinch Park, Traverse City;Great Lakes Children's Museum, Traverse City;", "lunch": "Famous Dave's, Traverse City", "dinner": "Daily Eats, Traverse City", "accommodation": "Heart of Soho! Cute studio with clean finishes!, Traverse City"}, {"day": 4, "current_city": "Traverse City", "transportation": "-", "breakfast": "Arigato Sushi, Traverse City", "attraction": "World's Largest Cherry Pie Pan, Traverse City;Hippie Tree, Traverse City;", "lunch": "Tasty Bites, Traverse City", "dinner": "India on my Plate - Fortune Select Excalibur, Traverse City", "accommodation": "Heart of Soho! Cute studio with clean finishes!, Traverse City"}, {"day": 5, "current_city": "from Traverse City to Alpena", "transportation": "Self-driving, Duration: 2 hours 29 mins, Distance: 204 km, Cost: 10", "breakfast": "Desserts 83, Traverse City", "attraction": "Great Lakes Maritime Heritage Center, Alpena;Besser Museum for Northeast Michigan, Alpena;", "lunch": "A & A Pagliai's Pizza, Alpena", "dinner": "@Mango, Alpena", "accommodation": "Ultimate 50th Floor Downtown Penthouse - 4000SqFt, Alpena"}, {"day": 6, "current_city": "Alpena", "transportation": "-", "breakfast": "Shudh Restaurant, Alpena", "attraction": "Mich-e-ke-wis Park, Alpena;Bay View Park, Alpena;", "lunch": "Maplai, Alpena", "dinner": "Zaffran - The Bristol Hotel, Alpena", "accommodation": "Ultimate 50th Floor Downtown Penthouse - 4000SqFt, Alpena"}, {"day": 7, "current_city": "from Alpena to Sault Ste. Marie", "transportation": "Self-driving, Duration: 2 hours 39 mins, Distance: 247 km, Cost: 12", "breakfast": "Kylin Express, Alpena", "attraction": "Island Park, Alpena;Alpena Wildlife Sanctuary, Alpena;", "lunch": "Jain Chawal Wale, Alpena", "dinner": "-", "accommodation": "-"}]}]