[{"gpt-4-1106-preview_cot_sole-planning_results": "Travel Plan:\n\nDay 1:\nCurrent City: from Provo to Phoenix\nTransportation: Flight Number: F3576799, from Provo to Phoenix, Departure Time: 15:09, Arrival Time: 15:34\nBreakfast: - (Assuming breakfast was had before departure)\nAttraction: Phoenix Zoo, Phoenix\nLunch: Pizza Hut, Phoenix (As it offers a variety of cuisines including Italian which is on the preference list)\nDinner: Doughlicious, Phoenix (Offers French cuisine which is on the preference list)\nAccommodation: Twin Cabin with a Window One, Phoenix (Pet-friendly and a private room as requested)\n\nDay 2:\nCurrent City: Phoenix\nTransportation: -\nBreakfast: Subway, Phoenix (Offers American breakfast options)\nAttraction: Desert Botanical Garden, Phoenix; Heard Museum, Phoenix\nLunch: Mama Loca, Phoenix (Offers Italian cuisine which is on the preference list)\nDinner: Malabar Dosa Hut, Phoenix (Offers Indian cuisine which is on the preference list)\nAccommodation: Twin Cabin with a Window One, Phoenix (Pet-friendly and a private room as requested)\n\nDay 3:\nCurrent City: from Phoenix to Provo\nTransportation: Flight Number: F3578519, from Phoenix to Provo, Departure Time: 20:12, Arrival Time: 22:55\nBreakfast: Vero Gusto, Phoenix (Offers French cuisine which is on the preference list)\nAttraction: The Japanese Friendship Garden of Phoenix, Phoenix\nLunch: De Bone Chicken, Phoenix (Offers American cuisine which is on the preference list)\nDinner: - (Assuming dinner will be had after arrival in Provo)\nAccommodation: -\n\nPlease note that the flight prices, accommodation costs, and meal expenses should be within the $1,400 budget for two people. The attractions chosen do not have an entry fee listed, so it is assumed that the cost is either free or nominal. The restaurants selected offer a variety of cuisines as requested. The accommodation is pet-friendly and offers a private room, aligning with the preferences provided.", "gpt-4-1106-preview_cot_sole-planning_parsed_results": [{"day": 1, "current_city": "from Provo to Phoenix", "transportation": "Flight Number: F3576799, from Provo to Phoenix, Departure Time: 15:09, Arrival Time: 15:34", "breakfast": "-", "attraction": "Phoenix Zoo, Phoenix", "lunch": "Pizza Hut, Phoenix", "dinner": "Doughlicious, Phoenix", "accommodation": "Twin Cabin with a Window One, Phoenix"}, {"day": 2, "current_city": "Phoenix", "transportation": "-", "breakfast": "Subway, Phoenix", "attraction": "Desert Botanical Garden, Phoenix;Heard Museum, Phoenix", "lunch": "Mama Loca, Phoenix", "dinner": "Malabar Dosa Hut, Phoenix", "accommodation": "Twin Cabin with a Window One, Phoenix"}, {"day": 3, "current_city": "from Phoenix to Provo", "transportation": "Flight Number: F3578519, from Phoenix to Provo, Departure Time: 20:12, Arrival Time: 22:55", "breakfast": "Vero Gusto, Phoenix", "attraction": "The Japanese Friendship Garden of Phoenix, Phoenix", "lunch": "De Bone Chicken, Phoenix", "dinner": "-", "accommodation": "-"}]}]