[{"gpt-4-1106-preview_cot_sole-planning_results": "Travel Plan:\n\nDay 1: March 23, 2022\nCurrent City: from Houston to Salt Lake City\nTransportation: Flight Number: F3495303, from Houston to Salt Lake City, Departure Time: 06:01, Arrival Time: 07:56\nBreakfast: -\nAttraction: Utah State Capitol, Salt Lake City\nLunch: Sushi Loko, Salt Lake City\nDinner: Balada Mix, Salt Lake City\nAccommodation: Cozy apartment in Noho/ Soho, Salt Lake City\n\nDay 2: March 24, 2022\nCurrent City: Salt Lake City\nTransportation: -\nBreakfast: Makers & Bakers, Salt Lake City\nAttraction: Liberty Park, Salt Lake City; Natural History Museum of Utah, Salt Lake City\nLunch: Tikka Tonight, Salt Lake City\nDinner: Mainland China, Salt Lake City\nAccommodation: Cozy apartment in Noho/ Soho, Salt Lake City\n\nDay 3: March 25, 2022\nCurrent City: from Salt Lake City to Moab\nTransportation: Flight Number: F3809091, from Salt Lake City to Moab, Departure Time: 17:13, Arrival Time: 18:16\nBreakfast: Joey's Pizza, Salt Lake City\nAttraction: Clark Planetarium, Salt Lake City\nLunch: Shree Rathnam, Salt Lake City\nDinner: -\nAccommodation: Bright Brooklyn Apartment, Moab\n\nDay 4: March 26, 2022\nCurrent City: Moab\nTransportation: -\nBreakfast: Cafe Hydro, Moab\nAttraction: Arches National Park, Moab; Dead Horse Point State Park, Moab\nLunch: Spice Kraft, Moab\nDinner: Mangosteen Cafe, Moab\nAccommodation: Bright Brooklyn Apartment, Moab\n\nDay 5: March 27, 2022\nCurrent City: from Moab to Vernal\nTransportation: Self-driving, duration: 3 hours 40 mins, cost: $17\nBreakfast: -\nAttraction: Moab Giants, Moab\nLunch: McDonald's, Moab\nDinner: -\nAccommodation: Luxurious & Spacious 1 Bedroom Apt, Vernal\n\nDay 6: March 28, 2022\nCurrent City: Vernal\nTransportation: -\nBreakfast: The Corner Cafe, Vernal\nAttraction: Utah Field House of Natural History State Park Museum, Vernal; Steinaker State Park, Vernal\nLunch: Prost Brew Pub, Vernal\nDinner: Seasonings - The Spice Mysteries, Vernal\nAccommodation: Luxurious & Spacious 1 Bedroom Apt, Vernal\n\nDay 7: March 29, 2022\nCurrent City: from Vernal to Houston\nTransportation: Self-driving, duration: 20 hours 31 mins, cost: $108\nBreakfast: -\nAttraction: -\nLunch: -\nDinner: -\nAccommodation: -\n\nPlease note that the costs for flights, accommodations, meals, and attractions should be calculated to ensure they fit within the $7,700 budget. The provided flight and accommodation options were selected based on the best fit for the schedule and budget. Meals and attractions were chosen based on diversity and the desire to experience a range of offerings in each city.", "gpt-4-1106-preview_cot_sole-planning_parsed_results": [{"day": 1, "current_city": "from Houston to Salt Lake City", "transportation": "Flight Number: F3495303, from Houston to Salt Lake City, Departure Time: 06:01, Arrival Time: 07:56", "breakfast": "-", "attraction": "Utah State Capitol, Salt Lake City", "lunch": "Sushi Loko, Salt Lake City", "dinner": "Balada Mix, Salt Lake City", "accommodation": "Cozy apartment in Noho/ Soho, Salt Lake City"}, {"day": 2, "current_city": "Salt Lake City", "transportation": "-", "breakfast": "Makers & Bakers, Salt Lake City", "attraction": "Liberty Park, Salt Lake City;Natural History Museum of Utah, Salt Lake City", "lunch": "Tikka Tonight, Salt Lake City", "dinner": "Mainland China, Salt Lake City", "accommodation": "Cozy apartment in Noho/ Soho, Salt Lake City"}, {"day": 3, "current_city": "from Salt Lake City to Moab", "transportation": "Flight Number: F3809091, from Salt Lake City to Moab, Departure Time: 17:13, Arrival Time: 18:16", "breakfast": "Joey's Pizza, Salt Lake City", "attraction": "Clark Planetarium, Salt Lake City", "lunch": "Shree Rathnam, Salt Lake City", "dinner": "-", "accommodation": "Bright Brooklyn Apartment, Moab"}, {"day": 4, "current_city": "Moab", "transportation": "-", "breakfast": "Cafe Hydro, Moab", "attraction": "Arches National Park, Moab;Dead Horse Point State Park, Moab", "lunch": "Spice Kraft, Moab", "dinner": "Mangosteen Cafe, Moab", "accommodation": "Bright Brooklyn Apartment, Moab"}, {"day": 5, "current_city": "from Moab to Vernal", "transportation": "Self-driving, duration: 3 hours 40 mins, Cost: 17", "breakfast": "-", "attraction": "Moab Giants, Moab", "lunch": "McDonald's, Moab", "dinner": "-", "accommodation": "Luxurious & Spacious 1 Bedroom Apt, Vernal"}, {"day": 6, "current_city": "Vernal", "transportation": "-", "breakfast": "The Corner Cafe, Vernal", "attraction": "Utah Field House of Natural History State Park Museum, Vernal;Steinaker State Park, Vernal", "lunch": "Prost Brew Pub, Vernal", "dinner": "Seasonings - The Spice Mysteries, Vernal", "accommodation": "Luxurious & Spacious 1 Bedroom Apt, Vernal"}, {"day": 7, "current_city": "from Vernal to Houston", "transportation": "Self-driving, duration: 20 hours 31 mins, Cost: 108", "breakfast": "-", "attraction": "-", "lunch": "-", "dinner": "-", "accommodation": "-"}]}]