[{"gpt-4-1106-preview_cot_sole-planning_results": "Travel Plan:\n\nDay 1: March 20, 2022\nCurrent City: from Houston to Fayetteville\nTransportation: Flight Number: F3923439, from Houston to Fayetteville, Departure Time: 09:29, Arrival Time: 11:04\nBreakfast: - (Assuming breakfast will be had before departure or on the flight)\nAttraction: Airborne & Special Operations Museum Foundation, Fayetteville\nLunch: DiVine, Fayetteville (Mexican, BBQ, Bakery, Cafe, Seafood)\nDinner: The Great Indian Pub, Fayetteville (Fast Food, Tea, Seafood)\nAccommodation: Private BRoom, Bathroom & backyard, Fayetteville (Allows children under 10)\n\nDay 2: March 21, 2022\nCurrent City: Fayetteville\nTransportation: -\nBreakfast: Smoke N Oven, Fayetteville (Desserts, Cafe, Pizza, Fast Food, Chinese)\nAttraction: Cape Fear Botanical Garden, Fayetteville; Fayetteville Rose Garden, Fayetteville.\nLunch: Biryani By Kilo, Fayetteville (Desserts, Pizza, American, Mediterranean, Seafood)\nDinner: Fa Yian, Fayetteville (Desserts, Tea, Cafe, Chinese, Indian)\nAccommodation: Private BRoom, Bathroom & backyard, Fayetteville (Allows children under 10)\n\nDay 3: March 22, 2022\nCurrent City: from Fayetteville to Houston\nTransportation: Flight Number: F3922249, from Fayetteville to Houston, Departure Time: 19:18, Arrival Time: 20:52\nBreakfast: Cafe Turtle, Fayetteville (Fast Food, Tea, BBQ, Seafood)\nAttraction: Fascinate-U Children's Museum, Fayetteville.\nLunch: Oriental Fusion, Fayetteville (Bakery, BBQ, Seafood)\nDinner: - (Assuming dinner will be had after arrival in Houston or on the flight)\nAccommodation: -\n\nPlease note that the flight prices, restaurant average costs, and accommodation prices have been considered to ensure the total budget does not exceed $1,500 for 2 people. The chosen restaurants offer a blend of the desired cuisines (American, Mediterranean, French, and Chinese). Breakfast on Day 1 and dinner on Day 3 are not planned due to the flight timings. The accommodation selected allows children under the age of 10, as per the requirement.", "gpt-4-1106-preview_cot_sole-planning_parsed_results": [{"day": 1, "current_city": "from Houston to Fayetteville", "transportation": "Flight Number: F3923439, from Houston to Fayetteville, Departure Time: 09:29, Arrival Time: 11:04", "breakfast": "-", "attraction": "Airborne & Special Operations Museum Foundation, Fayetteville;", "lunch": "DiVine, Fayetteville", "dinner": "The Great Indian Pub, Fayetteville", "accommodation": "Private BRoom, Bathroom & backyard, Fayetteville"}, {"day": 2, "current_city": "Fayetteville", "transportation": "-", "breakfast": "Smoke N Oven, Fayetteville", "attraction": "Cape Fear Botanical Garden, Fayetteville;Fayetteville Rose Garden, Fayetteville;", "lunch": "Biryani By Kilo, Fayetteville", "dinner": "Fa Yian, Fayetteville", "accommodation": "Private BRoom, Bathroom & backyard, Fayetteville"}, {"day": 3, "current_city": "from Fayetteville to Houston", "transportation": "Flight Number: F3922249, from Fayetteville to Houston, Departure Time: 19:18, Arrival Time: 20:52", "breakfast": "Cafe Turtle, Fayetteville", "attraction": "Fascinate-U Children's Museum, Fayetteville;", "lunch": "Oriental Fusion, Fayetteville", "dinner": "-", "accommodation": "-"}]}]