[{"gpt-4-1106-preview_cot_sole-planning_results": "Travel Plan:\n\nDay 1: March 19, 2022\nCurrent City: from Moline to Abilene\nTransportation: Self-driving, Duration: 14 hours 27 mins, Distance: 1,618 km, Cost: $80\nBreakfast: - (Assuming breakfast is had before departure)\nLunch: - (Please pack a lunch for the road)\nDinner: Thai Garden, Abilene (Cafe, American, Desserts)\nAccommodation: Apartment minutes from manhattan, Abilene (Entire home/apt, $295)\n\nDay 2: March 20, 2022\nCurrent City: Abilene\nTransportation: -\nBreakfast: Thai Garden, Abilene (Cafe, American, Desserts)\nAttraction: The Grace Museum, Abilene; Frontier Texas!, Abilene.\nLunch: Crispy Crust, Abilene (Desserts, Bakery, Cafe, American, Seafood)\nDinner: LPK Waterfront, Abilene (Pizza, Italian, BBQ, Fast Food, Seafood)\nAccommodation: Apartment minutes from manhattan, Abilene (Entire home/apt, $295)\n\nDay 3: March 21, 2022\nCurrent City: from Abilene to Amarillo\nTransportation: Self-driving, Duration: 4 hours 10 mins, Distance: 446 km, Cost: $22\nBreakfast: Cakes Degree, Abilene (Cafe, Mexican, BBQ, Desserts)\nAttraction: Cadillac Ranch, Amarillo; Amarillo Botanical Gardens, Amarillo.\nLunch: The Cinnamon Kitchen, Amarillo (Desserts, Tea, Pizza, Chinese, Seafood)\nDinner: Komachi, Amarillo (Desserts, Tea, Fast Food, Chinese, Mediterranean)\nAccommodation: Gramercy Park restful, cozy, sun-filled home, Amarillo (Entire home/apt, $968)\n\nDay 4: March 22, 2022\nCurrent City: Amarillo\nTransportation: -\nBreakfast: Anand Restaurant, Amarillo (Fast Food, Seafood, Desserts, Italian)\nAttraction: Amarillo Zoo, Amarillo; Don Harrington Discovery Center, Amarillo.\nLunch: Wood Box Cafe, Amarillo (Desserts, French, Fast Food, Cafe, American)\nDinner: Sigree Global Grill, Amarillo (Chinese, BBQ, Cafe, Desserts)\nAccommodation: Gramercy Park restful, cozy, sun-filled home, Amarillo (Entire home/apt, $968)\n\nDay 5: March 23, 2022\nCurrent City: from Amarillo to Lubbock\nTransportation: Self-driving, Duration: 1 hour 47 mins, Distance: 197 km, Cost: $9\nBreakfast: Punjabi Chaap Corner, Amarillo (Desserts, Pizza, Italian, Bakery, Fast Food)\nAttraction: Buddy Holly Center, Lubbock; National Ranching Heritage Center, Lubbock.\nLunch: Grand Barbeque Buffet Restaurant, Lubbock (Tea, French, Fast Food, Cafe, Seafood)\nDinner: Paris 6 Classique, Lubbock (Desserts, Cafe, Pizza, Mexican, BBQ, Chinese)\nAccommodation: Private bedroom in UWS Apartment, Lubbock (Private room, $709)\n\nDay 6: March 24, 2022\nCurrent City: Lubbock\nTransportation: -\nBreakfast: 3 Squares Diner, Lubbock (Pizza, Indian, Fast Food)\nAttraction: American Windmill Museum, Lubbock; Mackenzie Main City Park, Lubbock.\nLunch: Sultanat, Lubbock (Chinese, Bakery, BBQ, Cafe)\nDinner: The Town House Cafe, Lubbock (Tea, American, BBQ, Cafe, Indian, Seafood)\nAccommodation: Private bedroom in UWS Apartment, Lubbock (Private room, $709)\n\nDay 7: March 25, 2022\nCurrent City: from Lubbock to Moline\nTransportation: Self-driving, Duration: 15 hours 14 mins, Distance: 1,704 km, Cost: $85\nBreakfast: - (Assuming breakfast is had before departure)\nLunch: - (Please pack a lunch for the road)\nDinner: - (Assuming dinner is had upon arrival back in Moline)\nAccommodation: -\n\nTotal Estimated Costs:\nAccommodations: $3944\nTransportation: $196\nMeals and Attractions: Estimated $1360 (assuming an average of $40 per meal per person, two meals a day, and $20 per attraction per person)\nTotal: $5500\n\nPlease note that the costs for meals and attractions are estimated and actual costs may vary. The budget is very tight and does not leave much room for additional expenses or unforeseen costs. It is recommended to have a buffer in the budget or to adjust the plan accordingly.", "gpt-4-1106-preview_cot_sole-planning_parsed_results": [{"day": 1, "current_city": "from Moline to Abilene", "transportation": "Self-driving, Duration: 14 hours 27 mins, Distance: 1618 km, Cost: 80", "breakfast": "-", "attraction": "-", "lunch": "-", "dinner": "Thai Garden, Abilene", "accommodation": "Apartment minutes from manhattan, Abilene"}, {"day": 2, "current_city": "Abilene", "transportation": "-", "breakfast": "Thai Garden, Abilene", "attraction": "The Grace Museum, Abilene;Frontier Texas!, Abilene;", "lunch": "Crispy Crust, Abilene", "dinner": "LPK Waterfront, Abilene", "accommodation": "Apartment minutes from manhattan, Abilene"}, {"day": 3, "current_city": "from Abilene to Amarillo", "transportation": "Self-driving, Duration: 4 hours 10 mins, Distance: 446 km, Cost: 22", "breakfast": "Cakes Degree, Abilene", "attraction": "Cadillac Ranch, Amarillo;Amarillo Botanical Gardens, Amarillo;", "lunch": "The Cinnamon Kitchen, Amarillo", "dinner": "Komachi, Amarillo", "accommodation": "Gramercy Park restful, cozy, sun-filled home, Amarillo"}, {"day": 4, "current_city": "Amarillo", "transportation": "-", "breakfast": "Anand Restaurant, Amarillo", "attraction": "Amarillo Zoo, Amarillo;Don Harrington Discovery Center, Amarillo;", "lunch": "Wood Box Cafe, Amarillo", "dinner": "Sigree Global Grill, Amarillo", "accommodation": "Gramercy Park restful, cozy, sun-filled home, Amarillo"}, {"day": 5, "current_city": "from Amarillo to Lubbock", "transportation": "Self-driving, Duration: 1 hour 47 mins, Distance: 197 km, Cost: 9", "breakfast": "Punjabi Chaap Corner, Amarillo", "attraction": "Buddy Holly Center, Lubbock;National Ranching Heritage Center, Lubbock;", "lunch": "Grand Barbeque Buffet Restaurant, Lubbock", "dinner": "Paris 6 Classique, Lubbock", "accommodation": "Private bedroom in UWS Apartment, Lubbock"}, {"day": 6, "current_city": "Lubbock", "transportation": "-", "breakfast": "3 Squares Diner, Lubbock", "attraction": "American Windmill Museum, Lubbock;Mackenzie Main City Park, Lubbock;", "lunch": "Sultanat, Lubbock", "dinner": "The Town House Cafe, Lubbock", "accommodation": "Private bedroom in UWS Apartment, Lubbock"}, {"day": 7, "current_city": "from Lubbock to Moline", "transportation": "Self-driving, Duration: 15 hours 14 mins, Distance: 1704 km, Cost: 85", "breakfast": "-", "attraction": "-", "lunch": "-", "dinner": "-", "accommodation": "-"}]}]