[{"gpt-4-1106-preview_cot_sole-planning_results": "Travel Plan:\n\nDay 1: March 6, 2022\nCurrent City: from Santa Ana to Helena\nTransportation: Self-driving, from Santa Ana to Helena, Duration: 16 hours 39 mins, Distance: 1,879 km, Cost: $93\nBreakfast: -\nAttraction: -\nLunch: -\nDinner: -\nAccommodation: Entire One bedroom Apartment in Midtown Manhattan, Helena, Price: $402, Room Type: Entire home/apt, Minimum Nights: 5, Maximum Occupancy: 2, Review Rate Number: 1.0\n\nDay 2: March 7, 2022\nCurrent City: Helena\nTransportation: -\nBreakfast: TT Burger, Helena, Average Cost: $63, Cuisines: Tea, Bakery, BBQ, Fast Food, Mediterranean, Aggregate Rating: 4.8\nAttraction: Holter Museum of Art, Helena, Address: 12 E Lawrence St, Helena, MT 59601, USA\nLunch: Elma's Delivers, Helena, Average Cost: $42, Cuisines: Tea, Pizza, BBQ, Indian, Seafood, Aggregate Rating: 3.1\nDinner: Aconchego Carioca, Helena, Average Cost: $58, Cuisines: Tea, American, Desserts, Aggregate Rating: 4.6\nAccommodation: Entire One bedroom Apartment in Midtown Manhattan, Helena, Price: $402\n\nDay 3: March 8, 2022\nCurrent City: from Helena to Billings\nTransportation: Self-driving, from Helena to Billings, Duration: 3 hours 37 mins, Distance: 384 km, Cost: $19\nBreakfast: Cafe Turtle, Helena, Average Cost: $34, Cuisines: Desserts, Fast Food, Cafe, American, Mediterranean, Seafood, Aggregate Rating: 3.5\nAttraction: Great Northern Carousel, Helena, Address: 989 Carousel Way, Helena, MT 59601, USA\nLunch: Just Vada Pav, Helena, Average Cost: $87, Cuisines: Desserts, Pizza, Mexican, Cafe, Seafood, Aggregate Rating: 3.6\nDinner: Holy Smoke, Billings, Average Cost: $38, Cuisines: Tea, Bakery, Cafe, Indian, Seafood, Aggregate Rating: 3.6\nAccommodation: Sunny 2 bd + Private rooftop on best GP street, Billings, Price: $293, Room Type: Entire home/apt, Minimum Nights: 3, Maximum Occupancy: 3, Review Rate Number: 3.0\n\nDay 4: March 9, 2022\nCurrent City: Billings\nTransportation: -\nBreakfast: L'Angoor, Billings, Average Cost: $19, Cuisines: Cafe, Pizza, Indian, Fast Food, Aggregate Rating: 3.5\nAttraction: Western Heritage Center, Billings, Address: 2822 Montana Ave, Billings, MT 59101, USA\nLunch: Hong Kong Express, Billings, Average Cost: $43, Cuisines: BBQ, Mediterranean, Seafood, Aggregate Rating: 3.8\nDinner: Puppychino, Billings, Average Cost: $66, Cuisines: Desserts, Tea, Mexican, Bakery, Cafe, American, Aggregate Rating: 4.4\nAccommodation: Sunny 2 bd + Private rooftop on best GP street, Billings, Price: $293\n\nDay 5: March 10, 2022\nCurrent City: from Billings to Santa Ana\nTransportation: Self-driving, from Billings to Santa Ana, Duration: 18 hours 15 mins, Distance: 1,992 km, Cost: $99\nBreakfast: Tsui Wong, Billings, Average Cost: $40, Cuisines: Desserts, Seafood, Aggregate Rating: 3.8\nAttraction: -\nLunch: -\nDinner: -\nAccommodation: -\n\nTotal Estimated Cost Breakdown:\n- Transportation (Self-driving total): $93 + $19 + $99 = $211\n- Accommodations: $402 (Helena) * 2 nights + $293 (Billings) * 2 nights = $1,390\n- Meals and Attractions (Estimated): $63 (Breakfast Day 2) + $42 (Lunch Day 2) + $58 (Dinner Day 2) + $34 (Breakfast Day 3) + $87 (Lunch Day 3) + $38 (Dinner Day 3) + $19 (Breakfast Day 4) + $43 (Lunch Day 4) + $66 (Dinner Day 4) + $40 (Breakfast Day 5) = $490\n- Total Estimated Cost: $211 (Transportation) + $1,390 (Accommodations) + $490 (Meals and Attractions) = $2,091\n\nRemaining Budget: $3,600 - $2,091 = $1,509\n\nNote: The remaining budget can be used for additional meals, attractions, or any unforeseen expenses. The plan does not include lunch and dinner on Day 1, and lunch and dinner on Day 5 due to travel times. Breakfast on Day 1 is not included as the departure is early in the morning. The cost for attractions is not explicitly mentioned, so it is included in the remaining budget.", "gpt-4-1106-preview_cot_sole-planning_parsed_results": [{"day": 1, "current_city": "from Santa Ana to Helena", "transportation": "Self-driving, from Santa Ana to Helena, Duration: 16 hours 39 mins, Distance: 1,879 km, Cost: 93", "breakfast": "-", "attraction": "-", "lunch": "-", "dinner": "-", "accommodation": "Entire One bedroom Apartment in Midtown Manhattan, Helena"}, {"day": 2, "current_city": "Helena", "transportation": "-", "breakfast": "TT Burger, Helena", "attraction": "Holter Museum of Art, Helena", "lunch": "Elma's Delivers, Helena", "dinner": "Aconchego Carioca, Helena", "accommodation": "Entire One bedroom Apartment in Midtown Manhattan, Helena"}, {"day": 3, "current_city": "from Helena to Billings", "transportation": "Self-driving, from Helena to Billings, Duration: 3 hours 37 mins, Distance: 384 km, Cost: 19", "breakfast": "Cafe Turtle, Helena", "attraction": "Great Northern Carousel, Helena", "lunch": "Just Vada Pav, Helena", "dinner": "Holy Smoke, Billings", "accommodation": "Sunny 2 bd + Private rooftop on best GP street, Billings"}, {"day": 4, "current_city": "Billings", "transportation": "-", "breakfast": "L'Angoor, Billings", "attraction": "Western Heritage Center, Billings", "lunch": "Hong Kong Express, Billings", "dinner": "Puppychino, Billings", "accommodation": "Sunny 2 bd + Private rooftop on best GP street, Billings"}, {"day": 5, "current_city": "from Billings to Santa Ana", "transportation": "Self-driving, from Billings to Santa Ana, Duration: 18 hours 15 mins, Distance: 1,992 km, Cost: 99", "breakfast": "Tsui Wong, Billings", "attraction": "-", "lunch": "-", "dinner": "-", "accommodation": "-"}]}]