[{"gpt-4-1106-preview_cot_sole-planning_results": "Travel Plan:\n\nDay 1: March 3, 2022\nCurrent City: from Atlanta to Bemidji\nTransportation: Taxi from Atlanta to Bemidji, duration: 19 hours 53 mins, distance: 2,166 km, cost: $2,166\nBreakfast: - (Assuming breakfast in Atlanta before departure)\nAttraction: Paul Bunyan & Babe the Blue Ox Statues, Bemidji\nLunch: Pig and Whistle, Bemidji\nDinner: Flying Cakes, Bemidji\nAccommodation: A beautiful Cozy 1 BR Apartment, Bemidji (Allows parties, entire home/apt)\n\nDay 2: March 4, 2022\nCurrent City: Bemidji\nTransportation: -\nBreakfast: The Chocolate Haven, Bemidji\nAttraction: Headwaters Science Center, Bemidji; Diamond Point Park, Bemidji\nLunch: Outback Bar and Grill - Leisure Inn, Bemidji\nDinner: Gastronomica Kitchen & Bar, Bemidji\nAccommodation: A beautiful Cozy 1 BR Apartment, Bemidji\n\nDay 3: March 5, 2022\nCurrent City: from Bemidji to Minneapolis\nTransportation: Flight Number: F3849472, from Bemidji to Minneapolis, Departure Time: 08:21, Arrival Time: 09:23, Price: $86 x 3 = $258\nBreakfast: - (Assuming breakfast in Bemidji before departure)\nAttraction: Minneapolis Sculpture Garden, Minneapolis; Minneapolis Institute of Art, Minneapolis\nLunch: The Cafe, Minneapolis\nDinner: Court Avenue Brewing Company, Minneapolis\nAccommodation: Entire 1 Bedroom Apartment in Midtown Manhattan, Minneapolis (Allows parties, entire home/apt)\n\nDay 4: March 6, 2022\nCurrent City: Minneapolis\nTransportation: -\nBreakfast: Malo, Minneapolis\nAttraction: Mill City Museum, Minneapolis; Mill Ruins Park, Minneapolis\nLunch: Troll Tavern, Minneapolis\nDinner: Monkeypod Kitchen by Merriman, Minneapolis\nAccommodation: Entire 1 Bedroom Apartment in Midtown Manhattan, Minneapolis\n\nDay 5: March 7, 2022\nCurrent City: from Minneapolis to Atlanta\nTransportation: Flight Number: F3780056, from Minneapolis to Atlanta, Departure Time: 08:53, Arrival Time: 12:19, Price: $439 x 3 = $1,317\nBreakfast: - (Assuming breakfast in Minneapolis before departure)\nAttraction: - (No time for attractions due to travel)\nLunch: - (Assuming lunch on the flight or upon arrival in Atlanta)\nDinner: - (Assuming dinner in Atlanta after arrival)\nAccommodation: -\n\nTotal Estimated Costs:\nTaxi to Bemidji: $2,166\nFlights to Minneapolis and back to Atlanta: $258 + $1,317 = $1,575\nAccommodations: $198 x 2 nights (Bemidji) + $107 x 2 nights (Minneapolis) = $610\nMeals and Attractions: Estimated $1,000 (for 3 people over 5 days)\nRemaining Budget: $7,900 - ($2,166 + $1,575 + $610 + $1,000) = $2,549\n\nThe remaining budget can be used for additional meals, attractions, transportation within cities (taxis/ride-sharing), and any unforeseen expenses. Please note that the accommodation prices are per night, and the flight prices are per person. The budget is sufficient for the planned activities and transportation.", "gpt-4-1106-preview_cot_sole-planning_parsed_results": [{"day": 1, "current_city": "from Atlanta to Bemidji", "transportation": "Taxi from Atlanta to Bemidji, Duration: 19 hours 53 mins, Distance: 2166 km, Cost: 2166", "breakfast": "-", "attraction": "Paul Bunyan & Babe the Blue Ox Statues, Bemidji;", "lunch": "Pig and Whistle, Bemidji", "dinner": "Flying Cakes, Bemidji", "accommodation": "A beautiful Cozy 1 BR Apartment, Bemidji"}, {"day": 2, "current_city": "Bemidji", "transportation": "-", "breakfast": "The Chocolate Haven, Bemidji", "attraction": "Headwaters Science Center, Bemidji;Diamond Point Park, Bemidji;", "lunch": "Outback Bar and Grill - Leisure Inn, Bemidji", "dinner": "Gastronomica Kitchen & Bar, Bemidji", "accommodation": "A beautiful Cozy 1 BR Apartment, Bemidji"}, {"day": 3, "current_city": "from Bemidji to Minneapolis", "transportation": "Flight Number: F3849472, from Bemidji to Minneapolis, Departure Time: 08:21, Arrival Time: 09:23, Cost: 258", "breakfast": "-", "attraction": "Minneapolis Sculpture Garden, Minneapolis;Minneapolis Institute of Art, Minneapolis;", "lunch": "The Cafe, Minneapolis", "dinner": "Court Avenue Brewing Company, Minneapolis", "accommodation": "Entire 1 Bedroom Apartment in Midtown Manhattan, Minneapolis"}, {"day": 4, "current_city": "Minneapolis", "transportation": "-", "breakfast": "Malo, Minneapolis", "attraction": "Mill City Museum, Minneapolis;Mill Ruins Park, Minneapolis;", "lunch": "Troll Tavern, Minneapolis", "dinner": "Monkeypod Kitchen by Merriman, Minneapolis", "accommodation": "Entire 1 Bedroom Apartment in Midtown Manhattan, Minneapolis"}, {"day": 5, "current_city": "from Minneapolis to Atlanta", "transportation": "Flight Number: F3780056, from Minneapolis to Atlanta, Departure Time: 08:53, Arrival Time: 12:19, Cost: 1317", "breakfast": "-", "attraction": "-", "lunch": "-", "dinner": "-", "accommodation": "-"}]}]