[{"gpt-4-1106-preview_cot_sole-planning_results": "Travel Plan:\n\nDay 1: March 1, 2022\nCurrent City: from Oklahoma City to Alamosa\nTransportation: Self-driving, Duration: 8 hours 53 mins, Distance: 922 km, Cost: $46\nBreakfast: - (Assuming breakfast in Oklahoma City before departure)\nAttraction: - (Traveling most of the day)\nLunch: - (On the road)\nDinner: Atlanta Highway Seafood Market, Alamosa (Average Cost: $68)\nAccommodation: Comfortable studio suite in midtown Manhattan, Alamosa (Price: $67)\n\nDay 2: March 2, 2022\nCurrent City: Alamosa\nTransportation: -\nBreakfast: Riverwalk Cafe, Alamosa (Average Cost: $97)\nAttraction 1: San Luis Valley Museum, Alamosa\nAttraction 2: Rio Grande Farm Park, Alamosa\nLunch: Cafe LazyMojo, Alamosa (Average Cost: $26)\nAttraction 3: Cole Park, Alamosa\nDinner: The Arena, Alamosa (Average Cost: $85)\nAccommodation: Comfortable studio suite in midtown Manhattan, Alamosa (Price: $67)\n\nDay 3: March 3, 2022\nCurrent City: from Alamosa to Grand Junction\nTransportation: Self-driving, Duration: 4 hours 29 mins, Distance: 396 km, Cost: $19\nBreakfast: - (Assuming breakfast at accommodation)\nAttraction: - (Traveling most of the morning)\nLunch: - (On the road)\nDinner: 2 Dog, Grand Junction (Average Cost: $29)\nAccommodation: NYC Apartment near Central Park!, Grand Junction (Price: $1118)\n\nDay 4: March 4, 2022\nCurrent City: Grand Junction\nTransportation: -\nBreakfast: Austin's BBQ and Oyster Bar, Grand Junction (Average Cost: $15)\nAttraction 1: Museum of the West, Museums of Western Colorado, Grand Junction\nAttraction 2: Eureka! McConnell Science Museum, Grand Junction\nLunch: Cocoa Tree, Grand Junction (Average Cost: $68)\nAttraction 3: Western Colorado Botanical Gardens, Grand Junction\nDinner: Penta Cafe, Grand Junction (Average Cost: $66)\nAccommodation: NYC Apartment near Central Park!, Grand Junction (Price: $1118)\n\nDay 5: March 5, 2022\nCurrent City: from Grand Junction to Durango\nTransportation: Self-driving, Duration: 3 hours 33 mins, Distance: 269 km, Cost: $13\nBreakfast: - (Assuming breakfast at accommodation)\nAttraction: - (Traveling most of the morning)\nLunch: - (On the road)\nDinner: Dub's High on the Hog, Durango (Average Cost: $98)\nAccommodation: Lux 1BR in the heart of NYC Theater district!, Durango (Price: $81)\n\nDay 6: March 6, 2022\nCurrent City: Durango\nTransportation: -\nBreakfast: Samurai Japanese Cuisine & Sushi Bar, Durango (Average Cost: $67)\nAttraction 1: Animas Museum, Durango\nAttraction 2: The Powerhouse, Durango\nLunch: Chickenette, Durango (Average Cost: $31)\nAttraction 3: Durango & Silverton Narrow Gauge Railroad, Durango\nDinner: The Mashal, Durango (Average Cost: $85)\nAccommodation: Lux 1BR in the heart of NYC Theater district!, Durango (Price: $81)\n\nDay 7: March 7, 2022\nCurrent City: from Durango to Oklahoma City\nTransportation: Self-driving, Duration: 11 hours 13 mins, Distance: 1,212 km, Cost: $60\nBreakfast: - (Assuming breakfast at accommodation)\nAttraction: - (Traveling most of the day)\nLunch: - (On the road)\nDinner: - (Assuming arrival in Oklahoma City after dinner time)\nAccommodation: -\n\nTotal Estimated Costs:\nAccommodation: $67 + $67 + $1118 + $1118 + $81 + $81 = $2532\nMeals and Attractions: Assuming an average of $50 per meal and $20 per attraction, for 12 meals and 9 attractions: $600 + $180 = $780\nTransportation: $46 + $19 + $13 + $60 = $138\nTotal: $2532 (Accommodation) + $780 (Meals/Attractions) + $138 (Transportation) = $3450\n\nNote: The total estimated cost exceeds the budget of $3,000. To stay within budget, consider adjusting accommodation choices, meal plans, or reducing the number of paid attractions.", "gpt-4-1106-preview_cot_sole-planning_parsed_results": [{"day": 1, "current_city": "from Oklahoma City to Alamosa", "transportation": "Self-driving, Duration: 8 hours 53 mins, Distance: 922 km, Cost: 46", "breakfast": "-", "attraction": "-", "lunch": "-", "dinner": "Atlanta Highway Seafood Market, Alamosa", "accommodation": "Comfortable studio suite in midtown Manhattan, Alamosa"}, {"day": 2, "current_city": "Alamosa", "transportation": "-", "breakfast": "Riverwalk Cafe, Alamosa", "attraction": "San Luis Valley Museum, Alamosa;Rio Grande Farm Park, Alamosa;Cole Park, Alamosa;", "lunch": "Cafe LazyMojo, Alamosa", "dinner": "The Arena, Alamosa", "accommodation": "Comfortable studio suite in midtown Manhattan, Alamosa"}, {"day": 3, "current_city": "from Alamosa to Grand Junction", "transportation": "Self-driving, Duration: 4 hours 29 mins, Distance: 396 km, Cost: 19", "breakfast": "-", "attraction": "-", "lunch": "-", "dinner": "2 Dog, Grand Junction", "accommodation": "NYC Apartment near Central Park!, Grand Junction"}, {"day": 4, "current_city": "Grand Junction", "transportation": "-", "breakfast": "Austin's BBQ and Oyster Bar, Grand Junction", "attraction": "Museum of the West, Museums of Western Colorado, Grand Junction;Eureka! McConnell Science Museum, Grand Junction;Western Colorado Botanical Gardens, Grand Junction;", "lunch": "Cocoa Tree, Grand Junction", "dinner": "Penta Cafe, Grand Junction", "accommodation": "NYC Apartment near Central Park!, Grand Junction"}, {"day": 5, "current_city": "from Grand Junction to Durango", "transportation": "Self-driving, Duration: 3 hours 33 mins, Distance: 269 km, Cost: 13", "breakfast": "-", "attraction": "-", "lunch": "-", "dinner": "Dub's High on the Hog, Durango", "accommodation": "Lux 1BR in the heart of NYC Theater district!, Durango"}, {"day": 6, "current_city": "Durango", "transportation": "-", "breakfast": "Samurai Japanese Cuisine & Sushi Bar, Durango", "attraction": "Animas Museum, Durango;The Powerhouse, Durango;Durango & Silverton Narrow Gauge Railroad, Durango;", "lunch": "Chickenette, Durango", "dinner": "The Mashal, Durango", "accommodation": "Lux 1BR in the heart of NYC Theater district!, Durango"}, {"day": 7, "current_city": "from Durango to Oklahoma City", "transportation": "Self-driving, Duration: 11 hours 13 mins, Distance: 1,212 km, Cost: 60", "breakfast": "-", "attraction": "-", "lunch": "-", "dinner": "-", "accommodation": "-"}]}]