[{"gpt-4-1106-preview_cot_sole-planning_results": "Travel Plan:\n\nDay 1: March 12, 2022\nCurrent City: from Oakland to Portland\nTransportation: Flight Number: F3860996, from Oakland to Portland, Departure Time: 13:26, Arrival Time: 14:50\nLunch: Osaka, Portland (Italian, BBQ)\nAttraction: Portland Art Museum, Portland\nDinner: Cactus Flower Cafe Navarre, Portland (Mediterranean)\nAccommodation: The ocean view room size 12x14, Portland (Price: $709)\n\nDay 2: March 13, 2022\nCurrent City: Portland\nBreakfast: Barbeque Nation, Portland (Mediterranean)\nAttraction: International Rose Test Garden, Portland\nLunch: Nacho Mamas Burritos, Portland (Italian)\nAttraction: Oregon Zoo, Portland\nDinner: Big Chill, Portland (Italian, BBQ, Seafood)\nAccommodation: The ocean view room size 12x14, Portland (Price: $709)\n\nDay 3: March 14, 2022\nCurrent City: from Portland to Medford\nTransportation: Flight Number: F3861509, from Portland to Medford, Departure Time: 16:10, Arrival Time: 17:12\nBreakfast: Sethi's Delicacy, Portland (Mediterranean)\nAttraction: Lan Su Chinese Garden, Portland\nLunch: Zizo, Portland (Mediterranean)\nDinner: Monarch Restaurant - Holiday Inn Jaipur City Centre, Medford (BBQ, Fast Food)\nAccommodation: The Fountain House, Medford (Price: $178)\n\nDay 4: March 15, 2022\nCurrent City: Medford\nBreakfast: Exotica, Medford (Pizza, BBQ, Seafood)\nAttraction: Medford Railroad Park, Medford\nLunch: NIU by Vikings, Medford (French, BBQ, Desserts, Fast Food)\nAttraction: RoxyAnn Winery, Medford\nDinner: Tandooriwala, Medford (American)\nAccommodation: The Fountain House, Medford (Price: $178)\n\nDay 5: March 16, 2022\nCurrent City: from Medford to Eugene\nTransportation: Self-driving, from Medford to Eugene, duration: 2 hours 40 mins, distance: 268 km, cost: $13\nBreakfast: Desi Tadka, Medford (Mexican, Bakery)\nAttraction: Crater Lake National Park Trust, Medford\nLunch: Calendar's Kitchen by Satish Kaushik, Medford (Chinese, BBQ, Desserts)\nDinner: Ammu's South Indian Restaurant, Eugene (Indian, Desserts)\nAccommodation: Perfect Vacation Rental for Family, Eugene (Price: $1009)\n\nDay 6: March 17, 2022\nCurrent City: Eugene\nBreakfast: Moti Mahal, Eugene (French, Seafood, Desserts, Italian)\nAttraction: Cascades Raptor Center, Eugene\nLunch: Upper Crust, Eugene (Italian, Cafe, Seafood)\nAttraction: Jordan Schnitzer Museum of Art, Eugene\nDinner: Panchwati Rasoi, Eugene (American, Mediterranean)\nAccommodation: Perfect Vacation Rental for Family, Eugene (Price: $1009)\n\nDay 7: March 18, 2022\nCurrent City: from Eugene to Oakland\nTransportation: Flight Number: F4027025, from Eugene to Oakland, Departure Time: 17:20, Arrival Time: 18:42\nBreakfast: The Coffee Bond, Eugene (Cafe, BBQ, Chinese)\nAttraction: Eugene Science Center, Eugene\nLunch: Grub Pub, Eugene (Cafe, Bakery, Pizza)\nDinner: - \nAccommodation: -\n\nTotal Estimated Costs:\nFlights: $152 (Oakland to Portland) + $78 (Portland to Medford) + $110 (Eugene to Oakland) = $340\nAccommodations: $709 x 2 (Portland) + $178 x 2 (Medford) + $1009 x 2 (Eugene) = $3082\nTransportation (Car): $13 (Medford to Eugene)\nMeals and Attractions: Estimated $100 per day per person for 7 days = $1400\nTotal: $340 (Flights) + $3082 (Accommodations) + $13 (Car) + $1400 (Meals/Attractions) = $4835\n\nNote: The total estimated cost slightly exceeds the budget by $335. To stay within budget, consider adjusting meal plans or finding more affordable accommodation options.", "gpt-4-1106-preview_cot_sole-planning_parsed_results": [{"day": 1, "current_city": "from Oakland to Portland", "transportation": "Flight Number: F3860996, from Oakland to Portland, Departure Time: 13:26, Arrival Time: 14:50", "breakfast": "-", "attraction": "Portland Art Museum, Portland;", "lunch": "Osaka, Portland", "dinner": "Cactus Flower Cafe Navarre, Portland", "accommodation": "The ocean view room size 12x14, Portland"}, {"day": 2, "current_city": "Portland", "transportation": "-", "breakfast": "Barbeque Nation, Portland", "attraction": "International Rose Test Garden, Portland;Oregon Zoo, Portland;", "lunch": "Nacho Mamas Burritos, Portland", "dinner": "Big Chill, Portland", "accommodation": "The ocean view room size 12x14, Portland"}, {"day": 3, "current_city": "from Portland to Medford", "transportation": "Flight Number: F3861509, from Portland to Medford, Departure Time: 16:10, Arrival Time: 17:12", "breakfast": "Sethi's Delicacy, Portland", "attraction": "Lan Su Chinese Garden, Portland;", "lunch": "Zizo, Portland", "dinner": "Monarch Restaurant - Holiday Inn Jaipur City Centre, Medford", "accommodation": "The Fountain House, Medford"}, {"day": 4, "current_city": "Medford", "transportation": "-", "breakfast": "Exotica, Medford", "attraction": "Medford Railroad Park, Medford;RoxyAnn Winery, Medford;", "lunch": "NIU by Vikings, Medford", "dinner": "Tandooriwala, Medford", "accommodation": "The Fountain House, Medford"}, {"day": 5, "current_city": "from Medford to Eugene", "transportation": "Self-driving, from Medford to Eugene, duration: 2 hours 40 mins, distance: 268 km, Cost: 13", "breakfast": "Desi Tadka, Medford", "attraction": "Crater Lake National Park Trust, Medford;", "lunch": "Calendar's Kitchen by Satish Kaushik, Medford", "dinner": "Ammu's South Indian Restaurant, Eugene", "accommodation": "Perfect Vacation Rental for Family, Eugene"}, {"day": 6, "current_city": "Eugene", "transportation": "-", "breakfast": "Moti Mahal, Eugene", "attraction": "Cascades Raptor Center, Eugene;Jordan Schnitzer Museum of Art, Eugene;", "lunch": "Upper Crust, Eugene", "dinner": "Panchwati Rasoi, Eugene", "accommodation": "Perfect Vacation Rental for Family, Eugene"}, {"day": 7, "current_city": "from Eugene to Oakland", "transportation": "Flight Number: F4027025, from Eugene to Oakland, Departure Time: 17:20, Arrival Time: 18:42", "breakfast": "The Coffee Bond, Eugene", "attraction": "Eugene Science Center, Eugene;", "lunch": "Grub Pub, Eugene", "dinner": "-", "accommodation": "-"}]}]