[{"gpt-4-1106-preview_cot_sole-planning_results": "Travel Plan:\n\nDay 1: March 15, 2022\nCurrent City: from Washington to Orlando\nTransportation: Flight Number: F3755232, from Washington to Orlando, Departure Time: 06:54, Arrival Time: 09:10\nBreakfast: - (Assuming breakfast will be had before the flight or during the flight if provided)\nAttraction: The Wheel at ICON Park, Orlando\nLunch: Fuji Japanese Steakhouse, Orlando\nDinner: Turquoise Villa, Orlando\nAccommodation: Sixth Ave Chelsea, Studio Serviced Apartment, Orlando\n\nDay 2: March 16, 2022\nCurrent City: Orlando\nTransportation: -\nBreakfast: Indochi Cafe & Restaurant, Orlando\nAttraction: Universal Orlando Resort, Orlando; The Wizarding World of Harry Potter - Diagon Alley, Orlando\nLunch: The Tandoori Times, Orlando\nDinner: Crust N Cakes, Orlando\nAccommodation: Sixth Ave Chelsea, Studio Serviced Apartment, Orlando\n\nDay 3: March 17, 2022\nCurrent City: from Orlando to Washington\nTransportation: Flight Number: F3910463, from Orlando to Washington, Departure Time: 06:59, Arrival Time: 09:01\nBreakfast: - (Assuming breakfast will be had before the flight or during the flight if provided)\nAttraction: Orlando Science Center, Orlando (if time permits before the flight)\nLunch: - (Assuming lunch will be had during the flight if provided or after arrival in Washington)\nDinner: - (After returning to Washington)\nAccommodation: -\n\nTotal Estimated Costs:\nFlights: $153 (F3755232) + $156 (F3910463) = $309 per person x 2 = $618\nAccommodation: $70 per night x 2 nights = $140\nMeals and Attractions: Assuming an average of $50 per meal per person and $100 for attraction tickets per person per day, the total for meals and attractions would be $600.\nMiscellaneous (transportation within the city, etc.): $200\n\nTotal Estimated Budget Used: $618 (flights) + $140 (accommodation) + $600 (meals and attractions) + $200 (miscellaneous) = $1558\n\nRemaining Budget: $2000 - $1558 = $442\n\nNote: The remaining budget can be used for additional meals, attractions, or any unforeseen expenses. The plan assumes that the prices for meals and attractions have not significantly changed since the provided data. The flight times and prices are based on the provided data, and the accommodation choice is based on the preference for a private room and the budget constraint.", "gpt-4-1106-preview_cot_sole-planning_parsed_results": [{"day": 1, "current_city": "from Washington to Orlando", "transportation": "Flight Number: F3755232, from Washington to Orlando, Departure Time: 06:54, Arrival Time: 09:10", "breakfast": "-", "attraction": "The Wheel at ICON Park, Orlando", "lunch": "Fuji Japanese Steakhouse, Orlando", "dinner": "Turquoise Villa, Orlando", "accommodation": "Sixth Ave Chelsea, Studio Serviced Apartment, Orlando"}, {"day": 2, "current_city": "Orlando", "transportation": "-", "breakfast": "Indochi Cafe & Restaurant, Orlando", "attraction": "Universal Orlando Resort, Orlando; The Wizarding World of Harry Potter - Diagon Alley, Orlando", "lunch": "The Tandoori Times, Orlando", "dinner": "Crust N Cakes, Orlando", "accommodation": "Sixth Ave Chelsea, Studio Serviced Apartment, Orlando"}, {"day": 3, "current_city": "from Orlando to Washington", "transportation": "Flight Number: F3910463, from Orlando to Washington, Departure Time: 06:59, Arrival Time: 09:01", "breakfast": "-", "attraction": "Orlando Science Center, Orlando", "lunch": "-", "dinner": "-", "accommodation": "-"}]}]