[{"gpt-4-1106-preview_cot_sole-planning_results": "Travel Plan:\n\nDay 1: March 1, 2022\nCurrent City: from San Jose to Boise\nTransportation: Flight Number: F3937562, from San Jose to Boise, Departure Time: 14:01, Arrival Time: 16:28\nDinner: Dhaba By Claridges, Boise\nAccommodation: Modern & Cozy 2 BR Private Apartment in Brooklyn, Boise\n\nDay 2: March 2, 2022\nCurrent City: Boise\nBreakfast: Gopala Hari, Boise\nAttraction: Zoo Boise, Boise; Idaho State Museum, Boise\nLunch: The Brewhouse, Boise\nAttraction: Old Idaho Penitentiary Site, Boise; Idaho Botanical Garden, Boise\nDinner: 19 Flavours Biryani, Boise\nAccommodation: Modern & Cozy 2 BR Private Apartment in Brooklyn, Boise\n\nDay 3: March 3, 2022\nCurrent City: from Boise to Idaho Falls\nTransportation: Self-driving, from Boise to Idaho Falls, duration: 4 hours 1 min, distance: 451 km, cost: 22\nBreakfast: Express Kitchen, Boise\nAttraction: Museum of Idaho, Idaho Falls; Idaho Falls River Walk - Greenbelt Trail, Idaho Falls\nLunch: Taste of China, Idaho Falls\nAttraction: Idaho Falls Zoo at Tautphaus Park, Idaho Falls; Japanese Friendship Garden, Idaho Falls\nDinner: Dhuaan, Idaho Falls\nAccommodation: Sunny & Spacious 2 bdrm apt, Idaho Falls\n\nDay 4: March 4, 2022\nCurrent City: Idaho Falls\nBreakfast: Shiv Restaurant, Idaho Falls\nAttraction: Giant Eagle Waterfall Nest, Idaho Falls; Tautphaus Park, Idaho Falls\nLunch: Karim's, Idaho Falls\nAttraction: Collectors Corner Museum, Idaho Falls; East Idaho Aquarium, Idaho Falls\nDinner: The Fusion Food Stand, Idaho Falls\nAccommodation: Sunny & Spacious 2 bdrm apt, Idaho Falls\n\nDay 5: March 5, 2022\nCurrent City: from Idaho Falls to San Jose\nTransportation: Self-driving, from Idaho Falls to San Jose, duration: 12 hours 56 mins, distance: 1,388 km, cost: 69\nBreakfast: Gupta's Vegetarian Paradise, Idaho Falls\n- (No further planning required as the group will be en route to San Jose)\n\nTotal Estimated Costs:\nFlights: $216 x 7 = $1,512\nAccommodation: (Boise) $843 x 2 nights = $1,686 + (Idaho Falls) $914 x 2 nights = $1,828\nTransportation (Self-driving): $22 + $69 = $91\nMeals and Attractions: Estimated $8,000 (for 7 people over 5 days)\nTotal: $1,512 + $1,686 + $1,828 + $91 + $8,000 = $13,117\n\nThis plan leaves a buffer of $783 for additional expenses such as souvenirs, snacks, and any unforeseen costs.", "gpt-4-1106-preview_cot_sole-planning_parsed_results": [{"day": 1, "current_city": "from San Jose to Boise", "transportation": "Flight Number: F3937562, from San Jose to Boise, Departure Time: 14:01, Arrival Time: 16:28", "breakfast": "-", "attraction": "-", "lunch": "-", "dinner": "Dhaba By Claridges, Boise", "accommodation": "Modern & Cozy 2 BR Private Apartment in Brooklyn, Boise"}, {"day": 2, "current_city": "Boise", "transportation": "-", "breakfast": "Gopala Hari, Boise", "attraction": "Zoo Boise, Boise;Idaho State Museum, Boise;Old Idaho Penitentiary Site, Boise;Idaho Botanical Garden, Boise;", "lunch": "The Brewhouse, Boise", "dinner": "19 Flavours Biryani, Boise", "accommodation": "Modern & Cozy 2 BR Private Apartment in Brooklyn, Boise"}, {"day": 3, "current_city": "from Boise to Idaho Falls", "transportation": "Self-driving, from Boise to Idaho Falls, duration: 4 hours 1 min, distance: 451 km, Cost: 22", "breakfast": "Express Kitchen, Boise", "attraction": "Museum of Idaho, Idaho Falls;Idaho Falls River Walk - Greenbelt Trail, Idaho Falls;Idaho Falls Zoo at Tautphaus Park, Idaho Falls;Japanese Friendship Garden, Idaho Falls;", "lunch": "Taste of China, Idaho Falls", "dinner": "Dhuaan, Idaho Falls", "accommodation": "Sunny & Spacious 2 bdrm apt, Idaho Falls"}, {"day": 4, "current_city": "Idaho Falls", "transportation": "-", "breakfast": "Shiv Restaurant, Idaho Falls", "attraction": "Giant Eagle Waterfall Nest, Idaho Falls;Tautphaus Park, Idaho Falls;Collectors Corner Museum, Idaho Falls;East Idaho Aquarium, Idaho Falls;", "lunch": "Karim's, Idaho Falls", "dinner": "The Fusion Food Stand, Idaho Falls", "accommodation": "Sunny & Spacious 2 bdrm apt, Idaho Falls"}, {"day": 5, "current_city": "from Idaho Falls to San Jose", "transportation": "Self-driving, from Idaho Falls to San Jose, duration: 12 hours 56 mins, distance: 1,388 km, Cost: 69", "breakfast": "Gupta's Vegetarian Paradise, Idaho Falls", "attraction": "-", "lunch": "-", "dinner": "-", "accommodation": "-"}]}]