[{"gpt-4-1106-preview_cot_sole-planning_results": "Travel Plan:\n\nDay 1: March 10, 2022\nCurrent City: from Seattle to Dallas\nTransportation: Flight Number: F3669219, from Seattle to Dallas, Departure Time: 07:42, Arrival Time: 13:36\nBreakfast: - (Assuming breakfast will be in Seattle or on the flight)\nAttraction: The Sixth Floor Museum at Dealey Plaza, Dallas\nLunch: Coconuts Fish Cafe, Dallas\nDinner: 1918 Bistro & Grill, Dallas\nAccommodation: Luxury Williamsburg duplex, private roof terrace, Dallas (Allows parties)\n\nDay 2: March 11, 2022\nCurrent City: Dallas\nTransportation: -\nBreakfast: Yanki Sizzlers, Dallas\nAttraction: The Dallas World Aquarium, Dallas; Reunion Tower, Dallas\nLunch: Aravali Owls, Dallas\nDinner: Kebab Xpress, Dallas\nAccommodation: Luxury Williamsburg duplex, private roof terrace, Dallas (Allows parties)\n\nDay 3: March 12, 2022\nCurrent City: from Dallas to Houston\nTransportation: Flight Number: F3667553, from Dallas to Houston, Departure Time: 07:06, Arrival Time: 08:21\nBreakfast: - (Assuming breakfast will be in Dallas or on the flight)\nAttraction: Space Center Houston, Houston; Houston Museum of Natural Science, Houston\nLunch: Jalapenos, Houston\nDinner: Matchbox, Houston\nAccommodation: Spacious room in front of prospect park, Houston (Allows parties)\n\nDay 4: March 13, 2022\nCurrent City: Houston\nTransportation: -\nBreakfast: Super Bakery, Houston\nAttraction: Water Wall, Houston; Houston Zoo, Houston\nLunch: Earthen Spices, Houston\nDinner: The BrewMaster - The Mix Fine Dine, Houston\nAccommodation: Spacious room in front of prospect park, Houston (Allows parties)\n\nDay 5: March 14, 2022\nCurrent City: from Houston to San Antonio\nTransportation: Flight Number: F3877522, from Houston to San Antonio, Departure Time: 16:34, Arrival Time: 17:21\nBreakfast: Vinayaka Mylari, Houston\nAttraction: Hermann Park, Houston; Gerald D. Hines Waterwall Park, Houston\nLunch: Pebble Street, Houston\nDinner: - (Assuming dinner will be in San Antonio)\nAccommodation: Large apt in prime carol gardens, San Antonio (Allows parties)\n\nDay 6: March 15, 2022\nCurrent City: San Antonio\nTransportation: -\nBreakfast: Cafe Le Rue @ The Landings, San Antonio\nAttraction: San Antonio River Walk, San Antonio; The Alamo, San Antonio\nLunch: Martin's BBQ, San Antonio\nDinner: Barbeque Nation, San Antonio\nAccommodation: Large apt in prime carol gardens, San Antonio (Allows parties)\n\nDay 7: March 16, 2022\nCurrent City: from San Antonio to Seattle\nTransportation: Flight Number: F3744881, from San Antonio to Seattle, Departure Time: 18:35, Arrival Time: 20:58\nBreakfast: Cream Stone, San Antonio\nAttraction: San Antonio Museum of Art (SAMA), San Antonio; San Antonio Botanical Garden, San Antonio\nLunch: Pita Pit, San Antonio\nDinner: - (Assuming dinner will be on the flight or after arrival in Seattle)\nAccommodation: -\n\nPlease note that the accommodation options selected allow for parties as requested. The restaurants and attractions were chosen based on the provided data, ensuring a diverse experience each day. The flight times were selected to maximize daytime activities in each city. The budget has been considered, but specific costs for meals, attractions, and other incidentals have not been provided, so please ensure that the total expenses do not exceed the $11,000 budget.", "gpt-4-1106-preview_cot_sole-planning_parsed_results": [{"day": 1, "current_city": "from Seattle to Dallas", "transportation": "Flight Number: F3669219, from Seattle to Dallas, Departure Time: 07:42, Arrival Time: 13:36", "breakfast": "-", "attraction": "The Sixth Floor Museum at Dealey Plaza, Dallas", "lunch": "Coconuts Fish Cafe, Dallas", "dinner": "1918 Bistro & Grill, Dallas", "accommodation": "Luxury Williamsburg duplex, private roof terrace, Dallas"}, {"day": 2, "current_city": "Dallas", "transportation": "-", "breakfast": "Yanki Sizzlers, Dallas", "attraction": "The Dallas World Aquarium, Dallas;Reunion Tower, Dallas", "lunch": "Aravali Owls, Dallas", "dinner": "Kebab Xpress, Dallas", "accommodation": "Luxury Williamsburg duplex, private roof terrace, Dallas"}, {"day": 3, "current_city": "from Dallas to Houston", "transportation": "Flight Number: F3667553, from Dallas to Houston, Departure Time: 07:06, Arrival Time: 08:21", "breakfast": "-", "attraction": "Space Center Houston, Houston;Houston Museum of Natural Science, Houston", "lunch": "Jalapenos, Houston", "dinner": "Matchbox, Houston", "accommodation": "Spacious room in front of prospect park, Houston"}, {"day": 4, "current_city": "Houston", "transportation": "-", "breakfast": "Super Bakery, Houston", "attraction": "Water Wall, Houston;Houston Zoo, Houston", "lunch": "Earthen Spices, Houston", "dinner": "The BrewMaster - The Mix Fine Dine, Houston", "accommodation": "Spacious room in front of prospect park, Houston"}, {"day": 5, "current_city": "from Houston to San Antonio", "transportation": "Flight Number: F3877522, from Houston to San Antonio, Departure Time: 16:34, Arrival Time: 17:21", "breakfast": "Vinayaka Mylari, Houston", "attraction": "Hermann Park, Houston;Gerald D. Hines Waterwall Park, Houston", "lunch": "Pebble Street, Houston", "dinner": "-", "accommodation": "Large apt in prime carol gardens, San Antonio"}, {"day": 6, "current_city": "San Antonio", "transportation": "-", "breakfast": "Cafe Le Rue @ The Landings, San Antonio", "attraction": "San Antonio River Walk, San Antonio;The Alamo, San Antonio", "lunch": "Martin's BBQ, San Antonio", "dinner": "Barbeque Nation, San Antonio", "accommodation": "Large apt in prime carol gardens, San Antonio"}, {"day": 7, "current_city": "from San Antonio to Seattle", "transportation": "Flight Number: F3744881, from San Antonio to Seattle, Departure Time: 18:35, Arrival Time: 20:58", "breakfast": "Cream Stone, San Antonio", "attraction": "San Antonio Museum of Art (SAMA), San Antonio;San Antonio Botanical Garden, San Antonio", "lunch": "Pita Pit, San Antonio", "dinner": "-", "accommodation": "-"}]}]