[{"gpt-4-1106-preview_cot_sole-planning_results": "Travel Plan:\n\nDay 1: March 15, 2022\nCurrent City: from New York to New Orleans\nTransportation: Flight Number: F3549542, from New York to New Orleans, Departure Time: 10:04, Arrival Time: 12:26\nBreakfast: - (Assuming breakfast is had before the flight)\nAttraction: New Orleans City Park, New Orleans\nLunch: Jimmy's Pancake House, New Orleans\nAttraction: The National WWII Museum, New Orleans\nDinner: Shenanigan's Irish Pub, New Orleans\nAccommodation: Cozy in Cobble Hill, New Orleans (Smoking is not mentioned as prohibited)\n\nDay 2: March 16, 2022\nCurrent City: New Orleans\nBreakfast: The Fish House, New Orleans\nAttraction: Audubon Aquarium, New Orleans\nLunch: Town Table Restaurant, New Orleans\nAttraction: Mardi Gras World, New Orleans\nDinner: Yeti - The Himalayan Kitchen, New Orleans\nAccommodation: Cozy in Cobble Hill, New Orleans\n\nDay 3: March 17, 2022\nCurrent City: from New Orleans to Baton Rouge\nTransportation: Taxi, from New Orleans to Baton Rouge, Departure Time: 09:00, Arrival Time: 10:17 (approximate times)\nBreakfast: - (Assuming breakfast is had before departure)\nAttraction: Louisiana's Old State Capitol, Baton Rouge\nLunch: Taste of India, Baton Rouge\nAttraction: USS KIDD Veterans Museum, Baton Rouge\nDinner: Bluebird Diner, Baton Rouge\nAccommodation: Spacious 1 Bedroom in Historic Brownstone, Baton Rouge (Smoking is not mentioned as prohibited)\n\nDay 4: March 18, 2022\nCurrent City: Baton Rouge\nBreakfast: Jimmy Jack's Rib Shack, Baton Rouge\nAttraction: BREC's Baton Rouge Zoo, Baton Rouge\nLunch: Tursi's Latin King, Baton Rouge\nAttraction: Louisiana Art & Science Museum, Baton Rouge\nDinner: Pizza Di Rocco, Baton Rouge\nAccommodation: Spacious 1 Bedroom in Historic Brownstone, Baton Rouge\n\nDay 5: March 19, 2022\nCurrent City: from Baton Rouge to New York\nTransportation: Self-driving, from Baton Rouge to New York, Departure Time: 06:00, Arrival Time: 02:05 (next day, approximate times)\nBreakfast: - (Assuming breakfast is had before departure)\nAttraction: - (No attractions planned due to the long drive back)\nLunch: - (On the road)\nDinner: - (On the road)\nAccommodation: -\n\nPlease note that the accommodation options listed do not explicitly state that smoking is allowed. It is recommended to contact the property owners directly to confirm their smoking policy. Additionally, the transportation times are approximate and should be confirmed with the service providers. The budget has been considered in the planning, but it is advisable to double-check all prices as they are subject to change and may vary depending on availability and booking time.", "gpt-4-1106-preview_cot_sole-planning_parsed_results": [{"day": 1, "current_city": "from New York to New Orleans", "transportation": "Flight Number: F3549542, from New York to New Orleans, Departure Time: 10:04, Arrival Time: 12:26", "breakfast": "-", "attraction": "New Orleans City Park, New Orleans;The National WWII Museum, New Orleans;", "lunch": "Jimmy's Pancake House, New Orleans", "dinner": "Shenanigan's Irish Pub, New Orleans", "accommodation": "Cozy in Cobble Hill, New Orleans"}, {"day": 2, "current_city": "New Orleans", "transportation": "-", "breakfast": "The Fish House, New Orleans", "attraction": "Audubon Aquarium, New Orleans;Mardi Gras World, New Orleans;", "lunch": "Town Table Restaurant, New Orleans", "dinner": "Yeti - The Himalayan Kitchen, New Orleans", "accommodation": "Cozy in Cobble Hill, New Orleans"}, {"day": 3, "current_city": "from New Orleans to Baton Rouge", "transportation": "Taxi, from New Orleans to Baton Rouge, Departure Time: 09:00, Arrival Time: 10:17", "breakfast": "-", "attraction": "Louisiana's Old State Capitol, Baton Rouge;USS KIDD Veterans Museum, Baton Rouge;", "lunch": "Taste of India, Baton Rouge", "dinner": "Bluebird Diner, Baton Rouge", "accommodation": "Spacious 1 Bedroom in Historic Brownstone, Baton Rouge"}, {"day": 4, "current_city": "Baton Rouge", "transportation": "-", "breakfast": "Jimmy Jack's Rib Shack, Baton Rouge", "attraction": "BREC's Baton Rouge Zoo, Baton Rouge;Louisiana Art & Science Museum, Baton Rouge;", "lunch": "Tursi's Latin King, Baton Rouge", "dinner": "Pizza Di Rocco, Baton Rouge", "accommodation": "Spacious 1 Bedroom in Historic Brownstone, Baton Rouge"}, {"day": 5, "current_city": "from Baton Rouge to New York", "transportation": "Self-driving, from Baton Rouge to New York, Departure Time: 06:00, Arrival Time: 02:05", "breakfast": "-", "attraction": "-", "lunch": "-", "dinner": "-", "accommodation": "-"}]}]